Workbook
Name _LEX1955: '[1]summary-targets'!#REF!
Name _LEX1955: '[1]summary-targets'!#REF!
Name _LEX1975: '[1]summary-targets'!#REF!
Name _LEX1975: '[1]summary-targets'!#REF!
Name _LEX2025: '[1]summary-targets'!#REF!
Name _LEX2025: '[1]summary-targets'!#REF!
Name _reg98: [2]whoreg!#REF!
Name _reg98: [2]whoreg!#REF!
Name _resul: '[3]slop-inter'!$A$45:$AG$48
Name _yellowF: #REF!
Name _yellowF: #REF!
Name _yellowM: #REF!
Name _yellowM: #REF!
Name data: #REF!
Name data: #REF!
Name Dist_Vars_byName: '[4]District Level Variables'!$B$1:$BD$201
Name eagd: #REF!
Name eagd: #REF!
Name Exchange_PPP: 'PPP Exchange Rates'!$1:$1048576
Name Exchange_Standard: 'Standard Exchange Rates'!$1:$1048576
Name fda: #REF!
Name fda: #REF!
Name fdae: [2]whoregeco!#REF!
Name fdae: [2]whoregeco!#REF!
Name fdageas: #REF!
Name fdageas: #REF!
Name fdas: #REF!
Name fdas: #REF!
Name GBDageD95: [5]Deaths!$A$1:$T$643
Name geasd: #REF!
Name geasd: #REF!
Name home: '[3]slop-inter'!$D$1:$F$1
Name inflation: '[6]Inflation Rates'!$C$1:$XFD$219
Name inflation: '[6]Inflation Rates'!$C$1:$XFD$219
Name inflation: 'Inflation Rates'!$C$1:$XFD$219
Name label: [3]lx!$D$1788:$E$1825
Name PA: #REF!
Name PA: #REF!
Name pop: #REF!
Name pop: #REF!
Name ppp: [7]Setup!#REF!
Name ppp: [7]Setup!#REF!
Name PrintAr2: #REF!
Name PrintAr2: #REF!
Name regeco98: [2]whoregeco!#REF!
Name regeco98: [2]whoregeco!#REF!
Name SlopeF: #REF!
Name SlopeF: #REF!
Name slopeintercept: '[8]intercept+slope projections'!$A$3:$H$29
Name slopeM: #REF!
Name slopeM: #REF!
Name sort1: '[8]intercept+slope projections'!$A$3:$B$29
Name sort2: '[8]intercept+slope projections'!$D$3:$F$29
Name sort3: '[8]intercept+slope projections'!$E$3:$F$29
Name sort4: '[8]intercept+slope projections'!$G$3:$H$29
Name SPSS: #REF!
Name SPSS: #REF!
Name year: '[8]intercept+slope projections'!$A$3:$A$29
Name yll: [7]Setup!#REF!
Name yll: [7]Setup!#REF!

Sheet Overview of Programs
A1: # | B1: Study Name | C1: Status | D1: Lead | E1: First QC | F1: Revision | G1: Second QC | H1: Iteration with PI | I1: Checked by Cornerstone | J1: Intervention | K1: PIs | L1: Impact (SD) | M1: Test Subjects (bold if significant) | N1: Impact source | O1: Country | P1: Region | Q1: PI CE Estimates | R1: Link to Eval Summary | S1: Link To Paper | T1: Notes | U1: Academic Citation
B4: color code: | C4: Not to be used
C5: Awaiting PI/RA response
C6: Initial calculations complete/In Progress
C7: Complete
C8: On hold

Sheet Comparisons
A2: I. Details of the Analysis
B4: Outcome Measure | C4: Additional Years of Education Induced, per $100 Spent
B5: Year of Analysis | C5: 2015
B6: Discount Rate | C6: 0.1
A9: II. Cost-Effectiveness Results and Sensitivity Analyses
B11: Cost-Effectiveness Graph
B12: Program | C12: Cost per Year of Student Attendance gained (Standard) | D12: Student Attendance Years per $100 (Standard) | E12: Student Attendance Years per $100 (PPP)
A13: 1
A14: 2
A15: 3
A16: 4
A17: 5
A18: 6
A19: 7
A20: 8
A21: 9
A22: 10
A25: III. Inflation and Exchange Rates Used in Calculations
A27: Year | B27: United States | C27: Country 1 | E27: Country 2 | G27: Country 3 | I27: Country 4 | K27: Country 5 | M27: Country 6 | O27: Country 7 | Q27: Country 8
B28: Inflation Rate | C28: Standard Exch. Rate | D28: PPP Exch. Rate | E28: Standard Exch. Rate | F28: PPP Exch. Rate | G28: Standard Exch. Rate | H28: PPP Exch. Rate | I28: Standard Exch. Rate | J28: PPP Exch. Rate | K28: Standard Exch. Rate | L28: PPP Exch. Rate | M28: Standard Exch. Rate | N28: PPP Exch. Rate | O28: Standard Exch. Rate | P28: PPP Exch. Rate | Q28: Standard Exch. Rate | R28: PPP Exch. Rate
A29: 1997
A30: 1998 | B30: 0.0113
A31: 1999 | B31: 0.0147
A32: 2000 | B32: 0.0216
A33: 2001 | B33: 0.0227
A34: 2002 | B34: 0.0162
A35: 2003 | B35: 0.0216
A36: 2004 | B36: 0.0283
A37: 2005 | B37: 0.0333
A38: 2006 | B38: 0.0325
A39: 2007 | B39: 0.0343
A40: 2008 | B40: 0.0219
A41: 2009 | B41: 0.0092
A42: 2010

Sheet 0 - Total Costs
A1: Study Title | B1: HIM
A2: Authors | B2: Banerjee, Chandrashekhar, Duflo, Dalpath, Floretta, Jackson, Kannan, Schrimpf, and Shrestha
A3: Publication Date
A4: Location | B4: Haryana, India
A5: Base Year | B5: 2016
A6: Year of Analysis | B6: 2018
A7: Outcome Measure | B7: Additional fully immunized children
A9: Demographics | B9: Number | C9: Unit | F9: Trainings | G9: Number | H9: Unit | L9: Gossips Identification | M9: Number | N9: Unit | P9: Implementation Costs: Meetings | Q9: Number | R9: Unit | T9: Government Costs | U9: Number | V9: Unit
A10: Intervention Duration | B10: 15 | C10: months | F10: Printing | G10: 125 | H10: 2017 INR | L10: Surveyors | M10: 426 | N10: man-days | P10: Lodging for meetings (launch + 6-month) | Q10: =50000+40000 -> 90000 | R10: 2017 INR | T10: ASHA incentives for mobilization | U10: 100 | V10: 2017 INR
A11: Months in 2017 | B11: 12 | C11: months | F11: Lunch and refreshments | G11: 7534 | H11: 2017 INR | L11: Monitors | M11: 133 | N11: man-days | P11: Transportation to monthly district meetings | Q11: 184011 | R11: 2017 INR | T11: ASHA incentives for FIC | U11: 150 | V11: 2017 INR
A12: Months in 2018 | B12: =B10-B11 -> 3 | C12: months | F12: J-PAL trainer lodging | G12: 15900 | H12: 2017 INR | L12: Field Manager | M12: 72 | N12: man-days | P12: Transportation to state-level meetings | Q12: 100200 | R12: 2017 INR | T12: AVD | U12: 75 | V12: 2017 INR
A13: Proportion of costs in 2017 | B13: =B11/B10 -> 0.8 | C13: percent | F13: J-PAL trainer per-diem | G13: 5899.98 | H13: 2017 INR | L13: Project Associate | M13: 57.8683 | N13: man-days | P13: Per-diem allowance (high level) | Q13: 800 | R13: 2017 INR | T13: Cost per BCG vaccine | U13: 3.25 | V13: 2017 INR
A14: Proportion of costs in 2018 | B14: =1-B13 -> 0.2 | C14: percent | F14: J-PAL transportation | G14: =5100+16900 -> 22000 | H14: 2017 INR | L14: Surveyor daily wage | M14: 350 | N14: 2017 INR | P14: Per-diem allowance (low level) | Q14: 300 | R14: 2017 INR | T14: Cost per Penta vaccines | U14: 137.15 | V14: 2017 INR
A15: Discount Rate | B15: =Comparisons!C6 -> 0.1 | C15: percent | F15: J-PAL staff lodging | G15: 1800 | H15: 2017 INR | L15: Monitors daily wage | M15: 525 | N15: 2017 INR | P15: Number of high level per-diem allowances | Q15: =70+1+1+2 -> 74 | R15: allowances | T15: Cost per measles vaccine | U15: 32.5 | V15: 2017 INR
A16: US-Local Exchange Rate, 2016 Standard | B16: 67.195 | C16: Rs/USD | F16: J-PAL staff transportation | G16: 14231.98 | H16: 2017 INR | L16: Field Manager daily wage | M16: 600 | N16: 2017 INR | P16: Number of low level per-diem allowances | Q16: 7 | R16: allowances | T16: Cost per 5 mL syringe | U16: 1.95 | V16: 2017 INR
A17: US-Local Exchange Rate, 2017 Standard | B17: 65.122 | C17: Rs/USD | F17: J-PAL staff per-diem | G17: =2263.63*22 -> 49799.86 | H17: 2017 INR | L17: Project Associate daily wage | M17: 896 | N17: 2017 INR | P17: Per-diem for launch + 6-month meetings | Q17: =1600*(2+5) -> 11200 | R17: 2017 INR | T17: Cost per 0.5 mL syringe | U17: 1.95 | V17: 2017 INR
A18: US-Local Exchange Rate, 2018, Standard | B18: 68.389 | C18: Rs/USD | F18: Number of trainers (Staff) | G18: 1 | H18: people | L18: Travel | M18: 94900 | N18: 2017 INR | T18: Cost per 0.1 mL syringe | U18: 2.6 | V18: 2017 INR
A19: Villages in entire sample | B19: 2360 | C19: villages | F19: Number of participants (Staff) | G19: 24 | H19: people | L19: Event space | M19: 1500 | N19: 2017 INR | T19: Number of BCG vaccines | U19: 24163 | V19: vaccines
A20: Total number of ANMs | B20: 1397 | C20: ANMs | F20: Master training materials | G20: =20526+42000+1400 -> 63926 | H20: 2017 INR | T20: Number of Penta vaccines | U20: =54873+52103+49026 -> 156002 | V20: vaccines
A21: Average US inflation, 2017 to 2018 | B21: 0.018 | C21: percent | F21: Master training food/bev | G21: 20934 | H21: 2017 INR | L21: Implementation Costs: Materials | M21: Number | N21: Unit | P21: Implementation Costs: Software | Q21: Number | R21: Unit | T21: Number of measles vaccines | U21: 49439 | V21: vaccines
A22: Average US inflation, 2016 to 2017 | B22: 0.022 | C22: percent | F22: Master training trainer lodging | G22: =7458.66666666666*6 -> 44752 | H22: 2017 INR | L22: Tablets + covers | M22: =7850+255+125 -> 8230 | N22: 2017 INR | P22: SANA software | Q22: 2026700 | R22: 2017 INR | T22: Number of 5 mL syringes | U22: 13535 | V22: syringes
A23: Average US inflation, 2016 to 2018 | B23: =AVERAGE(B21:B22) -> 0.02 | C23: percent | F23: Master training trainer transport | G23: =8400+12000 -> 20400 | H23: 2017 INR | L23: Bar codes (cost per roll) | M23: 175 | N23: 2017 INR | P23: Labor to develop software | Q23: 4200 | R23: 2017 INR | T23: Number of 0.5 mL syringes | U23: 225985 | V23: syringes
A24: Program Administration | B24: Number | C24: Unit | F24: Master training trainer per-diem | G24: 28800 | H24: 2017 INR | L24: Number of tablets | M24: 1200 | N24: tablets | P24: Server cost: SANA | Q24: 224428 | R24: 2017 INR | T24: Number of 0.1 mL syringes | U24: 26579 | V24: syringes
A25: Total field office rent and costs | B25: =628900+44932+61375+76400+13452+77750 -> 902809 | C25: 2017 INR | F25: Master training facilitator per-diem | G25: 14400 | H25: 2017 INR | L25: Number of bar codes | M25: 1676 | N25: rolls | P25: Server cost: SurveyCTO | Q25: 232960 | R25: 2017 INR | T25: ASHA incentives for mobilization | U25: =2622665/100 -> 26226.65 | V25: incentives
A26: Staff costs | B26: =17523362.8+2628504.42 -> 20151867 | C26: 2017 INR | F26: Trainee lodging | G26: 9150 | H26: 2017 INR | L26: ANM posters | M26: 16.576 | N26: 2017 INR | T26: ASHA incentives for FIC | U26: =6142800/150 -> 40952 | V26: incentives
A27: Intern daily salary | B27: 500 | C27: 2017 INR | F27: Trainee transport | G27: 61000 | H27: 2017 INR | L27: Number of posters | M27: 1600 | N27: posters | T27: AVD | U27: =1966999/75 -> 26226.653 | V27: incentives
A28: Number of intern days | B28: 210 | C28: man-days | F28: Trainee per-diem | G28: 12200 | H28: 2017 INR | L28: SIM cards | M28: 4267772 | N28: 2017 INR
F29: Number of trainers (Master) | G29: 2 | H29: trainings
F30: Number of participants (Master) | H30: people
A31: Targeting Costs | B31: Number | C31: Unit | F31: Number of master trainings | H31: trainings | L31: Implementation Costs: Phone Stuff | M31: Number | N31: Unit | P31: Pilot Costs | Q31: Number | R31: Unit
A32: IEC (Promotional Materials) | B32: 481040 | C32: 2017 INR | F32: ANM training materials | G32: 210000 | H32: 2017 INR | L32: Mobile recharges | M32: 16712390 | N32: 2017 INR | P32: Food and refreshments | Q32: =2660+2340+4390+1122 -> 10512 | R32: 2017 INR
A33: Travel to Gurgaon | B33: 1100 | C33: 2017 INR | F33: ANM training food/bev | G33: 420000 | H33: 2017 INR | L33: Congratulatory SMS | M33: 570271 | N33: SMS | P33: Per-diem allowance | Q33: =300*(4+7+11) -> 6600 | R33: 2017 INR
A34: Per-diem for monitors | B34: 900 | C34: 2017 INR | F34: ANM trainer per-diem | G34: 72000 | H34: 2017 INR | L34: Targeted reminder SMS | M34: 18685 | N34: SMS | P34: Travel to Gurgaon | Q34: =3*1100 -> 3300 | R34: 2017 INR
A35: Lunch and refreshments | B35: 612 | C35: 2017 INR | F35: ANM trainee per-diem | G35: 420000 | H35: 2017 INR | L35: ANM SMS | M35: =31405/M39 -> 65427.083 | N35: SMS
A36: Travel costs for core staff | B36: 600 | C36: 2017 INR | F36: ANM training travel + lodging | G36: =86400+3079.545454545*44+12087.2266666666*30+21000 -> 605516.8 | H36: 2017 INR | L36: Seeds SMS | M36: =14623/M40 -> 20309.722 | N36: SMS | P36: Monitoring Costs | Q36: Number | R36: Unit
F37: Per-diem allowance | G37: 210000 | H37: 2017 INR | L37: Voice calls | M37: =159676/M41 -> 456217.14 | N37: calls | P37: Travel (total costs) | Q37: 144000 | R37: 2017 INR
F38: Number of ANM trainings | G38: 45 | H38: trainings | L38: Exotel | M38: 37332 | N38: 2017 INR | P38: Cost per tablet | Q38: 3140 | R38: 2017 INR
F39: Number of trainers (ANM) | G39: 150 | H39: people | L39: Cost per SMS (regular) | M39: 0.48 | N39: 2017 INR | P39: Number of tablets | Q39: 50 | R39: tablets
F40: Number of participants (ANM) | G40: 1500 | H40: people | L40: Cost per SMS (seed) | M40: 0.72 | N40: 2017 INR
L41: Cost per voice call | M41: 0.35 | N41: 2017 INR
A46: Ingredient | B46: Unit Cost | C46: Currency (Location & Yr) | D46: Units Req'd (per year) | E46: Years Required | F46: Total Cost/Yr, Local Currency | G46: Total Cost/Yr, Yr Incurred USD | H46: Total Cost/Yr, Base Year USD | I46: PV of Cost Stream, Base Yr USD | J46: Total Cost, Yr of Analysis USD | K46: Unique # units per arm?
A47: Field office rental, furniture, and utilities - 2017 | B47: =B25*B13 -> 722247.2 | C47: 2017 INR | D47: 1 | E47: 1 | F47: =E47*D47*B47 -> 722247.2 | G47: =F47/$B$17 -> 11090.679 | K47: No
A48: Program implementation staff and interns - 2017 | B48: =(B26+B27*B28)*B13 -> 16205494 | C48: 2017 INR | D48: 1 | E48: 1 | F48: =E48*D48*B48 -> 16205494 | G48: =F48/$B$17 -> 248848.22 | K48: No
A49: Targeting costs: Advertisting | B49: =SUM(B32:B36) -> 484252 | C49: 2017 INR | D49: 1 | E49: 1 | F49: =E49*D49*B49 -> 484252 | G49: =F49/$B$17 -> 7436.0738 | K49: Maybe
A50: J-PAL staff training costs | B50: =SUM(G10:G17) -> 117290.82 | C50: 2017 INR | D50: 1 | E50: 1 | F50: =E50*D50*B50 -> 117290.82 | G50: =F50/$B$17 -> 1801.0936 | K50: No
A51: Master training costs | B51: =SUM(G20:G28) -> 275562 | C51: 2017 INR | D51: 1 | E51: 1 | F51: =E51*D51*B51 -> 275562 | G51: =F51/$B$17 -> 4231.4732 | K51: No
A52: ANM training costs | B52: =SUM(G32:G37) -> 1937516.8 | C52: 2017 INR | D52: 1 | E52: 1 | F52: =E52*D52*B52 -> 1937516.8 | G52: =F52/$B$17 -> 29752.108 | K52: Maybe
A53: Targeting costs: Gossips identfication | B53: =(M10*M14+M11*M15+M12*M16+M13*M17+M18+M19) -> 410375 | C53: 2017 INR | D53: 1 | E53: 1 | F53: =E53*D53*B53 -> 410375 | G53: =F53/$B$17 -> 6301.6338 | K53: No
A54: Tablets | B54: =M22 -> 8230 | C54: 2017 INR | D54: =M24 -> 1200 | E54: 1 | F54: =E54*D54*B54 -> 9876000 | G54: =F54/$B$17 -> 151653.82 | K54: Maybe
A55: Bar codes | B55: =M23 -> 175 | C55: 2017 INR | D55: =M25 -> 1676 | E55: 1 | F55: =E55*D55*B55 -> 293300 | G55: =F55/$B$17 -> 4503.8543 | K55: Maybe
A56: SIM cards | B56: =M28 -> 4267772 | C56: 2017 INR | D56: 1 | E56: 1 | F56: =E56*D56*B56 -> 4267772 | G56: =F56/$B$17 -> 65535.027 | K56: Maybe
A57: ANM posters | B57: =M26 -> 16.576 | C57: 2017 INR | D57: =M27 -> 1600 | E57: 1 | F57: =E57*D57*B57 -> 26521.6 | G57: =F57/$B$17 -> 407.26022 | K57: Maybe
A58: Mobile recharges | B58: =M32 -> 16712390 | C58: 2017 INR | E58: 1 | F58: =E58*D58*B58 -> 0 | G58: =F58/$B$17 -> 0 | K58: Maybe
A59: Seed SMS | B59: =M40 -> 0.72 | C59: 2017 INR | E59: 1 | F59: =E59*D59*B59 -> 0 | G59: =F59/$B$17 -> 0 | K59: Yes
A60: Regular SMS | B60: =M39 -> 0.48 | C60: 2017 INR | E60: 1 | F60: =E60*D60*B60 -> 0 | G60: =F60/$B$17 -> 0 | K60: Yes
A61: Voice calls | B61: =M41 -> 0.35 | C61: 2017 INR | E61: 1 | F61: =E61*D61*B61 -> 0 | G61: =F61/$B$17 -> 0 | K61: Yes
A62: Exotel toll-free number service - 2017 | B62: =M38*B13 -> 29865.6 | C62: 2017 INR | D62: 1 | E62: 1 | F62: =E62*D62*B62 -> 29865.6 | G62: =F62/$B$17 -> 458.60999 | K62: No
A63: Meeting costs (transportation, lodging, per-diem) - 2017 | B63: =SUM(Q10,B13*(Q11+Q12),B13*Q13*Q15,B13*Q14*Q16,Q17) -> 377608.8 | C63: 2017 INR | D63: 1 | E63: 1 | F63: =E63*D63*B63 -> 377608.8 | G63: =F63/$B$17 -> 5798.4828 | K63: No
A64: SANA software development | B64: =SUM(Q22:Q23) -> 2030900 | C64: 2016 INR | D64: 1 | E64: 1 | F64: =E64*D64*B64 -> 2030900 | G64: =F64/$B$17 -> 31186.082 | K64: No
A65: Server for SANA and tablet data - 2017 | B65: =Q24*B13 -> 179542.4 | C65: 2017 INR | D65: 1 | E65: 1 | F65: =E65*D65*B65 -> 179542.4 | G65: =F65/$B$17 -> 2757.0161 | K65: No
A66: Server for Survey CTO - 2017 | B66: =Q25*B13 -> 186368 | C66: 2017 INR | D66: 1 | E66: 1 | F66: =E66*D66*B66 -> 186368 | G66: =F66/$B$17 -> 2861.8286 | K66: No
A67: Software piloting costs | B67: =SUM(Q32:Q34) -> 20412 | C67: 2016 INR | D67: 1 | E67: 1 | F67: =E67*D67*B67 -> 20412 | G67: =F67/$B$17 -> 313.44246 | K67: No
A68: Monitoring travel - 2017 | B68: =Q37*B13 -> 115200 | C68: 2017 INR | D68: 1 | E68: 1 | F68: =E68*D68*B68 -> 115200 | G68: =F68/$B$17 -> 1768.9874 | K68: Maybe
A69: Tablets for monitoring - 2017 | B69: =Q38*B13 -> 2512 | C69: 2017 INR | D69: =Q39 -> 50 | E69: 1 | F69: =E69*D69*B69 -> 125600 | G69: =F69/$B$17 -> 1928.6877 | K69: No
A70: ASHA incentive for mobilization - 2017 | B70: =U10 -> 100 | C70: 2017 INR | E70: 1 | F70: =E70*D70*B70 -> 0 | G70: =F70/$B$17 -> 0 | K70: Yes
A71: ASHA incentive for FIC - 2017 | B71: =U11 -> 150 | C71: 2017 INR | E71: 1 | F71: =E71*D71*B71 -> 0 | G71: =F71/$B$17 -> 0 | K71: Yes
A72: AVD - 2017 | B72: =U12 -> 75 | C72: 2017 INR | E72: 1 | F72: =E72*D72*B72 -> 0 | G72: =F72/$B$17 -> 0 | K72: Yes
A73: BCG vaccines - 2017 | B73: =U13 -> 3.25 | C73: 2017 INR | E73: 1 | F73: =E73*D73*B73 -> 0 | G73: =F73/$B$17 -> 0 | K73: Yes
A74: Penta vaccines (1, 2, 3) - 2017 | B74: =U14 -> 137.15 | C74: 2017 INR | E74: 1 | F74: =E74*D74*B74 -> 0 | G74: =F74/$B$17 -> 0 | K74: Yes
A75: Measles 1 vaccines - 2017 | B75: =U15 -> 32.5 | C75: 2017 INR | E75: 1 | F75: =E75*D75*B75 -> 0 | G75: =F75/$B$17 -> 0 | K75: Yes
A76: 5 mL syringes - 2017 | B76: =U16 -> 1.95 | C76: 2017 INR | E76: 1 | F76: =E76*D76*B76 -> 0 | G76: =F76/$B$17 -> 0 | K76: Yes
A77: 0.5 mL syringes - 2017 | B77: =U17 -> 1.95 | C77: 2017 INR | E77: 1 | F77: =E77*D77*B77 -> 0 | G77: =F77/$B$17 -> 0 | K77: Yes
A78: 0.1 mL syringes - 2017 | B78: =U18 -> 2.6 | C78: 2017 INR | E78: 1 | F78: =E78*D78*B78 -> 0 | G78: =F78/$B$17 -> 0 | K78: Yes
A79: Field office rental, furniture, and utilities - 2018 | B79: =B25*(1-B13) -> 180561.8 | C79: 2018 INR | D79: 1 | E79: 1 | F79: =E79*D79*B79 -> 180561.8 | G79: =F79/B18 -> 2640.217 | K79: No
A80: Program implementation staff and interns - 2018 | B80: =(B26+B27*B28)*(1-B13) -> 4051373.4 | C80: 2018 INR | D80: 1 | E80: 1 | F80: =E80*D80*B80 -> 4051373.4 | G80: =F80/B18 -> 59240.133 | K80: No
A81: Targeting costs: Advertisting - 2018 | B81: =SUM(B64:B68) -> 2532422.4 | C81: 2018 INR | D81: 1 | E81: 1 | F81: =E81*D81*B81 -> 2532422.4 | G81: =F81/$B$17 -> 38887.356 | K81: Maybe
A82: J-PAL staff training costs - 2018 | B82: =SUM(G42:G49) -> 267374.97 | C82: 2018 INR | D82: 1 | E82: 1 | F82: =E82*D82*B82 -> 267374.97 | G82: =F82/$B$17 -> 4105.7549 | K82: No
A83: Master training costs - 2018 | B83: =SUM(G52:G60) -> 258153.7 | C83: 2018 INR | D83: 1 | E83: 1 | F83: =E83*D83*B83 -> 258153.7 | G83: =F83/$B$17 -> 3964.155 | K83: No
A84: ANM training costs - 2018 | B84: =SUM(G64:G69) -> 40816.044 | C84: 2018 INR | D84: 1 | E84: 1 | F84: =E84*D84*B84 -> 40816.044 | G84: =F84/$B$17 -> 626.76275 | K84: Maybe
A85: Mobile recharges - 2018 | B85: =M64 -> 0 | C85: 2018 INR | E85: 1 | F85: =E85*D85*B85 -> 0 | G85: =F85/$B$17 -> 0 | K85: Maybe
A86: Seed SMS - 2018 | B86: =M72 -> 0 | C86: 2018 INR | E86: 1 | F86: =E86*D86*B86 -> 0 | G86: =F86/$B$17 -> 0 | K86: Yes
A87: Regular SMS - 2018 | B87: =M71 -> 0 | C87: 2018 INR | E87: 1 | F87: =E87*D87*B87 -> 0 | G87: =F87/$B$17 -> 0 | K87: Yes
A88: Voice calls - 2018 | B88: =M73 -> 0 | C88: 2018 INR | E88: 1 | F88: =E88*D88*B88 -> 0 | G88: =F88/$B$17 -> 0 | K88: Yes
A89: Exotel toll-free number service - 2018 | B89: =M38*(1-B13) -> 7466.4 | C89: 2018 INR | D89: 1 | E89: 1 | F89: =E89*D89*B89 -> 7466.4 | G89: =F89/$B$17 -> 114.6525 | K89: No
A90: Meeting costs (transportation, per-diem) - 2018 | B90: =SUM((1-B13)*(Q11+Q12),(1-B13)*Q13*Q15,(1-B13)*Q14*Q16) -> 69102.2 | C90: 2018 INR | D90: 1 | E90: 1 | F90: =E90*D90*B90 -> 69102.2 | G90: =F90/$B$17 -> 1061.1191 | K90: No
A91: Server for SANA and tablet data - 2018 | B91: =Q24*(1-B13) -> 44885.6 | C91: 2018 INR | D91: 1 | E91: 1 | F91: =E91*D91*B91 -> 44885.6 | G91: =F91/$B$17 -> 689.25402 | K91: No
A92: Server for Survey CTO - 2018 | B92: =Q25*(1-B13) -> 46592 | C92: 2018 INR | D92: 1 | E92: 1 | F92: =E92*D92*B92 -> 46592 | G92: =F92/$B$17 -> 715.45714 | K92: No
A93: Monitoring travel - 2018 | B93: =Q37*(1-B13) -> 28800 | C93: 2018 INR | D93: 1 | E93: 1 | F93: =E93*D93*B93 -> 28800 | G93: =F93/$B$17 -> 442.24686 | K93: Maybe
A94: Tablets for monitoring - 2018 | B94: =Q38*(1-B13) -> 628 | C94: 2018 INR | D94: =Q39 -> 50 | E94: 1 | F94: =E94*D94*B94 -> 31400 | G94: =F94/$B$17 -> 482.17192 | K94: No
A95: ASHA incentive for mobilization - 2018 | B95: =U10 -> 100 | C95: 2018 INR | D95: =U57 -> 0 | E95: 1 | F95: =E95*D95*B95 -> 0 | G95: =F95/$B$17 -> 0 | K95: Yes
A96: ASHA incentive for FIC - 2018 | B96: =U11 -> 150 | C96: 2018 INR | D96: =U58 -> 0 | E96: 1 | F96: =E96*D96*B96 -> 0 | G96: =F96/$B$17 -> 0 | K96: Yes
A97: AVD - 2018 | B97: =U12 -> 75 | C97: 2018 INR | D97: =U59 -> 0 | E97: 1 | F97: =E97*D97*B97 -> 0 | G97: =F97/$B$17 -> 0 | K97: Yes
A98: BCG vaccines - 2018 | B98: =U13 -> 3.25 | C98: 2018 INR | D98: =U51 -> 0 | E98: 1 | F98: =E98*D98*B98 -> 0 | G98: =F98/$B$17 -> 0 | K98: Yes
A99: Penta vaccines (1, 2, 3) - 2018 | B99: =U14 -> 137.15 | C99: 2018 INR | D99: =U52 -> 0 | E99: 1 | F99: =E99*D99*B99 -> 0 | G99: =F99/$B$17 -> 0 | K99: Yes
A100: Measles 1 vaccines - 2018 | B100: =U15 -> 32.5 | C100: 2018 INR | D100: =U53 -> 0 | E100: 1 | F100: =E100*D100*B100 -> 0 | G100: =F100/$B$17 -> 0 | K100: Yes
A101: 5 mL syringes - 2018 | B101: =U16 -> 1.95 | C101: 2018 INR | D101: =U54 -> 0 | E101: 1 | F101: =E101*D101*B101 -> 0 | G101: =F101/$B$17 -> 0 | K101: Yes
A102: 0.5 mL syringes - 2018 | B102: =U17 -> 1.95 | C102: 2018 INR | D102: =U55 -> 0 | E102: 1 | F102: =E102*D102*B102 -> 0 | G102: =F102/$B$17 -> 0 | K102: Yes
A103: 0.1 mL syringes - 2018 | B103: =U18 -> 2.6 | C103: 2018 INR | D103: =U56 -> 0 | E103: 1 | F103: =E103*D103*B103 -> 0 | G103: =F103/$B$17 -> 0 | K103: Yes

Sheet policy template -perunit
A1: Study Title | B1: HIM
A2: Authors | B2: Banerjee, Chandrashekhar, Duflo, Dalpath, Floretta, Jackson, Kannan, Schrimpf, and Shrestha
A3: Publication Date
A4: Location | B4: Haryana, India
A5: Base Year | B5: 2016
A6: Year of Analysis | B6: 2018 | L6: Networks Switch | M6: 0
A7: Outcome Measure | B7: Additional fully immunized children | L7: Gossip Switch | M7: 0
A9: Demographics | B9: Number | C9: Unit | F9: Trainings | G9: Number | H9: Unit | L9: Gossips Identification | M9: Number | N9: Unit | P9: Implementation Costs: Meetings | Q9: Number | R9: Unit | T9: Government Costs | U9: Number | V9: Unit
A10: Intervention Duration | B10: ='0 - Total Costs'!B10 -> 15 | C10: months | F10: Printing | G10: ='0 - Total Costs'!G10*$B$20 -> 0.052966102 | H10: 2017 INR | L10: Surveyors | M10: ='0 - Total Costs'!M10*B$20 -> 0.18050847 | N10: man-days | P10: Lodging for meetings (launch + 6-month) | Q10: ='0 - Total Costs'!Q10*$B$20 -> 38.135593 | R10: 2017 INR | T10: ASHA incentives for mobilization | U10: ='0 - Total Costs'!U10 -> 100 | V10: 2017 INR
A11: Villages in trusted only treatment | B11: 1 | C11: villages | F11: Lunch and refreshments | G11: ='0 - Total Costs'!G11*$B$20 -> 3.1923729 | H11: 2017 INR | L11: Monitors | M11: ='0 - Total Costs'!M11*B$20 -> 0.056355932 | N11: man-days | P11: Transportation to monthly district meetings | Q11: ='0 - Total Costs'!Q11*$B$20 -> 77.970763 | R11: 2017 INR | T11: ASHA incentives for FIC | U11: ='0 - Total Costs'!U11 -> 150 | V11: 2017 INR
F12: J-PAL trainer lodging | G12: ='0 - Total Costs'!G12*$B$20 -> 6.7372881 | H12: 2017 INR | L12: Field Manager | M12: ='0 - Total Costs'!M12*B$20 -> 0.030508475 | N12: man-days | P12: Transportation to staet-level meetings | Q12: ='0 - Total Costs'!Q12*$B$20 -> 42.457627 | R12: 2017 INR | T12: AVD | U12: ='0 - Total Costs'!U12 -> 75 | V12: 2017 INR
A13: Discount Rate | B13: =Comparisons!C6 -> 0.1 | C13: percent | F13: J-PAL trainer per-diem | G13: ='0 - Total Costs'!G13*$B$20 -> 2.4999915 | H13: 2017 INR | L13: Project Associate | M13: ='0 - Total Costs'!M13*B$20 -> 0.024520466 | N13: man-days | P13: Per-diem allowance (high level) | Q13: ='0 - Total Costs'!Q13 -> 800 | R13: 2017 INR | T13: Cost per BCG vaccine | U13: ='0 - Total Costs'!U13 -> 3.25 | V13: 2017 INR
A14: US-Local Exchange Rate, 2017 Standard | B14: 65.122 | C14: Rs/USD | F14: J-PAL trainer transportation | G14: ='0 - Total Costs'!G14*$B$20 -> 9.3220339 | H14: 2017 INR | L14: Surveyor daily wage | M14: ='0 - Total Costs'!M14*B20 -> 0.14830508 | N14: 2017 INR | P14: Per-diem allowance (low level) | Q14: ='0 - Total Costs'!Q14 -> 300 | R14: 2017 INR | T14: Cost per Penta vaccines | U14: ='0 - Total Costs'!U14 -> 137.15 | V14: 2017 INR
F15: J-PAL staff lodging | G15: ='0 - Total Costs'!G15*$B$20 -> 0.76271186 | H15: 2017 INR | L15: Monitors daily wage | M15: =B20*'0 - Total Costs'!M15 -> 0.22245763 | N15: 2017 INR | P15: Number of high level per-diem allowances | Q15: ='0 - Total Costs'!Q15*$B$20 -> 0.031355932 | R15: allowances | T15: Cost per measles vaccine | U15: ='0 - Total Costs'!U15 -> 32.5 | V15: 2017 INR
F16: J-PAL staff transportation | G16: ='0 - Total Costs'!G16*$B$20 -> 6.0305 | H16: 2017 INR | L16: Field Manager daily wage | M16: =B20*'0 - Total Costs'!M16 -> 0.25423729 | N16: 2017 INR | P16: Number of low level per-diem allowances | Q16: ='0 - Total Costs'!Q16*$B$20 -> 0.0029661017 | R16: allowances | T16: Cost per 5 mL syringe | U16: ='0 - Total Costs'!U16 -> 1.95 | V16: 2017 INR | Y16: Totals
A17: Villages in entire sample | B17: ='0 - Total Costs'!B19 -> 2360 | C17: villages | F17: J-PAL staff per-diem | G17: ='0 - Total Costs'!G17*$B$20 -> 21.101636 | H17: 2017 INR | L17: Project Associate daily wage | M17: ='0 - Total Costs'!M17*B20 -> 0.37966102 | N17: 2017 INR | P17: Per-diem for launch + 6-month meetings | Q17: ='0 - Total Costs'!Q17*$B$20 -> 4.7457627 | R17: 2017 INR | T17: Cost per 0.5 mL syringe | U17: ='0 - Total Costs'!U17 -> 1.95 | V17: 2017 INR | Y17: BCG | Z17: 0
A18: Villages in baseline sample | B18: 903 | C18: villages | F18: Number of trainers (Staff) | G18: ='0 - Total Costs'!G18 -> 1 | H18: people | L18: Travel | M18: ='0 - Total Costs'!M18*B$20 -> 40.211864 | N18: 2017 INR | T18: Cost per 0.1 mL syringe | U18: ='0 - Total Costs'!U18 -> 2.6 | V18: 2017 INR | Y18: Penta | Z18: 0
A19: Average children per village | B19: 91.024286 | C19: children | F19: Number of participants (Staff) | G19: ='0 - Total Costs'!G19 -> 24 | H19: people | L19: Event space | M19: ='0 - Total Costs'!M19*B$20 -> 0.63559322 | N19: 2017 INR | T19: Number of BCG vaccines | U19: =Z17*#REF! -> #REF! | V19: vaccines | Y19: Measles | Z19: 0
A20: Scaling factor for single village | B20: =B11/B17 -> 0.00042372881 | C20: percent | F20: Master training materials | G20: ='0 - Total Costs'!G20*$B$20 -> 27.087288 | H20: 2017 INR | T20: Number of Penta vaccines | U20: =Z18*#REF! -> #REF! | V20: vaccines
A21: Number of children in package treatment arm | B21: =B19*B11 -> 91.024286 | C21: children | F21: Master training food/bev | G21: ='0 - Total Costs'!G21*$B$20 -> 8.870339 | H21: 2017 INR | L21: Implementation Costs: Materials | M21: Number | N21: Unit | P21: Implementation Costs: Software | Q21: Number | R21: Unit | T21: Number of measles vaccines | U21: =Z19*#REF! -> #REF! | V21: vaccines | Y21: Penta-1 | Z21: 0
A22: Rate of full immunization at baseline | B22: 0.4 | C22: percent | F22: Master training trainer lodging | G22: ='0 - Total Costs'!G22*$B$20 -> 18.962712 | H22: 2017 INR | L22: Tablets + covers (rental costs) | M22: ='0 - Total Costs'!M22/M29 -> 228.61111 | N22: 2017 INR | P22: SANA software | Q22: ='0 - Total Costs'!Q22*$B$20 -> 858.77119 | R22: 2017 INR | T22: Number of 5 mL syringes | U22: =0 -> 0 | V22: syringes | Y22: Penta-2 | Z22: 0
A23: Number of fully immunized children at baseline | B23: =B22*B21 -> 36.409714 | C23: children | F23: Master training trainer transport | G23: ='0 - Total Costs'!G23*$B$20 -> 8.6440678 | H23: 2017 INR | L23: Bar codes (cost per roll) | M23: ='0 - Total Costs'!M23 -> 175 | N23: 2017 INR | P23: Labor to develop software | Q23: ='0 - Total Costs'!Q23*$B$20 -> 1.779661 | R23: 2017 INR | T23: Number of 0.5 mL syringes | U23: =SUM(U20:U21) -> #REF! | V23: syringes | Y23: Penta-3 | Z23: 0
A24: Number of ANMs in package treatment villages | B24: ='0 - Total Costs'!B20*B20 -> 0.59194915 | C24: ANMs | F24: Master training trainer per-diem | G24: ='0 - Total Costs'!G24*$B$20 -> 12.20339 | H24: 2017 INR | L24: Number of tablets | M24: ='0 - Total Costs'!M24*$B$20 -> 0.50847458 | N24: tablets | P24: Server cost: SANA | Q24: ='0 - Total Costs'!Q24*$B$20 -> 95.09661 | R24: 2017 INR | T24: Number of 0.1 mL syringes | U24: =U19 -> #REF! | V24: syringes
F25: Master training facilitator per-diem | G25: ='0 - Total Costs'!G25*$B$20 -> 6.1016949 | H25: 2017 INR | L25: Number of bar codes | M25: ='0 - Total Costs'!M25*$B$20 -> 0.71016949 | N25: rolls | P25: Server cost: SurveyCTO | Q25: ='0 - Total Costs'!Q25*$B$20 -> 98.711864 | R25: 2017 INR | T25: ASHA incentives for mobilization | U25: =SUM(U19:U21) -> #REF! | V25: incentives
A26: Number of gossips per village | B26: 6 | C26: people | F26: Trainee lodging | G26: ='0 - Total Costs'!G26*$B$20 -> 3.8771186 | H26: 2017 INR | L26: ANM posters | M26: ='0 - Total Costs'!M26 -> 16.576 | N26: 2017 INR | T26: ASHA incentives for FIC | U26: =U21 -> #REF! | V26: incentives
F27: Trainee transport | G27: ='0 - Total Costs'!G27*$B$20 -> 25.847458 | H27: 2017 INR | L27: Number of posters | M27: ='0 - Total Costs'!M27*B20 -> 0.6779661 | N27: posters | P27: Pilot Costs | Q27: Number | R27: Unit | T27: AVD | U27: =U25 -> #REF! | V27: incentives
A28: Program Administration | B28: Number | C28: Unit | F28: Trainee per-diem | G28: ='0 - Total Costs'!G28*$B$20 -> 5.1694915 | H28: 2017 INR | L28: SIM cards | M28: ='0 - Total Costs'!M28*B20 -> 1808.378 | N28: 2017 INR | P28: Food and refreshments | Q28: ='0 - Total Costs'!Q32*$B$20 -> 4.4542373 | R28: 2017 INR
A29: Field office rent and costs | B29: ='0 - Total Costs'!B25*B20 -> 382.54619 | C29: 2017 INR | F29: Number of trainers (Master) | G29: ='0 - Total Costs'!G29 -> 2 | H29: trainings | L29: Useful life of tablet | M29: 36 | N29: months | P29: Per-diem allowance | Q29: ='0 - Total Costs'!Q33*$B$20 -> 2.7966102 | R29: 2017 INR | T29: Mobile Recharges | U29: Number | V29: Unit
A30: Staff costs | B30: ='0 - Total Costs'!B26*B20 -> 8538.9268 | C30: 2017 INR | F30: Number of participants (Master) | G30: ='0 - Total Costs'!G30 -> 0 | H30: people | P30: Travel to Gurgaon | Q30: ='0 - Total Costs'!Q34*$B$20 -> 1.3983051 | R30: 2017 INR | T30: Number of low-slope incentives for BCG | U30: 0 | V30: vaccines
A31: Intern daily salary | B31: ='0 - Total Costs'!B27 -> 500 | C31: 2017 INR | F31: Number of master trainings | G31: ='0 - Total Costs'!G31 -> 0 | H31: trainings | L31: Implementation Costs: Phone Stuff | M31: Number | N31: Unit | T31: Number of low-slope incentives for Penta-1 | U31: 0 | V31: vaccines
A32: Number of intern days | B32: ='0 - Total Costs'!B28*B20 -> 0.088983051 | C32: man-days | F32: ANM training materials | G32: ='0 - Total Costs'!G32*$B$20 -> 88.983051 | H32: 2017 INR | L32: Mobile recharges | M32: =(SUM(U30:U32)*U40+U33*U41+U34*U42)+(SUM(U35:U37)*U43+U38*U44+U39*U45) -> 0 | N32: 2017 INR | P32: Monitoring Costs | Q32: Number | R32: Unit | T32: Number of low-slope incentives for Penta-2 | U32: 0 | V32: vaccines
F33: ANM training food/bev | G33: ='0 - Total Costs'!G33*$B$20 -> 177.9661 | H33: 2017 INR | L33: Congratulatory SMS | M33: =SUM(U19:U21) -> #REF! | N33: SMS | P33: Travel (total costs) | Q33: ='0 - Total Costs'!Q37*B20 -> 61.016949 | R33: 2017 INR | T33: Number of low-slope incentives for Penta-3 | U33: 0 | V33: vaccines
F34: ANM trainer per-diem | G34: ='0 - Total Costs'!G34*$B$20 -> 30.508475 | H34: 2017 INR | L34: Targeted reminder SMS | M34: =SUM(U19:U21)*M42*M44 -> #REF! | N34: SMS | P34: Cost per tablet | Q34: ='0 - Total Costs'!Q38 -> 3140 | R34: 2017 INR | T34: Number of low-slope incentives for measls | U34: 0 | V34: vaccines
A35: Targeting Costs | B35: Number | C35: Unit | F35: ANM trainee per-diem | G35: ='0 - Total Costs'!G35*$B$20 -> 177.9661 | H35: 2017 INR | L35: ANM SMS | M35: =B24*B10 -> 8.8792373 | N35: SMS | P35: Number of tablets | Q35: ='0 - Total Costs'!Q39*B20 -> 0.021186441 | R35: tablets | T35: Number of high-slope incentives for BCG | U35: 0 | V35: vaccines
A36: IEC (Promotional Materials) | B36: ='0 - Total Costs'!B32*$B$20 -> 203.83051 | C36: 2017 INR | F36: ANM training travel + lodging | G36: ='0 - Total Costs'!G36*$B$20 -> 256.57492 | H36: 2017 INR | L36: Seeds SMS (monthly) | M36: =B26*B11 -> 6 | N36: SMS | T36: Number of high-slope incentives for Penta-1 | U36: 0 | V36: vaccines
A37: Travel to Gurgaon | B37: ='0 - Total Costs'!B33*$B$20 -> 0.46610169 | C37: 2017 INR | F37: Per-diem allowance | G37: ='0 - Total Costs'!G37*$B$20 -> 88.983051 | H37: 2017 INR | L37: Voice calls (monthly) | M37: =M36 -> 6 | N37: calls | T37: Number of high-slope incentives for Penta-2 | U37: 0 | V37: vaccines
A38: Per-diem for monitors | B38: ='0 - Total Costs'!B34*$B$20 -> 0.38135593 | C38: 2017 INR | F38: Number of ANM trainings | G38: ='0 - Total Costs'!G38 -> 45 | H38: trainings | L38: Exotel | M38: ='0 - Total Costs'!M38*B$20 -> 15.818644 | N38: 2017 INR | T38: Number of high-slope incentives for Penta-3 | U38: 0 | V38: vaccines
A39: Lunch and refreshments | B39: ='0 - Total Costs'!B35*$B$20 -> 0.25932203 | C39: 2017 INR | F39: Number of trainers (ANM) | G39: ='0 - Total Costs'!G39 -> 150 | H39: people | L39: Cost per SMS (regular) | M39: ='0 - Total Costs'!M39 -> 0.48 | N39: 2017 INR | T39: Number of high-slope incentives for measls | U39: 0 | V39: vaccines
A40: Travel costs for core staff | B40: ='0 - Total Costs'!B36*$B$20 -> 0.25423729 | C40: 2017 INR | F40: Number of participants (ANM) | G40: ='0 - Total Costs'!G40 -> 1500 | H40: people | L40: Cost per SMS (seed) | M40: ='0 - Total Costs'!M40 -> 0.72 | N40: 2017 INR | T40: Low slope incentives, vaccines 1-3 | U40: 10 | V40: 2017 INR
L41: Cost per voice call | M41: ='0 - Total Costs'!M41 -> 0.35 | N41: 2017 INR | T41: Low slope incentives, vaccine 4 | U41: 60 | V41: 2017 INR
L42: Average reminder saturation | M42: =(0.33+0.66)/2 -> 0.495 | N42: percent | T42: Low slope incentives, vaccine 5 | U42: 160 | V42: 2017 INR
T43: High slope incentives, vaccines 1-3 | U43: 50 | V43: 2017 INR
L44: Reminder switch | M44: 0 | T44: High slope incentives, vaccine 4 | U44: 100 | V44: 2017 INR
T45: High slope incentives, vaccine 5 | U45: 200 | V45: 2017 INR
A46: Ingredient | B46: Unit Cost | C46: Currency (Location & Yr) | D46: Units Req'd (per year) | E46: Years Required | F46: Total Cost/Yr, Local Currency | G46: Total Cost/Yr, Yr Incurred USD | H46: Total Cost/Yr, Base Year USD | I46: PV of Cost Stream, Base Yr USD | J46: Total Cost, Yr of Analysis USD | K46: Unique # units per arm? | L46: Experiment Only Cost | M46: At scale | N46: At scale products | P46: control at scale Fixed cost | Q46: control at scale fixed cost (USD) | R46: control at scaled per month
A47: SANA software development | B47: =SUM(Q22:Q23) -> 860.55085 | C47: 2016 INR | D47: 1 | E47: 1 | F47: =E47*D47*B47 -> 860.55085 | G47: =F47/'0 - Total Costs'!B16 -> 12.806769 | H47: =G47 -> 12.806769 | I47: =H47 -> 12.806769 | J47: =I47*((1+'0 - Total Costs'!$B$23)^2) -> 13.324163 | K47: No | L47: 1 | M47: =1-L47 -> 0 | N47: =M47*J47 -> 0 | P47: =+(B56*D56) + SUM(B57:B59) -> 3394.8692 | Q47: =P47/65.12 -> 52.132513 | R47: =Q47/15 -> 3.4755008
A48: Software piloting costs | B48: =SUM(Q28:Q30) -> 8.6491525 | C48: 2016 INR | D48: 1 | E48: 1 | F48: =E48*D48*B48 -> 8.6491525 | G48: =F48/'0 - Total Costs'!B16 -> 0.1287172 | H48: =G48 -> 0.1287172 | I48: =H48 -> 0.1287172 | J48: =I48*((1+'0 - Total Costs'!$B$23)^2) -> 0.13391738 | K48: No | L48: 1 | M48: =1-L48 -> 0 | N48: =M48*J48 -> 0
A49: Field office rental, furniture, and utilities - 2017 | B49: =B29*'0 - Total Costs'!B13 -> 306.03695 | C49: 2017 INR | D49: 1 | E49: 1 | F49: =E49*D49*B49 -> 306.03695 | G49: =F49/$B$14 -> 4.6994403 | H49: =G49/(1+'0 - Total Costs'!$B$22)^(2017-$B$5) -> 4.5982781 | I49: =H49/(1+$B$13)^(2017-$B$5) -> 4.1802529 | J49: =I49*((1+'0 - Total Costs'!$B$23)^2) -> 4.3491351 | K49: No | L49: 1 | M49: =1-L49 -> 0 | N49: =M49*J49 -> 0
A50: Program implementation staff and interns - 2017 | B50: =SUM(B30,B31*B32)*'0 - Total Costs'!B13 -> 6866.7347 | C50: 2017 INR | D50: 1 | E50: 1 | F50: =E50*D50*B50 -> 6866.7347 | G50: =F50/$B$14 -> 105.44416 | H50: =G50/(1+'0 - Total Costs'!$B$22)^(2017-$B$5) -> 103.17433 | I50: =H50/(1+$B$13)^(2017-$B$5) -> 93.794842 | J50: =I50*((1+'0 - Total Costs'!$B$23)^2) -> 97.584153 | K50: No | L50: 1 | M50: =1-L50 -> 0 | N50: =M50*J50 -> 0
A51: Targeting costs: Advertisting | B51: =SUM(B36:B40) -> 205.19153 | C51: 2017 INR | D51: 1 | E51: 1 | F51: =E51*D51*B51 -> 205.19153 | G51: =F51/$B$14 -> 3.1508787 | H51: =G51/(1+'0 - Total Costs'!$B$22)^(2017-$B$5) -> 3.0830516 | I51: =H51/(1+$B$13)^(2017-$B$5) -> 2.8027742 | J51: =I51*((1+'0 - Total Costs'!$B$23)^2) -> 2.9160063 | K51: Maybe | L51: 1 | M51: =1-L51 -> 0 | N51: =M51*J51 -> 0
A52: J-PAL staff training costs | B52: =SUM(G10:G17) -> 49.6995 | C52: 2017 INR | D52: 1 | E52: 1 | F52: =E52*D52*B52 -> 49.6995 | G52: =F52/$B$14 -> 0.76317527 | H52: =G52/(1+'0 - Total Costs'!$B$22)^(2017-$B$5) -> 0.74674684 | I52: =H52/(1+$B$13)^(2017-$B$5) -> 0.67886076 | J52: =I52*((1+'0 - Total Costs'!$B$23)^2) -> 0.70628674 | K52: No | L52: 1 | M52: =1-L52 -> 0 | N52: =M52*J52 -> 0
A53: Master training costs | B53: =SUM(G20:G28) -> 116.76356 | C53: 2017 INR | D53: 1 | E53: 1 | F53: =E53*D53*B53 -> 116.76356 | G53: =F53/$B$14 -> 1.7929971 | H53: =G53/(1+'0 - Total Costs'!$B$22)^(2017-$B$5) -> 1.7544003 | I53: =H53/(1+$B$13)^(2017-$B$5) -> 1.5949094 | J53: =I53*((1+'0 - Total Costs'!$B$23)^2) -> 1.6593437 | K53: No | L53: 0 | M53: =1-L53 -> 1 | N53: =M53*J53 -> 1.6593437
A54: ANM training costs | B54: =SUM(G32:G37) -> 820.98169 | C54: 2017 INR | D54: 1 | E54: 1 | F54: =E54*D54*B54 -> 820.98169 | G54: =F54/$B$14 -> 12.606826 | H54: =G54/(1+'0 - Total Costs'!$B$22)^(2017-$B$5) -> 12.335446 | I54: =H54/(1+$B$13)^(2017-$B$5) -> 11.214042 | J54: =I54*((1+'0 - Total Costs'!$B$23)^2) -> 11.667089 | K54: Maybe | L54: 1 | M54: =1-L54 -> 0 | N54: =M54*J54 -> 0
A55: Targeting costs: Gossips identfication | B55: =(M10*M14+M11*M15+M12*M16+M13*M17+M18+M19)*M7 -> 0 | C55: 2017 INR | D55: 1 | E55: 1 | F55: =E55*D55*B55 -> 0 | G55: =F55/$B$14 -> 0 | H55: =G55/(1+'0 - Total Costs'!$B$22)^(2017-$B$5) -> 0 | I55: =H55/(1+$B$13)^(2017-$B$5) -> 0 | J55: =I55*((1+'0 - Total Costs'!$B$23)^2) -> 0 | K55: No | L55: 0 | M55: =1-L55 -> 1 | N55: =M55*J55 -> 0
A56: Tablets (rental) - 2017 | B56: =M22 -> 228.61111 | C56: 2017 INR | D56: =M24*'0 - Total Costs'!B11 -> 6.1016949 | E56: 1 | F56: =E56*D56*B56 -> 1394.9153 | G56: =F56/$B$14 -> 21.420031 | H56: =G56/(1+'0 - Total Costs'!$B$22)^(2017-$B$5) -> 20.958934 | I56: =H56/(1+$B$13)^(2017-$B$5) -> 19.053577 | J56: =I56*((1+'0 - Total Costs'!$B$23)^2) -> 19.823341 | K56: Maybe | L56: 0 | M56: =1-L56 -> 1 | N56: =M56*J56 -> 19.823341
A57: Bar codes | B57: =M23 -> 175 | C57: 2017 INR | D57: =M25 -> 0.71016949 | E57: 1 | F57: =E57*D57*B57 -> 124.27966 | G57: =F57/$B$14 -> 1.9084128 | H57: =G57/(1+'0 - Total Costs'!$B$22)^(2017-$B$5) -> 1.8673315 | I57: =H57/(1+$B$13)^(2017-$B$5) -> 1.6975741 | J57: =I57*((1+'0 - Total Costs'!$B$23)^2) -> 1.7661561 | K57: Maybe | L57: 0 | M57: =1-L57 -> 1 | N57: =M57*J57 -> 1.7661561
A58: SIM cards | B58: =M28 -> 1808.378 | C58: 2017 INR | D58: 1 | E58: 1 | F58: =E58*D58*B58 -> 1808.378 | G58: =F58/$B$14 -> 27.769079 | H58: =G58/(1+'0 - Total Costs'!$B$22)^(2017-$B$5) -> 27.17131 | I58: =H58/(1+$B$13)^(2017-$B$5) -> 24.701191 | J58: =I58*((1+'0 - Total Costs'!$B$23)^2) -> 25.699119 | K58: Maybe | L58: 0 | M58: =1-L58 -> 1 | N58: =M58*J58 -> 25.699119
A59: ANM posters | B59: =M26 -> 16.576 | C59: 2017 INR | D59: =M27 -> 0.6779661 | E59: 1 | F59: =E59*D59*B59 -> 11.237966 | G59: =F59/$B$14 -> 0.17256789 | H59: =G59/(1+'0 - Total Costs'!$B$22)^(2017-$B$5) -> 0.16885312 | I59: =H59/(1+$B$13)^(2017-$B$5) -> 0.15350284 | J59: =I59*((1+'0 - Total Costs'!$B$23)^2) -> 0.15970435 | K59: Maybe | L59: 0 | M59: =1-L59 -> 1 | N59: =M59*J59 -> 0.15970435
A60: Seed SMS - 2017 | B60: =M40 -> 0.72 | C60: 2017 INR | D60: =(M36*'0 - Total Costs'!B11)*M6 -> 0 | E60: 1 | F60: =E60*D60*B60 -> 0 | G60: =F60/$B$14 -> 0 | H60: =G60/(1+'0 - Total Costs'!$B$22)^(2017-$B$5) -> 0 | I60: =H60/(1+$B$13)^(2017-$B$5) -> 0 | J60: =I60*((1+'0 - Total Costs'!$B$23)^2) -> 0 | K60: No | L60: 0 | M60: =1-L60 -> 1 | N60: =M60*J60 -> 0
A61: Exotel toll-free number service - 2017 | B61: =M38*'0 - Total Costs'!B13 -> 12.654915 | C61: 2017 INR | D61: 1 | E61: 1 | F61: =E61*D61*B61 -> 12.654915 | G61: =F61/$B$14 -> 0.19432627 | H61: =G61/(1+'0 - Total Costs'!$B$22)^(2017-$B$5) -> 0.19014312 | I61: =H61/(1+$B$13)^(2017-$B$5) -> 0.17285738 | J61: =I61*((1+'0 - Total Costs'!$B$23)^2) -> 0.17984082 | K61: No | L61: 1 | M61: =1-L61 -> 0 | N61: =M61*J61 -> 0
A62: Meeting costs (transportation, lodging, per-diem) - 2017 | B62: =SUM(Q10,'0 - Total Costs'!B13*(Q11+Q12),'0 - Total Costs'!B13*Q13*Q15,'0 - Total Costs'!B13*Q14*Q16,Q17) -> 160.00373 | C62: 2017 INR | D62: 1 | E62: 1 | F62: =E62*D62*B62 -> 160.00373 | G62: =F62/$B$14 -> 2.4569843 | H62: =G62/(1+'0 - Total Costs'!$B$22)^(2017-$B$5) -> 2.4040942 | I62: =H62/(1+$B$13)^(2017-$B$5) -> 2.1855402 | J62: =I62*((1+'0 - Total Costs'!$B$23)^2) -> 2.273836 | K62: Maybe | L62: 1 | M62: =1-L62 -> 0 | N62: =M62*J62 -> 0
A63: Server for SANA and tablet data - 2017 | B63: =Q24*'0 - Total Costs'!B13 -> 76.077288 | C63: 2017 INR | D63: 1 | E63: 1 | F63: =E63*D63*B63 -> 76.077288 | G63: =F63/$B$14 -> 1.1682271 | H63: =G63/(1+'0 - Total Costs'!$B$22)^(2017-$B$5) -> 1.1430794 | I63: =H63/(1+$B$13)^(2017-$B$5) -> 1.0391631 | J63: =I63*((1+'0 - Total Costs'!$B$23)^2) -> 1.0811453 | K63: No | L63: 1 | M63: =1-L63 -> 0 | N63: =M63*J63 -> 0
A64: Server for Survey CTO - 2017 | B64: =Q25*'0 - Total Costs'!B13 -> 78.969492 | C64: 2017 INR | D64: 1 | E64: 1 | F64: =E64*D64*B64 -> 78.969492 | G64: =F64/$B$14 -> 1.2126392 | H64: =G64/(1+'0 - Total Costs'!$B$22)^(2017-$B$5) -> 1.1865354 | I64: =H64/(1+$B$13)^(2017-$B$5) -> 1.0786686 | J64: =I64*((1+'0 - Total Costs'!$B$23)^2) -> 1.1222468 | L64: 1 | M64: =1-L64 -> 0 | N64: =M64*J64 -> 0
A65: Monitoring travel - 2017 | B65: =Q33*'0 - Total Costs'!B13 -> 48.813559 | C65: 2017 INR | D65: 1 | E65: 1 | F65: =E65*D65*B65 -> 48.813559 | G65: =F65/$B$14 -> 0.74957095 | H65: =G65/(1+'0 - Total Costs'!$B$22)^(2017-$B$5) -> 0.73343537 | I65: =H65/(1+$B$13)^(2017-$B$5) -> 0.66675943 | J65: =I65*((1+'0 - Total Costs'!$B$23)^2) -> 0.69369651 | L65: 1 | M65: =1-L65 -> 0 | N65: =M65*J65 -> 0
A66: Tablets for monitoring - 2017 | B66: =Q34 -> 3140 | C66: 2017 INR | D66: =Q35*'0 - Total Costs'!B13 -> 0.016949153 | E66: 1 | F66: =E66*D66*B66 -> 53.220339 | G66: =F66/$B$14 -> 0.81724055 | H66: =G66/(1+'0 - Total Costs'!$B$22)^(2017-$B$5) -> 0.79964829 | I66: =H66/(1+$B$13)^(2017-$B$5) -> 0.72695299 | J66: =I66*((1+'0 - Total Costs'!$B$23)^2) -> 0.75632189 | L66: 1 | M66: =1-L66 -> 0 | N66: =M66*J66 -> 0
A67: Field office rental, furniture, and utilities - 2018 | B67: =B29*'0 - Total Costs'!B14 -> 76.509237 | C67: 2018 INR | D67: 1 | E67: 1 | F67: =E67*D67*B67 -> 76.509237 | G67: =F67/'0 - Total Costs'!$B$18 -> 1.118736 | H67: =G67/(1+'0 - Total Costs'!$B$23)^(2018-$B$5) -> 1.0752941 | I67: =H67/(1+$B$13)^(2018-$B$5) -> 0.88867284 | J67: =I67*((1+'0 - Total Costs'!$B$23)^2) -> 0.92457522 | L67: 1 | M67: =1-L67 -> 0 | N67: =M67*J67 -> 0
A68: Program implementation staff and interns - 2018 | B68: =SUM(B30,B31*B32)*'0 - Total Costs'!B14 -> 1716.6837 | C68: 2018 INR | D68: 1 | E68: 1 | F68: =E68*D68*B68 -> 1716.6837 | G68: =F68/'0 - Total Costs'!$B$18 -> 25.101751 | H68: =G68/(1+'0 - Total Costs'!$B$23)^(2018-$B$5) -> 24.12702 | I68: =H68/(1+$B$13)^(2018-$B$5) -> 19.939686 | J68: =I68*((1+'0 - Total Costs'!$B$23)^2) -> 20.745249 | L68: 1 | M68: =1-L68 -> 0 | N68: =M68*J68 -> 0
A69: Tablets (rental) - 2018 | B69: =M22 -> 228.61111 | C69: 2018 INR | D69: =M24*'0 - Total Costs'!B12 -> 1.5254237 | E69: 1 | F69: =E69*D69*B69 -> 348.72881 | G69: =F69/'0 - Total Costs'!$B$18 -> 5.0991945 | H69: =G69/(1+'0 - Total Costs'!$B$23)^(2018-$B$5) -> 4.9011866 | I69: =H69/(1+$B$13)^(2018-$B$5) -> 4.0505674 | J69: =I69*((1+'0 - Total Costs'!$B$23)^2) -> 4.2142103 | L69: 0 | M69: =1-L69 -> 1 | N69: =M69*J69 -> 4.2142103
A70: Seed SMS - 2018 | B70: =M40 -> 0.72 | C70: 2018 INR | D70: =M6*(M36*'0 - Total Costs'!B12) -> 0 | E70: 1 | F70: =E70*D70*B70 -> 0 | G70: =F70/'0 - Total Costs'!$B$18 -> 0 | H70: =G70/(1+'0 - Total Costs'!$B$23)^(2018-$B$5) -> 0 | I70: =H70/(1+$B$13)^(2018-$B$5) -> 0 | J70: =I70*((1+'0 - Total Costs'!$B$23)^2) -> 0 | L70: 0 | M70: =1-L70 -> 1 | N70: =M70*J70 -> 0
A71: Exotel toll-free number service - 2018 | B71: =M38*'0 - Total Costs'!B14 -> 3.1637288 | C71: 2018 INR | D71: 1 | E71: 1 | F71: =E71*D71*B71 -> 3.1637288 | G71: =F71/'0 - Total Costs'!$B$18 -> 0.046260785 | H71: =G71/(1+'0 - Total Costs'!$B$23)^(2018-$B$5) -> 0.044464422 | I71: =H71/(1+$B$13)^(2018-$B$5) -> 0.036747456 | J71: =I71*((1+'0 - Total Costs'!$B$23)^2) -> 0.038232054 | L71: 0 | M71: =1-L71 -> 1 | N71: =M71*J71 -> 0.038232054
A72: Meeting costs (transportation, per-diem) - 2018 | B72: =SUM('0 - Total Costs'!B14*(Q11+Q12),'0 - Total Costs'!B14*Q13*Q15,'0 - Total Costs'!B14*Q14*Q16) -> 29.280593 | C72: 2018 INR | D72: 1 | E72: 1 | F72: =E72*D72*B72 -> 29.280593 | G72: =F72/'0 - Total Costs'!$B$18 -> 0.4281477 | H72: =G72/(1+'0 - Total Costs'!$B$23)^(2018-$B$5) -> 0.41152221 | I72: =H72/(1+$B$13)^(2018-$B$5) -> 0.340101 | J72: =I72*((1+'0 - Total Costs'!$B$23)^2) -> 0.35384108 | L72: 1 | M72: =1-L72 -> 0 | N72: =M72*J72 -> 0
A73: Server for SANA and tablet data - 2018 | B73: =Q24*'0 - Total Costs'!B14 -> 19.019322 | C73: 2018 INR | D73: 1 | E73: 1 | F73: =E73*D73*B73 -> 19.019322 | G73: =F73/'0 - Total Costs'!$B$18 -> 0.27810499 | H73: =G73/(1+'0 - Total Costs'!$B$23)^(2018-$B$5) -> 0.26730583 | I73: =H73/(1+$B$13)^(2018-$B$5) -> 0.22091391 | J73: =I73*((1+'0 - Total Costs'!$B$23)^2) -> 0.22983883 | L73: 1 | M73: =1-L73 -> 0 | N73: =M73*J73 -> 0
A74: Server for Survey CTO - 2018 | B74: =Q25*'0 - Total Costs'!B14 -> 19.742373 | C74: 2018 INR | D74: 1 | E74: 1 | F74: =E74*D74*B74 -> 19.742373 | G74: =F74/'0 - Total Costs'!$B$18 -> 0.28867761 | H74: =G74/(1+'0 - Total Costs'!$B$23)^(2018-$B$5) -> 0.2774679 | I74: =H74/(1+$B$13)^(2018-$B$5) -> 0.22931232 | J74: =I74*((1+'0 - Total Costs'!$B$23)^2) -> 0.23857653 | L74: 1 | M74: =1-L74 -> 0 | N74: =M74*J74 -> 0
A75: Monitoring travel - 2018 | B75: =Q33*'0 - Total Costs'!B14 -> 12.20339 | C75: 2018 INR | D75: 1 | E75: 1 | F75: =E75*D75*B75 -> 12.20339 | G75: =F75/'0 - Total Costs'!$B$18 -> 0.17844083 | H75: =G75/(1+'0 - Total Costs'!$B$23)^(2018-$B$5) -> 0.17151175 | I75: =H75/(1+$B$13)^(2018-$B$5) -> 0.14174525 | J75: =I75*((1+'0 - Total Costs'!$B$23)^2) -> 0.14747176 | L75: 1 | M75: =1-L75 -> 0 | N75: =M75*J75 -> 0
A76: Tablets for monitoring - 2018 | B76: =Q34*'0 - Total Costs'!B14 -> 628 | C76: 2018 INR | D76: 1 | E76: 1 | F76: =E76*D76*B76 -> 628 | G76: =F76/'0 - Total Costs'!$B$18 -> 9.1827633 | H76: =G76/(1+'0 - Total Costs'!$B$23)^(2018-$B$5) -> 8.8261854 | I76: =H76/(1+$B$13)^(2018-$B$5) -> 7.2943681 | J76: =I76*((1+'0 - Total Costs'!$B$23)^2) -> 7.5890606 | L76: 1 | M76: =1-L76 -> 0 | N76: =M76*J76 -> 0
I78: Total fixed cost | J78: =SUM(J47:J76) -> 220.37656
I79: Total fixed cost per month | J79: =J78/15 -> 14.69177
I81: Total fixed cost at scale | J81: =SUM(N47:N76) -> 53.360107
I82: Total fixed cost per unit at scale | J82: =J81/15 -> 3.5573405

Sheet Inflation Rates
D1: Year | E1: =E2&"y" -> 1990y | F1: =F2&"y" -> 1991y | G1: =G2&"y" -> 1992y | H1: =H2&"y" -> 1993y | I1: =I2&"y" -> 1994y | J1: =J2&"y" -> 1995y | K1: =K2&"y" -> 1996y | L1: =L2&"y" -> 1997y | ... XFD1: =XFD2&"y" -> y
A2: Indicator Name | B2: Indicator Code | C2: Country Name | D2: Country Code | E2: 1990 | F2: 1991 | G2: 1992 | H2: 1993 | I2: 1994 | J2: 1995 | K2: 1996 | L2: 1997 | M2: 1998 | N2: 1999 | O2: 2000 | P2: 2001 | Q2: 2002 | R2: 2003 | S2: 2004 | T2: 2005 | U2: 2006 | V2: 2007 | W2: 2008 | X2: 2009 | Y2: 2010 | Z2: 2011 | AA2: 2012 | AB2: 2013
A3: Inflation, GDP deflator (annual %) | B3: NY.GDP.DEFL.KD.ZG | C3: United States | D3: USA | E3: 3.699951 | F3: 3.3261335 | G3: 2.2804256 | H3: 2.379793 | I3: 2.1287896 | J3: 2.0859922 | K3: 1.8263571 | L3: 1.7109594 | M3: 1.0847572 | N3: 1.4281215 | O3: 2.2722091 | P3: 2.2911273 | Q3: 1.5366495 | R3: 1.9983867 | S3: 2.7412332 | T3: 3.2073946 | U3: 3.0741277 | V3: 2.6538814 | W3: 1.9534819 | X3: 0.7696854 | Y3: 1.2104686 | Z3: 1.9639198 | AA3: 1.7482852 | AB3: 1.5141203
A6: Inflation, GDP deflator (annual %) | B6: NY.GDP.DEFL.KD.ZG | C6: Afghanistan | D6: AFG | E6: .. | F6: .. | G6: .. | H6: .. | I6: .. | J6: .. | K6: .. | L6: .. | M6: .. | N6: .. | O6: .. | P6: .. | Q6: .. | R6: 11.715672 | S6: 11.242729 | T6: 10.900268 | U6: 7.1712607 | V6: 22.382016 | W6: 2.1791033 | X6: -2.1070825 | Y6: 9.4377948 | Z6: 10.561139 | AA6: 8.3047609 | AB6: 3.7689159
A7: Inflation, GDP deflator (annual %) | B7: NY.GDP.DEFL.KD.ZG | C7: Albania | D7: ALB | E7: -0.46870766 | F7: 38.568343 | G7: 249.68344 | H7: 114.83565 | I7: 38.416495 | J7: 5.5733074 | K7: 28.418483 | L7: 13.943101 | M7: 13.556008 | N7: 4.4760685 | O7: 4.3215111 | P7: 3.458281 | Q7: 3.3001959 | R7: 3.3834861 | S7: 6.0077447 | T7: 3.4692522 | U7: 1.9952412 | V7: 1.9893036 | W7: 3.6937272 | X7: 2.4722096 | Y7: 4.7019901 | Z7: 1.8632165 | AA7: 1.3628712 | AB7: 0.78968101
A8: Inflation, GDP deflator (annual %) | B8: NY.GDP.DEFL.KD.ZG | C8: Algeria | D8: DZA | E8: 30.259598 | F8: 53.788604 | G8: 21.926115 | H8: 13.624425 | I8: 29.077647 | J8: 28.577038 | K8: 24.021904 | L8: 7.0019631 | M8: -3.1310887 | N8: 10.856408 | O8: 24.598099 | P8: -2.0071939 | Q8: 1.3204322 | R8: 8.3307285 | S8: 12.247624 | T8: 16.125362 | U8: 10.546696 | V8: 6.3953443 | W8: 15.762769 | X8: -11.161591 | Y8: 16.119787 | Z8: 17.785503 | AA8: 5.6273442 | AB8: 2.5270381
A9: Inflation, GDP deflator (annual %) | B9: NY.GDP.DEFL.KD.ZG | C9: American Samoa | D9: ASM | E9: .. | F9: .. | G9: .. | H9: .. | I9: .. | J9: .. | K9: .. | L9: .. | M9: .. | N9: .. | O9: .. | P9: .. | Q9: .. | R9: .. | S9: .. | T9: .. | U9: .. | V9: .. | W9: .. | X9: .. | Y9: .. | Z9: .. | AA9: .. | AB9: ..
A10: Inflation, GDP deflator (annual %) | B10: NY.GDP.DEFL.KD.ZG | C10: Andorra | D10: ADO | E10: 7.3262512 | F10: 6.9351393 | G10: 6.7107714 | H10: 4.5372411 | I10: 3.8798421 | J10: 4.9331298 | K10: 0.79718278 | L10: 2.2281515 | M10: 1.4995616 | N10: 2.7319769 | O10: 4.5139798 | P10: 2.77 | Q10: 3.3999999 | R10: 2.88 | S10: 3.35 | T10: 3.1 | U10: 3.2 | V10: 3.87 | W10: 3.1850987 | X10: .. | Y10: .. | Z10: .. | AA10: .. | AB10: ..
A11: Inflation, GDP deflator (annual %) | B11: NY.GDP.DEFL.KD.ZG | C11: Angola | D11: AGO | E11: 10.858624 | F11: 165.39958 | G11: 252.7405 | H11: 1253.2806 | I11: 2124.6072 | J11: 1895.2065 | K11: 5399.5262 | L11: 94.319571 | M11: 35.316825 | N11: 556.93926 | O11: 418.23295 | P11: 106.32249 | Q11: 142.47819 | R11: 84.886475 | S11: 39.792942 | T11: 26.816294 | U11: 13.04118 | V11: 12.616432 | W11: 19.681609 | X11: -7.4188384 | Y11: 22.393924 | Z11: 24.167172 | AA11: 7.0276475 | AB11: 2.5111103
A12: Inflation, GDP deflator (annual %) | B12: NY.GDP.DEFL.KD.ZG | C12: Antigua and Barbuda | D12: ATG | E12: 2.2624687 | F12: 2.7142022 | G12: 2.3904149 | H12: 2.2240747 | I12: 3.020839 | J12: 3.1268992 | K12: 2.5750158 | L12: 2.1747109 | M12: 2.4160861 | N12: 0.96955078 | O12: 14.975686 | P12: 1.9910954 | Q12: 0.70700551 | R12: -1.2067408 | S12: 1.5892508 | T12: 4.3219409 | U12: 0.33413296 | V12: 3.7246722 | W12: 4.4479527 | X12: 1.7712865 | Y12: 1.4138879 | Z12: 1.2813743 | AA12: 2.5513272 | AB12: 2.3450641
A13: Inflation, GDP deflator (annual %) | B13: NY.GDP.DEFL.KD.ZG | C13: Argentina | D13: ARG | E13: 2076.7935 | F13: 132.95323 | G13: 11.92076 | H13: -1.4666599 | I13: 24.587524 | J13: 3.1651236 | K13: -0.052376507 | L13: -0.46391279 | M13: -1.7052792 | N13: -1.8365582 | O13: 1.0372869 | P13: -1.0957672 | Q13: 30.555203 | R13: 10.495702 | S13: 7.9257364 | T13: 10.620156 | U13: 15.28385 | V13: 17.63826 | W13: 21.213723 | X13: 9.8845046 | Y13: 17.513685 | Z13: 17.204583 | AA13: 18.055141 | AB13: 18.543698
A14: Inflation, GDP deflator (annual %) | B14: NY.GDP.DEFL.KD.ZG | C14: Armenia | D14: ARM | E14: .. | F14: 79.386104 | G14: 568.80733 | H14: 1391.1665 | I14: 4107.2968 | J14: 161.16392 | K14: 19.59177 | L14: 17.735995 | M14: 10.698498 | N14: 0.053804078 | O14: -1.373676 | P14: 4.0691399 | Q14: 2.3697878 | R14: 4.5610984 | S14: 6.3095327 | T14: 3.2398363 | U14: 4.6198577 | V14: 4.2327704 | W14: 5.9895624 | X14: 2.5569351 | Y14: 7.7687155 | Z14: 4.28155 | AA14: -1.2157086 | AB14: 3.1913884
A15: Inflation, GDP deflator (annual %) | B15: NY.GDP.DEFL.KD.ZG | C15: Aruba | D15: ABW | E15: .. | F15: .. | G15: .. | H15: .. | I15: .. | J15: -1.9349795 | K15: -3.0891098 | L15: 4.0739304 | M15: 7.4754938 | N15: -1.0192115 | O15: 9.1427411 | P15: 4.7662208 | Q15: 0.61671322 | R15: -3.1505348 | S15: 8.9577248 | T15: 4.2136963 | U15: 1.4908946 | V15: 12.462489 | W15: 14.275706 | X15: -5.1320556 | Y15: .. | Z15: .. | AA15: .. | AB15: ..
A16: Inflation, GDP deflator (annual %) | B16: NY.GDP.DEFL.KD.ZG | C16: Australia | D16: AUS | E16: 5.1478376 | F16: 2.6393887 | G16: 1.6730756 | H16: 0.76884958 | I16: 1.0250911 | J16: 2.4482731 | K16: 2.6763353 | L16: 1.2251342 | M16: 1.2784561 | N16: 0.33458501 | O16: 2.5635191 | P16: 4.7047498 | Q16: 2.8655882 | R16: 3.1134022 | S16: 3.2835446 | T16: 3.7079639 | U16: 5.0586325 | V16: 4.9825597 | W16: 4.5384532 | X16: 4.9317299 | Y16: 1.0102778 | Z16: 6.1356205 | AA16: 1.9588802 | AB16: -0.29103246
A17: Inflation, GDP deflator (annual %) | B17: NY.GDP.DEFL.KD.ZG | C17: Austria | D17: AUT | E17: 2.9996804 | F17: 3.6418715 | G17: 3.4790931 | H17: 2.7570846 | I17: 2.5249429 | J17: 1.813918 | K17: 0.81197607 | L17: -0.22090193 | M17: 0.32032606 | N17: 0.28342109 | O17: 0.91921702 | P17: 1.8738007 | Q17: 1.239627 | R17: 1.1496102 | S17: 1.683295 | T17: 2.0391816 | U17: 1.8844718 | V17: 2.0048146 | W17: 1.7228742 | X17: 1.5775652 | Y17: 1.4407855 | Z17: 2.0435017 | AA17: 1.7089737 | AB17: 1.6170558
A18: Inflation, GDP deflator (annual %) | B18: NY.GDP.DEFL.KD.ZG | C18: Azerbaijan | D18: AZE | E18: .. | F18: 83.549512 | G18: 1065.3292 | H18: 747.56698 | I18: 1385.202 | J18: 545.6953 | K18: 26.421013 | L18: 9.2402137 | M18: -0.96393089 | N18: 2.1610078 | O18: 12.493369 | P18: 2.5150101 | Q18: 3.1193184 | R18: 6.0086142 | S18: 8.3151767 | T18: 16.139422 | U18: 11.301397 | V18: 20.98171 | W18: 27.761953 | X18: -18.929731 | Y18: 13.756553 | Z18: 22.566087 | AA18: 1.4413445 | AB18: 1.0210666
A19: Inflation, GDP deflator (annual %) | B19: NY.GDP.DEFL.KD.ZG | C19: Bahamas, The | D19: BHS | E19: 5.0737112 | F19: 2.5565382 | G19: 3.9055659 | H19: -0.85198361 | I19: 2.1833662 | J19: 0.80243636 | K19: 0.98424379 | L19: 34.687616 | M19: 3.0493128 | N19: 4.9509405 | O19: 0.92183066 | P19: 0.35359062 | Q19: 3.9608188 | R19: 1.1546133 | S19: 1.1944872 | T19: 5.0568275 | U19: 0.82796732 | V19: 2.9475256 | W19: 1.4888899 | X19: -1.0365421 | Y19: -0.12152524 | Z19: -1.8256277 | AA19: 1.648792 | AB19: ..
A20: Inflation, GDP deflator (annual %) | B20: NY.GDP.DEFL.KD.ZG | C20: Bahrain | D20: BHR | E20: 4.8266931 | F20: -1.8825275 | G20: -3.5326488 | H20: -3.025817 | I20: 7.3311889 | J20: 1.0906712 | K20: 0.19672117 | L20: 0.93171529 | M20: -7.0574088 | N20: 2.6564307 | O20: 29.991486 | P20: -3.3638767 | Q20: 3.5646423 | R20: 8.4449435 | S20: 10.991078 | T20: 13.734991 | U20: 8.8423562 | V20: 8.4356733 | W20: 11.373776 | X20: -12.998703 | Y20: 7.4385878 | Z20: 10.63034 | AA20: 1.1006975 | AB20: 2.3694171
A21: Inflation, GDP deflator (annual %) | B21: NY.GDP.DEFL.KD.ZG | C21: Bangladesh | D21: BGD | E21: 6.3355972 | F21: 6.5962352 | G21: 2.9763698 | H21: 0.28696994 | I21: 3.7718272 | J21: 7.3453322 | K21: 4.2345036 | L21: 3.0900972 | M21: 5.2743663 | N21: 4.6557307 | O21: 1.8596609 | P21: 1.5853946 | Q21: 3.1953751 | R21: 4.5276296 | S21: 4.2404288 | T21: 5.0747149 | U21: 5.1723735 | V21: 6.7864503 | W21: 8.7891012 | X21: 6.5209543 | Y21: 6.4736227 | Z21: 7.5319114 | AA21: 8.4801147 | AB21: 6.6233843
A22: Inflation, GDP deflator (annual %) | B22: NY.GDP.DEFL.KD.ZG | C22: Barbados | D22: BRB | E22: 24.740742 | F22: 2.1742885 | G22: 1.7176882 | H22: 4.4446092 | I22: 1.1174457 | J22: 3.6007715 | K22: 4.7067636 | L22: -0.65504454 | M22: 8.301261 | N22: 2.1379519 | O22: 0.67065958 | P22: 2.3817192 | Q22: 1.1271126 | R22: 1.2404815 | S22: 5.7748824 | T22: 6.6171789 | U22: 4.8736436 | V22: 2.8980939 | W22: 0.28292564 | X22: 5.492194 | Y22: -3.705047 | Z22: -2.2033191 | AA22: -3.306155 | AB22: ..
A23: Inflation, GDP deflator (annual %) | B23: NY.GDP.DEFL.KD.ZG | C23: Belarus | D23: BLR | E23: .. | F23: 103.59791 | G23: 1074.1412 | H23: 1053.449 | I23: 1945.1071 | J23: 661.493 | K23: 53.715001 | L23: 71.649451 | M23: 76.580409 | N23: 316.79333 | O23: 185.2908 | P23: 79.534573 | Q23: 44.893739 | R23: 30.685321 | S23: 22.675123 | T23: 18.927696 | U23: 10.750637 | V23: 12.823553 | W23: 21.160491 | X23: 5.7222859 | Y23: 11.071486 | Z23: 71.179529 | AA23: 75.438581 | AB23: 19.002897
A24: Inflation, GDP deflator (annual %) | B24: NY.GDP.DEFL.KD.ZG | C24: Belgium | D24: BEL | E24: 2.8124032 | F24: 2.8766246 | G24: 3.4245245 | H24: 3.9932318 | I24: 2.0943051 | J24: 1.2207694 | K24: 0.37235765 | L24: 0.87104965 | M24: 1.8702952 | N24: 0.31387861 | O24: 1.9787055 | P24: 2.0505637 | Q24: 2.0067862 | R24: 1.9829917 | S24: 2.1345637 | T24: 2.3777128 | U24: 2.3441939 | V24: 2.375905 | W24: 2.1383592 | X24: 1.1864466 | Y24: 2.0530829 | Z24: 1.9958346 | AA24: 1.9323239 | AB24: 1.6200574
A25: Inflation, GDP deflator (annual %) | B25: NY.GDP.DEFL.KD.ZG | C25: Belize | D25: BLZ | E25: 2.8132817 | F25: -2.5607132 | G25: 3.9934962 | H25: 1.6515198 | I25: 3.588105 | J25: 6.0789813 | K25: 1.9687101 | L25: -1.4770146 | M25: 1.5030976 | N25: -2.235249 | O25: 0.43700258 | P25: -0.18627188 | Q25: 1.7687458 | R25: -2.8771609 | S25: 2.0714008 | T25: 2.287547 | U25: 4.3642885 | V25: 4.7484166 | W25: 2.1565753 | X25: -2.5499769 | Y25: 0.60822354 | Z25: 5.0736256 | AA25: 1.5288662 | AB25: 1.3374336
A26: Inflation, GDP deflator (annual %) | B26: NY.GDP.DEFL.KD.ZG | C26: Benin | D26: BEN | E26: 2.1765969 | F26: 0.75662014 | G26: 3.0251345 | H26: 2.3783218 | I26: 35.030113 | J26: 15.099452 | K26: 6.9072937 | L26: 3.6675092 | M26: 5.2316047 | N26: 0.43636213 | O26: 4.5260527 | P26: 2.6600425 | Q26: 2.2919259 | R26: 1.7011314 | S26: 0.37749952 | T26: 4.4239216 | U26: 3.1563457 | V26: 2.5217255 | W26: 7.1852792 | X26: 1.9561074 | Y26: 1.8641879 | Z26: 2.358015 | AA26: 6.1438549 | AB26: 0.91829512
A27: Inflation, GDP deflator (annual %) | B27: NY.GDP.DEFL.KD.ZG | C27: Bermuda | D27: BMU | E27: 6.0335723 | F27: 6.4305905 | G27: 2.813884 | H27: 5.1963043 | I27: 1.9595642 | J27: 4.1784635 | K27: 29.3647 | L27: 4.0239039 | M27: 2.7415512 | N27: 2.7121495 | O27: -4.2363554 | P27: -1.3691962 | Q27: 8.580442 | R27: 2.82474 | S27: 4.6921434 | T27: 6.7623737 | U27: 5.3771711 | V27: 5.8664058 | W27: 2.0853376 | X27: 0.33366495 | Y27: 1.0489075 | Z27: -0.032572528 | AA27: 3.6551254 | AB27: ..
A28: Inflation, GDP deflator (annual %) | B28: NY.GDP.DEFL.KD.ZG | C28: Bhutan | D28: BTN | E28: 5.7088499 | F28: 8.7641477 | G28: 9.2967574 | H28: 8.1864621 | I28: 12.851991 | J28: 8.0478193 | K28: 8.0561273 | L28: 12.485398 | M28: 10.50963 | N28: 7.4353082 | O28: 2.2862093 | P28: 5.2663086 | Q28: 4.8812172 | R28: 3.0850745 | S28: 3.7909328 | T28: 5.857934 | U28: 5.411195 | V28: 3.1106604 | W28: 5.6530725 | X28: 4.8512511 | Y28: 5.9855106 | Z28: 9.1669159 | AA28: 10.650446 | AB28: 5.7161497
A29: Inflation, GDP deflator (annual %) | B29: NY.GDP.DEFL.KD.ZG | C29: Bolivia | D29: BOL | E29: 16.267938 | F29: 17.689443 | G29: 13.199204 | H29: 6.5571577 | I29: 7.9522082 | J29: 11.427281 | K29: 11.580209 | L29: 5.7050425 | M29: 7.0511278 | N29: 2.4115657 | O29: 5.1954044 | P29: 1.8700947 | Q29: 2.8207575 | R29: 6.329992 | S29: 7.9677087 | T29: 5.9407973 | U29: 13.66368 | V29: 7.3733536 | W29: 10.381182 | X29: -2.4198942 | Y29: 8.7775081 | Z29: 14.565892 | AA29: 6.914597 | AB29: 6.0077679
A30: Inflation, GDP deflator (annual %) | B30: NY.GDP.DEFL.KD.ZG | C30: Bosnia and Herzegovina | D30: BIH | E30: .. | F30: .. | G30: .. | H30: .. | I30: .. | J30: 8.8474311 | K30: -17.056763 | L30: 13.011481 | M30: -1.5819249 | N30: 8.3556508 | O30: 28.790136 | P30: 2.9619625 | Q30: 4.4615831 | R30: 0.91238477 | S30: 2.5724976 | T30: 3.8776273 | U30: 5.7284902 | V30: 5.7177923 | W30: 7.5565844 | X30: 0.051945393 | Y30: 2.2859525 | Z30: 2.3309419 | AA30: 0.60297475 | AB30: 1.9977767
A31: Inflation, GDP deflator (annual %) | B31: NY.GDP.DEFL.KD.ZG | C31: Botswana | D31: BWA | E31: 6.3000182 | F31: 5.1777104 | G31: 6.6392807 | H31: 13.0647 | I31: 9.4638049 | J31: 7.1552948 | K31: 16.112195 | L31: 5.2815377 | M31: 9.6633934 | N31: 14.235208 | O31: 14.170967 | P31: 8.3128251 | Q31: 1.1873707 | R31: 3.2590844 | S31: 10.078789 | T31: 15.471707 | U31: 7.875649 | V31: 4.5361282 | W31: 8.734782 | X31: 3.428869 | Y31: 18.921544 | Z31: 5.4546543 | AA31: 1.5946057 | AB31: 5.9064544
A32: Inflation, GDP deflator (annual %) | B32: NY.GDP.DEFL.KD.ZG | C32: Brazil | D32: BRA | E32: 2735.4885 | F32: 414.2356 | G32: 968.18423 | H32: 2001.3482 | I32: 2251.704 | J32: 93.522004 | K32: 17.085269 | L32: 7.6450029 | M32: 4.2359035 | N32: 8.4764493 | O32: 6.1778398 | P32: 8.9661797 | Q32: 10.555805 | R32: 13.726476 | S32: 8.0362173 | T32: 7.2129981 | U32: 6.1514402 | V32: 5.8645301 | W32: 8.3349497 | X32: 7.1851465 | Y32: 8.2285351 | Z32: 6.9688848 | AA32: 4.9293577 | AB32: 7.6255921
A33: Inflation, GDP deflator (annual %) | B33: NY.GDP.DEFL.KD.ZG | C33: Brunei Darussalam | D33: BRN | E33: 8.4099635 | F33: -2.8372807 | G33: 1.7268761 | H33: -2.9514906 | I33: -8.7636259 | J33: 2.8729978 | K33: 4.4887553 | L33: 8.5848536 | M33: -11.648574 | N33: 11.593978 | O33: 29.015709 | P33: -5.591899 | Q33: 0.37420917 | R33: 6.1046113 | S33: 15.886165 | T33: 18.76632 | U33: 10.047721 | V33: 1.120448 | W33: 12.69273 | X33: -22.091416 | Y33: 5.3087402 | Z33: 20.351114 | AA33: -0.048589631 | AB33: -3.1529121
A34: Inflation, GDP deflator (annual %) | B34: NY.GDP.DEFL.KD.ZG | C34: Bulgaria | D34: BGR | E34: 26.18799 | F34: 226.53787 | G34: 59.578649 | H34: 51.091054 | I34: 72.704969 | J34: 62.376649 | K34: 98.030635 | L34: 987.07049 | M34: 29.672229 | N34: 3.694683 | O34: 6.6300326 | P34: 6.1281009 | Q34: 4.6206137 | R34: 2.277877 | S34: 4.2199104 | T34: 7.3430637 | U34: 6.901073 | V34: 9.2335361 | W34: 8.4157098 | X34: 4.3335496 | Y34: 2.7937159 | Z34: 4.9142571 | AA34: 3.0738571 | AB34: -0.85765163
A35: Inflation, GDP deflator (annual %) | B35: NY.GDP.DEFL.KD.ZG | C35: Burkina Faso | D35: BFA | E35: 1.8100154 | F35: -3.9677808 | G35: 0.22705961 | H35: -1.4418398 | I35: 14.638962 | J35: 6.769569 | K35: 0.34870515 | L35: 1.5561999 | M35: 7.940316 | N35: 4.4364839 | O35: -1.6646694 | P35: 4.0661418 | Q35: 3.0569861 | R35: 1.4847288 | S35: 0.09064859 | T35: 3.7393854 | U35: -0.65963185 | V35: 2.2585138 | W35: 9.1619456 | X35: 2.3764028 | Y35: 7.1985968 | Z35: 3.2026759 | AA35: 1.9134616 | AB35: -1.9091507
A36: Inflation, GDP deflator (annual %) | B36: NY.GDP.DEFL.KD.ZG | C36: Burundi | D36: BDI | E36: 5.9855615 | F36: 4.0931408 | G36: 5.4017607 | H36: 7.7426457 | I36: 6.6384455 | J36: 16.102712 | K36: 14.453111 | L36: 32.397789 | M36: 11.450556 | N36: 14.95414 | O36: 38.944893 | P36: 13.716407 | Q36: 1.0278586 | R36: 11.945749 | S36: 13.146159 | T36: 18.856933 | U36: 2.845128 | V36: 6.9018753 | W36: 23.990943 | X36: 8.2473529 | Y36: 12.303296 | Z36: 14.294338 | AA36: 15.416499 | AB36: 13.452353
A37: Inflation, GDP deflator (annual %) | B37: NY.GDP.DEFL.KD.ZG | C37: Cambodia | D37: KHM | E37: 2.3453103 | F37: 4.7924188 | G37: -4.1158446 | H37: 49.354086 | I37: -29.172462 | J37: -1.5468995 | K37: -0.54613589 | L37: -0.83529133 | M37: -0.33599077 | N37: 7.6120783 | O37: -7.9011035 | P37: 5.1553351 | Q37: -0.36320894 | R37: 4.9210998 | S37: -6.332547 | T37: -1.7948832 | U37: 4.639771 | V37: 8.751419 | W37: 3.5459326 | X37: 2.1745981 | Y37: 0.50496457 | Z37: 2.6765122 | AA37: 0.64858299 | AB37: 3.4825689
A38: Inflation, GDP deflator (annual %) | B38: NY.GDP.DEFL.KD.ZG | C38: Cameroon | D38: CMR | E38: .. | F38: .. | G38: .. | H38: .. | I38: -4.41424 | J38: 11.515505 | K38: 3.5067149 | L38: 4.3860194 | M38: 10.01366 | N38: 1.981472 | O38: -3.2036247 | P38: 2.6428281 | Q38: 0.71614401 | R38: 1.7975225 | S38: 4.8237384 | T38: 6.0766799 | U38: 4.6299188 | V38: 6.5192442 | W38: 12.253787 | X38: 2.5043847 | Y38: 3.1205929 | Z38: 3.3640662 | AA38: 1.4405181 | AB38: 0.82821486
A39: Inflation, GDP deflator (annual %) | B39: NY.GDP.DEFL.KD.ZG | C39: Canada | D39: CAN | E39: 1.6430984 | F39: 3.5687135 | G39: -1.277671 | H39: 16.098656 | I39: 14.383143 | J39: 9.4843054 | K39: 2.6923792 | L39: 3.7377422 | M39: 3.6622322 | N39: 1.9485677 | O39: 2.8400676 | P39: 2.1785001 | Q39: 3.247868 | R39: 0.35809872 | S39: 1.5079707 | T39: 2.6312118 | U39: 3.9414724 | V39: 1.4311312 | W39: 4.7444412 | X39: -3.3385516 | Y39: 3 | Z39: 3.6991727 | AA39: 7.4355885 | AB39: 1.4354772
A40: Inflation, GDP deflator (annual %) | B40: NY.GDP.DEFL.KD.ZG | C40: Cape Verde | D40: CPV | E40: 3.3751796 | F40: 3.0711924 | G40: 1.4905335 | H40: 1.3228816 | I40: 1.4469047 | J40: 2.2384476 | K40: 1.756461 | L40: 1.1410801 | M40: -0.20737964 | N40: 1.8610517 | O40: 4.2723608 | P40: 1.6230619 | Q40: 1.2274263 | R40: 3.335092 | S40: 3.279353 | T40: 3.2088703 | U40: 2.7092892 | V40: 3.2384435 | W40: 3.8924299 | X40: -2.1442546 | Y40: 2.6468104 | Z40: 3.2388912 | AA40: 1.66904 | AB40: 1.2359855
A41: Inflation, GDP deflator (annual %) | B41: NY.GDP.DEFL.KD.ZG | C41: Cayman Islands | D41: CYM | E41: .. | F41: .. | G41: .. | H41: .. | I41: 3.0978032 | J41: .. | K41: .. | L41: .. | M41: .. | N41: .. | O41: .. | P41: .. | Q41: .. | R41: .. | S41: .. | T41: .. | U41: .. | V41: .. | W41: .. | X41: .. | Y41: .. | Z41: .. | AA41: .. | AB41: ..
A42: Inflation, GDP deflator (annual %) | B42: NY.GDP.DEFL.KD.ZG | C42: Central African Republic | D42: CAF | E42: 1.8367641 | F42: -0.38993188 | G42: 2.7826648 | H42: -3.4328953 | I42: 24.412511 | J42: 9.8980202 | K42: -3.5431378 | L42: 0.82331721 | M42: -0.41401283 | N42: 4.0846873 | O42: 8.5066207 | P42: 0.42589674 | Q42: -2.3718307 | R42: 1.3364015 | S42: -4.4398828 | T42: 5.1965653 | U42: 0.55077189 | V42: -2.3203694 | W42: 5.1480171 | X42: -3.3569916 | Y42: -1.4238785 | Z42: 1.9626477 | AA42: 2.7063442 | AB42: 7.163029
A43: Inflation, GDP deflator (annual %) | B43: NY.GDP.DEFL.KD.ZG | C43: Chad | D43: TCD | E43: 8.012329 | F43: 3.073499 | G43: -12.906554 | H43: -1.3146037 | I43: 43.544964 | J43: 8.8331273 | K43: 11.458455 | L43: 3.7827855 | M43: 6.7494088 | N43: -7.5728663 | O43: 5.2898049 | P43: 13.797653 | Q43: 1.9078194 | R43: 0.079004696 | S43: 9.7342565 | T43: 28.111934 | U43: 9.9844279 | V43: 3.3019343 | W43: 8.6488198 | X43: -9.5587545 | Y43: 6.3911951 | Z43: 8.580399 | AA43: 5.3395942 | AB43: -2.7736093
A44: Inflation, GDP deflator (annual %) | B44: NY.GDP.DEFL.KD.ZG | C44: Channel Islands | D44: CHI | E44: .. | F44: .. | G44: .. | H44: .. | I44: .. | J44: .. | K44: .. | L44: .. | M44: .. | N44: 3.909631 | O44: 3.8923176 | P44: 3.3016355 | Q44: 4.3827256 | R44: 4.3537155 | S44: 3.7975713 | T44: 2.5047097 | U44: 3.2789316 | V44: 3.3363333 | W44: .. | X44: .. | Y44: .. | Z44: .. | AA44: .. | AB44: ..
A45: Inflation, GDP deflator (annual %) | B45: NY.GDP.DEFL.KD.ZG | C45: Chile | D45: CHL | E45: 22.459259 | F45: 22.435127 | G45: 12.893196 | H45: 11.750306 | I45: 13.730796 | J45: 10.420668 | K45: 2.7274605 | L45: 4.2700102 | M45: 1.9260726 | N45: 2.4316653 | O45: 10.278221 | P45: 3.8428912 | Q45: 4.2178428 | R45: 5.8608089 | S45: 7.4776597 | T45: 7.5523257 | U45: 12.809675 | V45: 4.8437536 | W45: 0.47302641 | X45: 3.8422459 | Y45: 8.8293547 | Z45: 3.3307278 | AA45: 1.3009312 | AB45: 1.7277448
A46: Inflation, GDP deflator (annual %) | B46: NY.GDP.DEFL.KD.ZG | C46: China | D46: CHN | E46: 5.5708007 | F46: 12.365635 | G46: 13.215139 | H46: 14.878793 | I46: 19.692506 | J46: 11.543082 | K46: 5.5477656 | L46: 0.85915079 | M46: -2.2161861 | N46: -1.4687316 | O46: 2.8020378 | P46: 2.052582 | Q46: 0.60073302 | R46: 2.5878772 | S46: 6.9273444 | T46: 3.9203811 | U46: 3.8071647 | V46: 7.6374153 | W46: 7.7637638 | X46: -0.60626578 | Y46: 6.6387203 | Z46: 7.8046689 | AA46: 1.9951583 | AB46: 1.7030632
A47: Inflation, GDP deflator (annual %) | B47: NY.GDP.DEFL.KD.ZG | C47: Colombia | D47: COL | E47: 26.105139 | F47: 26.187814 | G47: 22.225955 | H47: 27.95354 | I47: 45.357061 | J47: 18.850957 | K47: 16.868379 | L47: 16.839853 | M47: 14.773045 | N47: 12.622941 | O47: 31.761348 | P47: 6.5184483 | Q47: 5.9681906 | R47: 6.8290148 | S47: 7.2830334 | T47: 5.5575412 | U47: 5.7750911 | V47: 5.0397573 | W47: 7.5556995 | X47: 3.4079069 | Y47: 3.8562589 | Z47: 6.7252117 | AA47: 3.1701601 | AB47: 1.8604508
A48: Inflation, GDP deflator (annual %) | B48: NY.GDP.DEFL.KD.ZG | C48: Comoros | D48: COM | E48: 2.1751823 | F48: 8.1194391 | G48: -6.7646903 | H48: 2.8330009 | I48: 9.4167852 | J48: 8.3207386 | K48: 3.1990915 | L48: 0.92383158 | M48: 1.3463855 | N48: 5.8116548 | O48: 3.4264455 | P48: 8.6308125 | Q48: 4.1706883 | R48: 5.1247938 | S48: 1.7706572 | T48: 2.2997626 | U48: 1.9998974 | V48: 5.1832448 | W48: 5.5059841 | X48: 4.5597843 | Y48: 4.3521331 | Z48: 4.6884125 | AA48: 2.5897775 | AB48: 3.1141119
A49: Inflation, GDP deflator (annual %) | B49: NY.GDP.DEFL.KD.ZG | C49: Congo, Dem. Rep. | D49: ZAR | E49: 108.95531 | F49: 2202.2899 | G49: 4078.4763 | H49: 1662.4167 | I49: 26762.018 | J49: 466.40724 | K49: 638.18883 | L49: 192.64284 | M49: 26.935377 | N49: 441.90249 | O49: 2630.1227 | P49: 73.059711 | Q49: 31.719461 | R49: 13.415454 | S49: 6.3654583 | T49: 29.869547 | U49: 12.106683 | V49: 18.868968 | W49: 19.584885 | X49: 33.8548 | Y49: 17.406683 | Z49: 10.289402 | AA49: 7.5309486 | AB49: 2.8518866
A50: Inflation, GDP deflator (annual %) | B50: NY.GDP.DEFL.KD.ZG | C50: Congo, Rep. | D50: COG | E50: -1.0290683 | F50: -1.4806357 | G50: -1.5692684 | H50: -1.1308286 | I50: 36.752826 | J50: 3.3959295 | K50: 17.991924 | L50: 4.9645177 | M50: -18.22209 | N50: 29.355342 | O50: 47.040083 | P50: -13.925208 | Q50: -1.7389276 | R50: -4.2515369 | S50: 16.807238 | T50: 21.329454 | U50: 18.519373 | V50: 1.1224529 | W50: 25.027646 | X50: -20.62722 | Y50: 20.722029 | Z50: 10.670333 | AA50: -1.1699616 | AB50: -3.5058045
A51: Inflation, GDP deflator (annual %) | B51: NY.GDP.DEFL.KD.ZG | C51: Costa Rica | D51: CRI | E51: 17.113174 | F51: 26.148285 | G51: 20.48121 | H51: 10.623454 | I51: 15.548364 | J51: 22.192483 | K51: 15.797795 | L51: 14.894698 | M51: 12.125615 | N51: 14.973829 | O51: 6.9765333 | P51: 8.6003905 | Q51: 9.1822875 | R51: 8.2876629 | S51: 11.84563 | T51: 10.623635 | U51: 10.99948 | V51: 9.3840216 | W51: 12.397409 | X51: 8.380179 | Y51: 7.9609137 | Z51: 4.5351425 | AA51: 4.088459 | AB51: 5.004324
A52: Inflation, GDP deflator (annual %) | B52: NY.GDP.DEFL.KD.ZG | C52: Cote d'Ivoire | D52: CIV | E52: -4.5232735 | F52: 0.66348927 | G52: -0.023837136 | H52: 6.1541943 | I52: 46.386069 | J52: 11.04379 | K52: 4.9830846 | L52: 4.2177761 | M52: 5.2189283 | N52: 0.91720176 | O52: -0.37928024 | P52: 4.2477313 | Q52: 5.0734634 | R52: 1.3028299 | S52: 0.62715203 | T52: 4.2270406 | U52: 4.4988979 | V52: 2.7124296 | W52: 8.1217855 | X52: 0.11385566 | Y52: 1.9319232 | Z52: 5.0271499 | AA52: 1.2966903 | AB52: 11.480385
A53: Inflation, GDP deflator (annual %) | B53: NY.GDP.DEFL.KD.ZG | C53: Croatia | D53: HRV | E53: .. | F53: .. | G53: .. | H53: .. | I53: .. | J53: .. | K53: 3.8469858 | L53: 7.135076 | M53: 8.2041127 | N53: 3.8128927 | O53: 4.6049624 | P53: 4.1482394 | Q53: 3.5340312 | R53: 4.0547841 | S53: 3.7942839 | T53: 3.3464131 | U53: 4.0143331 | V53: 4.100214 | W53: 5.6839715 | X53: 2.8533051 | Y53: 0.8104048 | Z53: 1.7614417 | AA53: 1.8509812 | AB53: 0.9147826
A54: Inflation, GDP deflator (annual %) | B54: NY.GDP.DEFL.KD.ZG | C54: Cuba | D54: CUB | E54: 5.2612744 | F54: -7.387843 | G54: 3.7457209 | H54: 18.975492 | I54: 26.282032 | J54: 10.508667 | K54: -2.6718847 | L54: -1.3526964 | M54: 1.3024618 | N54: 3.7881249 | O54: 1.7369797 | P54: 0.46117588 | Q54: 4.5260104 | R54: 2.9760424 | S54: 0.60428706 | T54: 0.38141169 | U54: 10.363211 | V54: 3.5904433 | W54: -0.34401626 | X54: 0.63425831 | Y54: 1.2067421 | Z54: 3.2724537 | AA54: .. | AB54: ..
A55: Inflation, GDP deflator (annual %) | B55: NY.GDP.DEFL.KD.ZG | C55: Curacao | D55: CUW | E55: .. | F55: .. | G55: .. | H55: .. | I55: .. | J55: .. | K55: .. | L55: .. | M55: .. | N55: .. | O55: .. | P55: .. | Q55: .. | R55: .. | S55: .. | T55: .. | U55: .. | V55: .. | W55: .. | X55: .. | Y55: .. | Z55: .. | AA55: .. | AB55: ..
A56: Inflation, GDP deflator (annual %) | B56: NY.GDP.DEFL.KD.ZG | C56: Cyprus | D56: CYP | E56: 5.4331257 | F56: 3.8880067 | G56: 6.0413821 | H56: 4.803134 | I56: 5.27098 | J56: 8.0427502 | K56: 2.2897929 | L56: 2.438376 | M56: 2.9402153 | N56: 2.3485635 | O56: 3.819324 | P56: 3.3739603 | Q56: 1.1938099 | R56: 5.0852583 | S56: 3.2268371 | T56: 2.3876103 | U56: 2.979006 | V56: 4.6336305 | W56: 5.0570414 | X56: -0.31161306 | Y56: 1.740049 | Z56: 1.9569019 | AA56: 1.5546628 | AB56: ..
A57: Inflation, GDP deflator (annual %) | B57: NY.GDP.DEFL.KD.ZG | C57: Czech Republic | D57: CZE | E57: .. | F57: 36.192388 | G57: 12.357263 | H57: 21.008803 | I57: 12.341967 | J57: 9.1073667 | K57: 9.871829 | L57: 7.9222635 | M57: 9.6309099 | N57: 2.5197988 | O57: 1.3721202 | P57: 4.6393942 | Q57: 2.6525904 | R57: 0.89629509 | S57: 4.0339313 | T57: -0.34880164 | U57: 0.53328296 | V57: 3.3202318 | W57: 1.9156075 | X57: 2.2863181 | Y57: -1.5815957 | Z57: -0.94357848 | AA57: 1.6268667 | AB57: 1.9364859
A58: Inflation, GDP deflator (annual %) | B58: NY.GDP.DEFL.KD.ZG | C58: Denmark | D58: DNK | E58: 2.8338652 | F58: 2.6753782 | G58: 1.6777373 | H58: 0.66532019 | I58: 1.5334739 | J58: 1.2568325 | K58: 2.0071198 | L58: 1.9884039 | M58: 1.1874343 | N58: 1.6812515 | O58: 2.9985628 | P58: 2.4962109 | Q58: 2.3031242 | R58: 1.6460747 | S58: 2.3257304 | T58: 2.8778868 | U58: 2.124598 | V58: 2.2788376 | W58: 4.231712 | X58: 0.6637465 | Y58: 4.2759427 | Z58: 0.72329911 | AA58: 2.2537149 | AB58: 1.37151
A59: Inflation, GDP deflator (annual %) | B59: NY.GDP.DEFL.KD.ZG | C59: Djibouti | D59: DJI | E59: .. | F59: 6.8000429 | G59: 3.3999712 | H59: 4.3999878 | I59: 6.5000047 | J59: 4.8860478 | K59: 3.512804 | L59: 2.5198926 | M59: 2.2045558 | N59: 2.0184356 | O59: 2.4 | P59: 1.7597048 | Q59: 0.6325246 | R59: 1.9682326 | S59: 3.1315535 | T59: 3.1213279 | U59: 3.5315659 | V59: 4.9292006 | W59: 11.370825 | X59: 14.293013 | Y59: -9.8808483 | Z59: 4.1832864 | AA59: 6.0539854 | AB59: 2.4647037
A60: Inflation, GDP deflator (annual %) | B60: NY.GDP.DEFL.KD.ZG | C60: Dominica | D60: DMA | E60: 3.0281731 | F60: 7.8308986 | G60: 4.1427125 | H60: 2.7878746 | I60: 5.9876555 | J60: 1.9675762 | K60: 2.8217806 | L60: 2.4220055 | M60: 0.16434834 | N60: 2.8954246 | O60: 28.38346 | P60: 2.0661735 | Q60: 0.95785954 | R60: -2.9520986 | S60: 4.5134087 | T60: -0.6486804 | U60: -3.4633604 | V60: 1.9213175 | W60: 1.6100886 | X60: 7.9982284 | Y60: -2.7041401 | Z60: 3.1669509 | AA60: 2.0375035 | AB60: 2.6595011
A61: Inflation, GDP deflator (annual %) | B61: NY.GDP.DEFL.KD.ZG | C61: Dominican Republic | D61: DOM | E61: 50.459253 | F61: 102.75464 | G61: 5.6167065 | H61: 5.0085655 | I61: 10.183855 | J61: 9.4044348 | K61: 3.4324055 | L61: 8.6612332 | M61: 6.0001311 | N61: 3.4795984 | O61: 6.9143735 | P61: 5.1081051 | Q61: 5.4717277 | R61: 33.633765 | S61: 45.191128 | T61: 2.6945583 | U61: 5.3996559 | V61: 5.7008573 | W61: 9.7676417 | X61: 2.9534006 | Y61: 5.1418078 | Z61: 6.6499369 | AA61: 5.2273476 | AB61: 5.1066438
A62: Inflation, GDP deflator (annual %) | B62: NY.GDP.DEFL.KD.ZG | C62: Ecuador | D62: ECU | E62: 5.8136292 | F62: 6.8893204 | G62: 4.3032294 | H62: 2.6417709 | I62: 15.008719 | J62: 5.2225532 | K62: 1.4901548 | L62: 7.006173 | M62: -3.7826792 | N62: -26.299993 | O62: -7.7140668 | P62: 28.414278 | Q62: 12.085274 | R62: 10.59309 | S62: 4.2618425 | T62: 7.732711 | U62: 8.0009108 | V62: 6.6505023 | W62: 13.847319 | X62: 0.65553756 | Y62: 4.8904084 | Z62: 5.4483646 | AA62: 4.1349325 | AB62: 3
A63: Inflation, GDP deflator (annual %) | B63: NY.GDP.DEFL.KD.ZG | C63: Egypt, Arab Rep. | D63: EGY | E63: 18.440607 | F63: 14.478572 | G63: 19.733419 | H63: 8.4291054 | I63: 8.4488716 | J63: 11.399741 | K63: 7.1076674 | L63: 9.8775515 | M63: 3.892273 | N63: 0.8699564 | O63: 4.9328671 | P63: 1.8677257 | Q63: 3.185448 | R63: 6.7774275 | S63: 11.669909 | T63: 6.2127285 | U63: 7.3599779 | V63: 12.59574 | W63: 12.203984 | X63: 11.172235 | Y63: 10.10751 | Z63: 11.665333 | AA63: 12.42313 | AB63: 8.9953997
A64: Inflation, GDP deflator (annual %) | B64: NY.GDP.DEFL.KD.ZG | C64: El Salvador | D64: SLV | E64: 4.7439793 | F64: 6.805293 | G64: 4.2557639 | H64: 8.5159018 | I64: 9.8919246 | J64: 10.43496 | K64: 6.7576491 | L64: 3.5445894 | M64: 3.9498465 | N64: 0.33904759 | O64: 3.1499069 | P64: 3.3996689 | Q64: 1.2073345 | R64: 2.8077834 | S64: 3.0874454 | T64: 4.4778958 | U64: 4.4374344 | V64: 4.370537 | W64: 5.2547201 | X64: -0.47475412 | Y64: 2.269601 | Z64: 5.6907931 | AA64: 1.0153701 | AB64: 0.19167841
A65: Inflation, GDP deflator (annual %) | B65: NY.GDP.DEFL.KD.ZG | C65: Equatorial Guinea | D65: GNQ | E65: 10.352527 | F65: 3.5521124 | G65: -15.423701 | H65: -2.6931154 | I65: 24.526347 | J65: 7.6808341 | K65: 0.82119633 | L65: -13.147174 | M65: -31.565915 | N65: 39.157626 | O65: 64.735022 | P65: -11.971527 | Q65: -1.5828903 | R65: 0.6356219 | S65: 16.922764 | T65: 42.646227 | U65: 14.406247 | V65: 2.2254728 | W65: 25.830797 | X65: -30.225506 | Y65: 31.264001 | Z65: 23.077392 | AA65: 9.9626692 | AB65: -3.8891683
A66: Inflation, GDP deflator (annual %) | B66: NY.GDP.DEFL.KD.ZG | C66: Eritrea | D66: ERI | E66: .. | F66: .. | G66: .. | H66: -1.38317 | I66: 10.432148 | J66: 9.8100406 | K66: 9.0748336 | L66: 3.8971519 | M66: 9.1091727 | N66: 2.3185616 | O66: 24.977595 | P66: 15.077269 | Q66: 16.148668 | R66: 21.872841 | S66: 24.799287 | T66: 7.6236895 | U66: 11.394003 | V66: 7.288209 | W66: 16.07622 | X66: 29.504507 | Y66: 11.573758 | Z66: 13.34085 | AA66: 10.794306 | AB66: 9.9240783
A67: Inflation, GDP deflator (annual %) | B67: NY.GDP.DEFL.KD.ZG | C67: Estonia | D67: EST | E67: .. | F67: .. | G67: .. | H67: .. | I67: 39.669014 | J67: 31.517058 | K67: 24.13619 | L67: 10.237948 | M67: 5.1502903 | N67: 6.7714639 | O67: 4.792986 | P67: 6.4779336 | Q67: 4.6864351 | R67: 4.0420795 | S67: 4.4580858 | T67: 6.0608444 | U67: 8.7725495 | V67: 11.639336 | W67: 5.4067079 | X67: 0.1687625 | Y67: 0.3006923 | Z67: 2.9958669 | AA67: 3.3223042 | AB67: 4.9826367
A68: Inflation, GDP deflator (annual %) | B68: NY.GDP.DEFL.KD.ZG | C68: Ethiopia | D68: ETH | E68: 3.2717334 | F68: 19.08377 | G68: 15.532493 | H68: 13.376353 | I68: 2.9308209 | J68: 12.70672 | K68: 0.23899345 | L68: 0.20664976 | M68: -0.15063523 | N68: 2.2230835 | O68: 9.4645617 | P68: -5.755372 | Q68: -3.621017 | R68: 12.767404 | S68: 3.911626 | T68: 9.8752908 | U68: 11.55209 | V68: 17.220835 | W68: 30.312487 | X68: 24.146079 | Y68: 1.444581 | Z68: 20.061867 | AA68: 34.34904 | AB68: 4.6125371
A69: Inflation, GDP deflator (annual %) | B69: NY.GDP.DEFL.KD.ZG | C69: Faeroe Islands | D69: FRO | E69: .. | F69: .. | G69: .. | H69: .. | I69: .. | J69: .. | K69: .. | L69: .. | M69: .. | N69: .. | O69: .. | P69: .. | Q69: .. | R69: .. | S69: .. | T69: .. | U69: .. | V69: .. | W69: .. | X69: .. | Y69: .. | Z69: .. | AA69: .. | AB69: ..
A70: Inflation, GDP deflator (annual %) | B70: NY.GDP.DEFL.KD.ZG | C70: Fiji | D70: FJI | E70: 6.6794721 | F70: 5.9931276 | G70: 6.2651334 | H70: 7.2367371 | I70: 0.84161086 | J70: 1.1569029 | K70: 2.8959918 | L70: 3.4506123 | M70: 7.4875809 | N70: 6.8110926 | O70: -4.6665241 | P70: 3.3610653 | Q70: 3.3190158 | R70: 7.8738303 | S70: 2.239113 | T70: 6.8177381 | U70: 3.7251067 | V70: 2.9550565 | W70: 4.4270199 | X70: 0.17468231 | Y70: 8.0125829 | Z70: 6.7992118 | AA70: 5.0011889 | AB70: -0.047931213
A71: Inflation, GDP deflator (annual %) | B71: NY.GDP.DEFL.KD.ZG | C71: Finland | D71: FIN | E71: 5.4288232 | F71: 1.5006398 | G71: 0.91893928 | H71: 1.9238448 | I71: 1.6371634 | J71: 4.5230874 | K71: -0.36379854 | L71: 1.9919101 | M71: 3.4124735 | N71: 0.9337678 | O71: 2.6095274 | P71: 3.0130016 | Q71: 1.2713219 | R71: -0.68636695 | S71: 0.48308248 | T71: 0.46126601 | U71: 0.84712964 | V71: 2.990147 | W71: 2.9452946 | X71: 1.4731455 | Y71: 0.34297866 | Z71: 2.7051421 | AA71: 2.9483123 | AB71: 1.9749533
A72: Inflation, GDP deflator (annual %) | B72: NY.GDP.DEFL.KD.ZG | C72: France | D72: FRA | E72: 2.7560425 | F72: 2.650573 | G72: 1.9300943 | H72: 1.7483339 | I72: 1.1250317 | J72: 1.2351105 | K72: 1.4604478 | L72: 0.91343163 | M72: 1.0347874 | N72: 0.17666794 | O72: 1.5727941 | P72: 2.0138678 | Q72: 2.2182463 | R72: 1.9974018 | S72: 1.6742579 | T72: 1.912226 | U72: 2.1407583 | V72: 2.5872997 | W72: 2.542074 | X72: 0.71604919 | Y72: 0.96084729 | Z72: 1.286611 | AA72: 1.5297712 | AB72: 1.1396178
A73: Inflation, GDP deflator (annual %) | B73: NY.GDP.DEFL.KD.ZG | C73: French Polynesia | D73: PYF | E73: 0.76436396 | F73: 1.4501747 | G73: 1.2715699 | H73: 2.0028435 | I73: 0.86732344 | J73: 1.141564 | K73: 1.468338 | L73: 0.98404423 | M73: 0.72591438 | N73: 0.93059325 | O73: 0.96153405 | P73: .. | Q73: .. | R73: .. | S73: .. | T73: .. | U73: .. | V73: .. | W73: .. | X73: .. | Y73: .. | Z73: .. | AA73: .. | AB73: ..
A74: Inflation, GDP deflator (annual %) | B74: NY.GDP.DEFL.KD.ZG | C74: Gabon | D74: GAB | E74: 15.358141 | F74: -11.366103 | G74: 0.21386696 | H74: -0.50948078 | I74: 46.551443 | J74: 1.3391155 | K74: 13.562677 | L74: 0.94653684 | M74: -17.786401 | N74: 19.191336 | O74: 28.089344 | P74: -6.2525934 | Q74: -0.24004332 | R74: -0.090206007 | S74: 6.3264941 | T74: 17.002102 | U74: 7.92687 | V74: 5.25431 | W74: 25.406763 | X74: -16.704593 | Y74: 19.043155 | Z74: 14.763967 | AA74: -2.7355856 | AB74: -0.92864089
A75: Inflation, GDP deflator (annual %) | B75: NY.GDP.DEFL.KD.ZG | C75: Gambia, The | D75: GMB | E75: 11.964533 | F75: 134.03587 | G75: 1.9500299 | H75: 5.1423238 | I75: 3.7773964 | J75: 3.9632499 | K75: 8.3685692 | L75: -5.9691191 | M75: 5.4118223 | N75: -2.4354953 | O75: 2.2169823 | P75: 1.8054376 | Q75: 10.391345 | R75: 12.89394 | S75: 16.846208 | T75: 3.5936812 | U75: 1.9317687 | V75: 4.2939751 | W75: 2.0113625 | X75: 5.179089 | Y75: 4.2998046 | Z75: 3.7152083 | AA75: 4.4707878 | AB75: 4.6876849
A76: Inflation, GDP deflator (annual %) | B76: NY.GDP.DEFL.KD.ZG | C76: Georgia | D76: GEO | E76: 22.425051 | F76: 62.132461 | G76: 1314.1864 | H76: 15442.301 | I76: 6041.5953 | J76: 162.72511 | K76: 43.032632 | L76: 6.537979 | M76: 6.9362304 | N76: 9.7266121 | O76: 4.6796355 | P76: 5.3769256 | Q76: 5.9196597 | R76: 3.4245665 | S76: 8.3675189 | T76: 7.9272634 | U76: 8.4848595 | V76: 9.692843 | W76: 9.7074093 | X76: -2.0083707 | Y76: 8.5433674 | Z76: 9.7280109 | AA76: 1.2335465 | AB76: -0.64293893
A77: Inflation, GDP deflator (annual %) | B77: NY.GDP.DEFL.KD.ZG | C77: Germany | D77: DEU | E77: 3.3966435 | F77: 3.0850797 | G77: 5.4004753 | H77: 3.9842707 | I77: 2.4934308 | J77: 2.0094188 | K77: 0.6377697 | L77: 0.26347736 | M77: 0.58978677 | N77: 0.19197153 | O77: -0.67232846 | P77: 1.1254836 | Q77: 1.4312595 | R77: 1.0971318 | S77: 1.0709031 | T77: 0.61821196 | U77: 0.31201245 | V77: 1.6303356 | W77: 0.77376649 | X77: 1.1800199 | Y77: 1.034072 | Z77: 1.2308488 | AA77: 1.4660823 | AB77: 2.2286745
A78: Inflation, GDP deflator (annual %) | B78: NY.GDP.DEFL.KD.ZG | C78: Ghana | D78: GHA | E78: 31.166607 | F78: 20.041361 | G78: 11.150066 | H78: 31.757208 | I78: 30.128927 | J78: 43.045331 | K78: 39.837743 | L78: 19.458167 | M78: 17.048465 | N78: 13.971165 | O78: 27.230114 | P78: 34.817944 | Q78: 22.818584 | R78: 28.704407 | S78: 14.350151 | T78: 14.963718 | U78: 80.749976 | V78: 16.276597 | W78: 20.202141 | X78: 16.618798 | Y78: 16.476577 | Z78: 12.963952 | AA78: 15.190333 | AB78: 16.382656
A79: Inflation, GDP deflator (annual %) | B79: NY.GDP.DEFL.KD.ZG | C79: Greece | D79: GRC | E79: 20.690598 | F79: 19.787743 | G79: 14.798814 | H79: 14.428747 | I79: 11.181889 | J79: 9.791836 | K79: 7.3412296 | L79: 6.7761836 | M79: 5.1973081 | N79: 3.0286005 | O79: 3.3968484 | P79: 3.117539 | Q79: 3.4004534 | R79: 3.9220995 | S79: 2.9469443 | T79: 2.8119697 | U79: 2.4253014 | V79: 3.3152964 | W79: 4.7232105 | X79: 2.301246 | Y79: 1.1355088 | Z79: 1.0495375 | AA79: -0.33222983 | AB79: -2.0652055
A80: Inflation, GDP deflator (annual %) | B80: NY.GDP.DEFL.KD.ZG | C80: Greenland | D80: GRL | E80: 5.0925845 | F80: 3.225275 | G80: 1.5456783 | H80: 1.0420168 | I80: 0.46837437 | J80: 2.0558707 | K80: 0.98010184 | L80: 0.4967035 | M80: 0.97842771 | N80: 1.0604558 | O80: 2.1100931 | P80: 3.4022564 | Q80: 3.1030843 | R80: 2.1972856 | S80: 2.1490561 | T80: 1.5911487 | U80: -3.0771029 | V80: 5.8875189 | W80: -23.481732 | X80: -18.985239 | Y80: .. | Z80: .. | AA80: .. | AB80: ..
A81: Inflation, GDP deflator (annual %) | B81: NY.GDP.DEFL.KD.ZG | C81: Grenada | D81: GRD | E81: -1.3715033 | F81: 6.8195218 | G81: 4.1770194 | H81: 2.4428753 | I81: 1.7996787 | J81: 2.9678717 | K81: 2.4851906 | L81: -1.067758 | M81: 4.9016999 | N81: 1.1958165 | O81: 34.467417 | P81: 2.1443952 | Q81: 0.37163449 | R81: -0.087263994 | S81: 1.6619624 | T81: 2.8369292 | U81: 4.6593267 | V81: 2.3582645 | W81: 7.8104017 | X81: 0.041183362 | Y81: 0.43099548 | Z81: 0.21354893 | AA81: 4.8334714 | AB81: 2.1964258
A82: Inflation, GDP deflator (annual %) | B82: NY.GDP.DEFL.KD.ZG | C82: Guam | D82: GUM | E82: .. | F82: .. | G82: .. | H82: .. | I82: .. | J82: .. | K82: .. | L82: .. | M82: .. | N82: .. | O82: .. | P82: .. | Q82: .. | R82: .. | S82: .. | T82: .. | U82: .. | V82: .. | W82: .. | X82: .. | Y82: .. | Z82: .. | AA82: .. | AB82: ..
A83: Inflation, GDP deflator (annual %) | B83: NY.GDP.DEFL.KD.ZG | C83: Guatemala | D83: GTM | E83: 40.531259 | F83: 32.975052 | G83: 8.8613849 | H83: 14.504352 | I83: 11.722278 | J83: 8.6678183 | K83: 8.9000045 | L83: 8.2573395 | M83: 9.5024352 | N83: 5.0415579 | O83: 6.8301147 | P83: -4.0839305 | Q83: 6.4495231 | R83: 4.4559685 | S83: 6.0770208 | T83: 5.6344841 | U83: 4.9939379 | V83: 7.1359693 | W83: 9.4406971 | X83: 3.5432804 | Y83: 5.1419091 | Z83: 6.9330467 | AA83: 3.3225073 | AB83: 3.2690117
A84: Inflation, GDP deflator (annual %) | B84: NY.GDP.DEFL.KD.ZG | C84: Guinea | D84: GIN | E84: 17.279181 | F84: 25.818671 | G84: 26.220214 | H84: 0.67375728 | I84: 1.4280016 | J84: 5.9513383 | K84: 1.5459682 | L84: 1.4341267 | M84: 3.3246404 | N84: 4.2276753 | O84: 6.300124 | P84: 1.7524263 | Q84: 0.43277238 | R84: 15.910697 | S84: 16.521583 | T84: 27.390845 | U84: 37.58389 | V84: 12.986878 | W84: 14.109211 | X84: 6.8063368 | Y84: 20.199578 | Z84: 19.732208 | AA84: 12.891511 | AB84: 6.9222832
A85: Inflation, GDP deflator (annual %) | B85: NY.GDP.DEFL.KD.ZG | C85: Guinea-Bissau | D85: GNB | E85: 30.246037 | F85: 67.894367 | G85: 64.98119 | H85: 49.058885 | I85: 23.249481 | J85: 44.730038 | K85: 39.233714 | L85: 34.138195 | M85: 8.0748345 | N85: 12.306066 | O85: 79.882497 | P85: 1.9678573 | Q85: -1.3479475 | R85: 0.39059159 | S85: 2.8427809 | T85: 4.3002513 | U85: 2.1363705 | V85: 3.2021544 | W85: 10.461782 | X85: 1.1189168 | Y85: 1.7189163 | Z85: 4.7756817 | AA85: -6.7141463 | AB85: 0.78892017
A86: Inflation, GDP deflator (annual %) | B86: NY.GDP.DEFL.KD.ZG | C86: Guyana | D86: GUY | E86: 56.397175 | F86: 126.7371 | G86: 13.499999 | H86: 15.499995 | I86: 19.700005 | J86: 12.400008 | K86: 3.9999906 | L86: 1.3990551 | M86: 3.0009579 | N86: 11.199999 | O86: 6.6000107 | P86: -1.8875603 | Q86: 4.5138523 | R86: 5.485871 | S86: 4.8939091 | T86: 7.8985863 | U86: 68.443677 | V86: 25.171415 | W86: 9.0203717 | X86: 2.1301538 | Y86: 6.7029899 | Z86: 8.3666087 | AA86: 5.7471423 | AB86: 2.9344506
A87: Inflation, GDP deflator (annual %) | B87: NY.GDP.DEFL.KD.ZG | C87: Haiti | D87: HTI | E87: .. | F87: .. | G87: .. | H87: .. | I87: .. | J87: .. | K87: .. | L87: .. | M87: .. | N87: 7.045707 | O87: 11.050452 | P87: 11.630584 | Q87: 10.005281 | R87: 26.90425 | S87: 21.491544 | T87: 17.587335 | U87: 14.760833 | V87: 8.015994 | W87: 12.894852 | X87: 3.7023174 | Y87: 5.4510563 | Z87: 7.5102741 | AA87: 5.2855628 | AB87: 6.6211819
A88: Inflation, GDP deflator (annual %) | B88: NY.GDP.DEFL.KD.ZG | C88: Honduras | D88: HND | E88: 21.200558 | F88: 26.02834 | G88: 9.1022143 | H88: 13.608335 | I88: 28.886742 | J88: 24.879072 | K88: 22.924776 | L88: 22.279686 | M88: 11.628663 | N88: 11.560254 | O88: 30.819514 | P88: 8.0848259 | Q88: 5.1319991 | R88: 5.7595614 | S88: 6.4521643 | T88: 7.278278 | U88: 5.3491337 | V88: 6.6254906 | W88: 7.790374 | X88: 7.653886 | Y88: 4.6759883 | Z88: 7.8074045 | AA88: 4.0444228 | AB88: 1.6977394
A89: Inflation, GDP deflator (annual %) | B89: NY.GDP.DEFL.KD.ZG | C89: Hong Kong SAR, China | D89: HKG | E89: 7.5648052 | F89: 9.1405178 | G89: 9.899477 | H89: 8.6128914 | I89: 6.321278 | J89: 4.139663 | K89: 5.8836966 | L89: 5.7602016 | M89: 1.2198914 | N89: -4.0956347 | O89: -3.3941697 | P89: -1.7740271 | Q89: -3.4019361 | R89: -6.0077173 | S89: -3.5908979 | T89: -0.15006767 | U89: -0.53488494 | V89: 3.1374208 | W89: 1.2814864 | X89: -0.37539958 | Y89: 0.27067108 | Z89: 3.9263931 | AA89: 3.6995854 | AB89: 1.3619351
A90: Inflation, GDP deflator (annual %) | B90: NY.GDP.DEFL.KD.ZG | C90: Hungary | D90: HUN | E90: 25.666054 | F90: 38.466154 | G90: 21.50918 | H90: 21.278455 | I90: 19.491061 | J90: 26.732789 | K90: 22.208702 | L90: 20.212936 | M90: 13.651884 | N90: 7.8590578 | O90: 9.7430961 | P90: 11.2631 | Q90: 8.4571531 | R90: 5.397668 | S90: 5.2344588 | T90: 2.4856047 | U90: 3.4947807 | V90: 5.437458 | W90: 5.2759093 | X90: 3.5647678 | Y90: 2.1884213 | Z90: 2.5919303 | AA90: 3.2483521 | AB90: ..
A91: Inflation, GDP deflator (annual %) | B91: NY.GDP.DEFL.KD.ZG | C91: Iceland | D91: ISL | E91: 15.171552 | F91: 8.3653422 | G91: 3.4492895 | H91: 1.8318475 | I91: 2.603377 | J91: 2.9975697 | K91: 2.474381 | L91: 2.9055571 | M91: 5.1464299 | N91: 3.2562657 | O91: 3.6376147 | P91: 8.6316108 | Q91: 5.6255693 | R91: 0.61751015 | S91: 2.5030371 | T91: 2.8424817 | U91: 8.8040899 | V91: 5.6508241 | W91: 11.802145 | X91: 8.2940681 | Y91: 6.9191234 | Z91: 3.2729377 | AA91: 2.8605381 | AB91: 1.7888925
A92: Inflation, GDP deflator (annual %) | B92: NY.GDP.DEFL.KD.ZG | C92: India | D92: IND | E92: 10.668304 | F92: 13.751819 | G92: 8.9651524 | H92: 9.8617829 | I92: 9.9800448 | J92: 9.0627022 | K92: 7.5750183 | L92: 6.4762713 | M92: 8.0101675 | N92: 3.0683955 | O92: 3.6449702 | P92: 3.215616 | Q92: 3.7156838 | R92: 3.8677981 | S92: 5.7254132 | T92: 4.2369251 | U92: 6.4225843 | V92: 5.7562435 | W92: 8.6646653 | X92: 6.0638293 | Y92: 8.9838126 | Z92: 8.53972 | AA92: 7.1725498 | AB92: 6.9149093
A93: Inflation, GDP deflator (annual %) | B93: NY.GDP.DEFL.KD.ZG | C93: Indonesia | D93: IDN | E93: 7.7239105 | F93: 8.8277302 | G93: 5.3643162 | H93: 8.8801055 | I93: 7.7763777 | J93: 9.7032769 | K93: 8.8535913 | L93: 12.571309 | M93: 75.271284 | N93: 14.161193 | O93: 20.447459 | P93: 14.295715 | Q93: 5.8960517 | R93: 5.487427 | S93: 8.5507327 | T93: 14.331786 | U93: 14.087422 | V93: 11.258579 | W93: 18.149752 | X93: 8.2747513 | Y93: 8.2572001 | Z93: 8.0731011 | AA93: 4.3828415 | AB93: 4.3510819
A94: Inflation, GDP deflator (annual %) | B94: NY.GDP.DEFL.KD.ZG | C94: Iran, Islamic Rep. | D94: IRN | E94: 20.564472 | F94: 25.170583 | G94: 28.076456 | H94: 52.959141 | I94: 30.962089 | J94: 38.723397 | K94: 24.716345 | L94: 13.991504 | M94: 9.4563488 | N94: 30.142014 | O94: 26.442305 | P94: 11.625867 | Q94: 28.281656 | R94: 11.803703 | S94: 20.59202 | T94: 17.006726 | U94: 12.145026 | V94: 20.462335 | W94: 25.693344 | X94: 2.5427012 | Y94: 14.386639 | Z94: 25.696362 | AA94: 5.9322011 | AB94: 17.814547
A95: Inflation, GDP deflator (annual %) | B95: NY.GDP.DEFL.KD.ZG | C95: Iraq | D95: IRQ | E95: .. | F95: .. | G95: .. | H95: .. | I95: .. | J95: .. | K95: .. | L95: .. | M95: .. | N95: .. | O95: .. | P95: -19.576533 | Q95: 6.653371 | R95: 7.8042354 | S95: 16.7217 | T95: 32.306923 | U95: 18.00503 | V95: 15.015814 | W95: 32.152594 | X95: -21.369827 | Y95: 19.64715 | Z95: 22.046021 | AA95: 3.0756338 | AB95: -0.66385252
A96: Inflation, GDP deflator (annual %) | B96: NY.GDP.DEFL.KD.ZG | C96: Ireland | D96: IRL | E96: -0.7291846 | F96: 1.8013963 | G96: 2.8122195 | H96: 5.1757526 | I96: 1.6945317 | J96: 3.0339962 | K96: 0.039945253 | L96: 3.6627537 | M96: 6.0319577 | N96: 3.8991848 | O96: 5.319563 | P96: 5.9630515 | Q96: 5.5105285 | R96: 3.7189565 | S96: 2.3767801 | T96: 2.3564124 | U96: 3.3217297 | V96: 1.7465489 | W96: -2.8605636 | X96: -3.827158 | Y96: -1.533064 | Z96: 0.66513247 | AA96: 0.6651315 | AB96: 0.4091517
A97: Inflation, GDP deflator (annual %) | B97: NY.GDP.DEFL.KD.ZG | C97: Isle of Man | D97: IMY | E97: 9.0493598 | F97: 6.8904577 | G97: 3.7555344 | H97: 2.1879592 | I97: 2.5377757 | J97: 2.9388806 | K97: 2.5544905 | L97: 2.661685 | M97: 2.3787686 | N97: 2.3000693 | O97: 3.2670543 | P97: 1.1673283 | Q97: 2.9450325 | R97: 2.649966 | S97: 5.9628494 | T97: 3.1620909 | U97: 3.276908 | V97: 3.9046407 | W97: .. | X97: .. | Y97: .. | Z97: .. | AA97: .. | AB97: ..
A98: Inflation, GDP deflator (annual %) | B98: NY.GDP.DEFL.KD.ZG | C98: Israel | D98: ISR | E98: 15.898717 | F98: 18.315315 | G98: 13.544681 | H98: 9.2841527 | I98: 12.695597 | J98: 20.676291 | K98: 10.016746 | L98: 7.9035877 | M98: 7.1245588 | N98: 6.3357798 | O98: 1.6221632 | P98: 1.7621471 | Q98: 4.1190094 | R98: -0.53262192 | S98: 0.1166339 | T98: 0.98926956 | U98: 5.97324 | V98: -0.074928032 | W98: 1.8513538 | X98: 4.5192674 | Y98: 1.3054266 | Z98: 1.9928028 | AA98: 4.0316722 | AB98: 2.5115966
A99: Inflation, GDP deflator (annual %) | B99: NY.GDP.DEFL.KD.ZG | C99: Italy | D99: ITA | E99: 8.9140634 | F99: 7.5813287 | G99: 4.3681156 | H99: 3.8859518 | I99: 3.5424736 | J99: 4.9252445 | K99: 4.7972208 | L99: 2.563045 | M99: 2.6622744 | N99: 1.7937945 | O99: 1.9449975 | P99: 2.8777519 | Q99: 3.2080397 | R99: 3.1187679 | S99: 2.3921949 | T99: 1.8170971 | U99: 1.7075994 | V99: 2.3738569 | W99: 2.5331583 | X99: 2.0889481 | Y99: 0.38824144 | Z99: 1.3525879 | AA99: 1.5800748 | AB99: 1.4412693
A100: Inflation, GDP deflator (annual %) | B100: NY.GDP.DEFL.KD.ZG | C100: Jamaica | D100: JAM | E100: 25.117106 | F100: 43.842288 | G100: 60.035734 | H100: 37.389448 | I100: 32.061794 | J100: 22.171469 | K100: 18.731851 | L100: 10.45127 | M100: 23.662772 | N100: 6.7892618 | O100: 10.595535 | P100: 7.4182567 | Q100: .. | R100: .. | S100: .. | T100: .. | U100: .. | V100: 11.344234 | W100: 13.456181 | X100: 11.790021 | Y100: 9.8798417 | Z100: 5.6624572 | AA100: 5.1496792 | AB100: 8.2642615
A101: Inflation, GDP deflator (annual %) | B101: NY.GDP.DEFL.KD.ZG | C101: Japan | D101: JPN | E101: 2.2645969 | F101: 2.6057347 | G101: 1.5881739 | H101: 0.43740385 | I101: 0.11504053 | J101: -0.72531445 | K101: -0.55689871 | L101: 0.595059 | M101: -0.054467497 | N101: -1.2736998 | O101: -1.2475981 | P101: -1.1978675 | Q101: -1.550273 | R101: -1.714756 | S101: -1.3524658 | T101: -1.2511519 | U101: -1.1214322 | V101: -0.93074037 | W101: -1.2652014 | X101: -0.5002834 | Y101: -2.1644214 | Z101: -1.8512529 | AA101: -0.91049224 | AB101: -0.56176455
A102: Inflation, GDP deflator (annual %) | B102: NY.GDP.DEFL.KD.ZG | C102: Jordan | D102: JOR | E102: 12.740962 | F102: 5.216267 | G102: 2.8575876 | H102: 2.8158946 | I102: 6.8766893 | J102: 1.8785289 | K102: 2.0629819 | L102: 1.2323272 | M102: 6.019841 | N102: -0.40049714 | O102: -0.41221773 | P102: 0.77977781 | Q102: 0.92121359 | R102: 2.1441675 | S102: 3.0855327 | T102: 2.0029395 | U102: 10.675165 | V102: 5.0507279 | W102: 19.868027 | X102: 2.8187552 | Y102: 8.4121838 | Z102: 6.4132125 | AA102: 4.5004527 | AB102: 5.5995888
...

Sheet Standard Exchange Rates
A1: Year | C1: =C2&"y" -> 1960y | D1: =D2&"y" -> 1961y | E1: =E2&"y" -> 1962y | F1: =F2&"y" -> 1963y | G1: =G2&"y" -> 1964y | H1: =H2&"y" -> 1965y | I1: =I2&"y" -> 1966y | J1: =J2&"y" -> 1967y | ... XFD1: =XFD2&"y" -> y
A2: Country Name | B2: Country Code | C2: 1960 | D2: 1961 | E2: 1962 | F2: 1963 | G2: 1964 | H2: 1965 | I2: 1966 | J2: 1967 | K2: 1968 | L2: 1969 | M2: 1970 | N2: 1971 | O2: 1972 | P2: 1973 | Q2: 1974 | R2: 1975 | S2: 1976 | T2: 1977 | U2: 1978 | V2: 1979 | W2: 1980 | X2: 1981 | Y2: 1982 | Z2: 1983 | AA2: 1984 | AB2: 1985 | AC2: 1986 | AD2: 1987 | AE2: 1988 | AF2: 1989 | AG2: 1990 | AH2: 1991 | AI2: 1992 | AJ2: 1993 | AK2: 1994 | AL2: 1995 | AM2: 1996 | AN2: 1997 | AO2: 1998 | AP2: 1999 | AQ2: 2000 | AR2: 2001 | AS2: 2002 | AT2: 2003 | AU2: 2004 | AV2: 2005 | AW2: 2006 | AX2: 2007 | AY2: 2008 | AZ2: 2009 | BA2: 2010 | BB2: 2011 | BC2: 2012 | BD2: 2013
A3: Afghanistan | B3: AFG | C3: 193.90501 | D3: 193.90501 | E3: 193.90501 | F3: 395.88939 | G3: 436.28627 | H3: 436.28627 | I3: 436.28627 | J3: 436.28627 | K3: 436.28627 | L3: 436.28627 | M3: 436.28627 | N3: 436.28627 | O3: 436.28627 | P3: 436.28627 | Q3: 436.28627 | R3: 436.28627 | S3: 436.28627 | T3: 436.28627 | U3: 436.28627 | V3: 422.75332 | W3: 429.28953 | X3: 481.65196 | Y3: 490.57967 | Z3: 490.57967 | AA3: 490.57967 | AB3: 490.57967 | AC3: 490.57967 | AD3: 490.57967 | AE3: 490.57967 | AF3: 490.57967 | AG3: 490.57967 | AH3: 490.57967 | AI3: 490.57967 | AJ3: 490.57967 | AK3: 484.85948 | AL3: 36.567145 | AM3: 47.5 | AN3: 47.5 | AO3: 47.5 | AP3: 46.619531 | AQ3: 47.357575 | AR3: 47.500015 | AS3: 47.263 | AT3: 48.762754 | AU3: 47.845312 | AV3: 49.494597 | AW3: 49.925331 | AX3: 49.962018 | AY3: 50.249615 | AZ3: 50.325 | BA3: 46.452461 | BB3: 46.747008 | BC3: 50.9214 | BD3: 55.3775
A4: Albania | B4: ALB | C4: .. | D4: .. | E4: .. | F4: .. | G4: .. | H4: .. | I4: .. | J4: .. | K4: .. | L4: .. | M4: .. | N4: .. | O4: .. | P4: .. | Q4: .. | R4: .. | S4: .. | T4: .. | U4: .. | V4: .. | W4: .. | X4: .. | Y4: .. | Z4: .. | AA4: .. | AB4: .. | AC4: .. | AD4: .. | AE4: .. | AF4: .. | AG4: .. | AH4: .. | AI4: 75.0325 | AJ4: 102.0625 | AK4: 94.623333 | AL4: 92.6975 | AM4: 104.49892 | AN4: 148.93292 | AO4: 150.63333 | AP4: 137.69058 | AQ4: 143.70942 | AR4: 143.48483 | AS4: 140.15452 | AT4: 121.86325 | AU4: 102.78005 | AV4: 99.870254 | AW4: 98.103377 | AX4: 90.427894 | AY4: 83.894604 | AZ4: 94.97812 | BA4: 103.93644 | BB4: 100.89495 | BC4: 108.18464 | BD4: 105.66867
A5: Algeria | B5: DZA | C5: 4.93706 | D5: 4.93706 | E5: 4.93706 | F5: 4.93706 | G5: 4.93706 | H5: 4.93706 | I5: 4.93706 | J5: 4.93706 | K5: 4.93706 | L5: 4.93706 | M5: 4.93706 | N5: 4.9126383 | O5: 4.480515 | P5: 3.9624954 | Q5: 4.18075 | R5: 3.9494083 | S5: 4.163825 | T5: 4.1467583 | U5: 3.9659 | V5: 3.8532667 | W5: 3.83745 | X5: 4.3158083 | Y5: 4.5921917 | Z5: 4.7888 | AA5: 4.983375 | AB5: 5.0278 | AC5: 4.7023167 | AD5: 4.8497417 | AE5: 5.9147667 | AF5: 7.6085583 | AG5: 8.9575083 | AH5: 18.472875 | AI5: 21.836075 | AJ5: 23.345407 | AK5: 35.058501 | AL5: 47.662727 | AM5: 54.748933 | AN5: 57.70735 | AO5: 58.738958 | AP5: 66.573875 | AQ5: 75.259792 | AR5: 77.215021 | AS5: 79.6819 | AT5: 77.394975 | AU5: 72.06065 | AV5: 73.276308 | AW5: 72.646617 | AX5: 69.2924 | AY5: 64.5828 | AZ5: 72.647417 | BA5: 74.385983 | BB5: 72.937883 | BC5: 77.535967 | BD5: 79.3684
A6: American Samoa | B6: ASM | C6: .. | D6: .. | E6: .. | F6: .. | G6: .. | H6: .. | I6: .. | J6: .. | K6: .. | L6: .. | M6: .. | N6: .. | O6: .. | P6: .. | Q6: .. | R6: .. | S6: .. | T6: .. | U6: .. | V6: .. | W6: .. | X6: .. | Y6: .. | Z6: .. | AA6: .. | AB6: .. | AC6: .. | AD6: .. | AE6: .. | AF6: .. | AG6: .. | AH6: .. | AI6: .. | AJ6: .. | AK6: .. | AL6: .. | AM6: .. | AN6: .. | AO6: .. | AP6: .. | AQ6: .. | AR6: .. | AS6: .. | AT6: .. | AU6: .. | AV6: .. | AW6: .. | AX6: .. | AY6: .. | AZ6: .. | BA6: .. | BB6: .. | BC6: .. | BD6: ..
A7: Andorra | B7: AND | C7: .. | D7: .. | E7: .. | F7: .. | G7: .. | H7: .. | I7: .. | J7: .. | K7: .. | L7: .. | M7: .. | N7: .. | O7: .. | P7: .. | Q7: .. | R7: .. | S7: .. | T7: .. | U7: .. | V7: .. | W7: .. | X7: .. | Y7: .. | Z7: .. | AA7: .. | AB7: .. | AC7: .. | AD7: .. | AE7: .. | AF7: .. | AG7: .. | AH7: .. | AI7: .. | AJ7: .. | AK7: .. | AL7: .. | AM7: .. | AN7: .. | AO7: .. | AP7: .. | AQ7: .. | AR7: .. | AS7: .. | AT7: .. | AU7: .. | AV7: .. | AW7: .. | AX7: .. | AY7: .. | AZ7: .. | BA7: .. | BB7: .. | BC7: .. | BD7: ..
A8: Angola | B8: AGO | C8: 2.8668443e-08 | D8: 2.873486e-08 | E8: 2.8678443e-08 | F8: 2.8752027e-08 | G8: 2.8819777e-08 | H8: 2.8778527e-08 | I8: 2.882386e-08 | J8: 2.884161e-08 | K8: 2.872761e-08 | L8: 2.8561193e-08 | M8: 2.862511e-08 | N8: 2.819112e-08 | O8: 2.7052815e-08 | P8: 2.451462e-08 | Q8: 2.5407601e-08 | R8: 2.5552181e-08 | S8: 2.9383623e-08 | T8: 2.9918e-08 | U8: 2.9918e-08 | V8: 2.9918e-08 | W8: 2.9918e-08 | X8: 2.9918e-08 | Y8: 2.9918e-08 | Z8: 2.9918e-08 | AA8: 2.9918e-08 | AB8: 2.9918e-08 | AC8: 2.9918e-08 | AD8: 2.9918e-08 | AE8: 2.9918e-08 | AF8: 2.9918e-08 | AG8: 2.9918e-08 | AH8: 5.5098333e-08 | AI8: 2.5141667e-07 | AJ8: 2.6601667e-06 | AK8: 5.9515e-05 | AL8: 0.0027502296 | AM8: 0.12802917 | AN8: 0.22904008 | AO8: 0.39282352 | AP8: 2.7907062 | AQ8: 10.040544 | AR8: 22.057862 | AS8: 43.530207 | AT8: 74.606301 | AU8: 83.541363 | AV8: 87.159142 | AW8: 80.368072 | AX8: 76.706143 | AY8: 75.033354 | AZ8: 79.328167 | BA8: 91.90572 | BB8: 93.93475 | BC8: 95.467955 | BD8: 96.518279
A9: Antigua and Barbuda | B9: ATG | C9: 1.71429 | D9: 1.71429 | E9: 1.71429 | F9: 1.71429 | G9: 1.71429 | H9: 1.71429 | I9: 1.71429 | J9: 1.7619083 | K9: 2 | L9: 2 | M9: 2 | N9: 1.9748727 | O9: 1.9212781 | P9: 1.9592192 | Q9: 2.0532324 | R9: 2.1697958 | S9: 2.6146708 | T9: 2.7 | U9: 2.7 | V9: 2.7 | W9: 2.7 | X9: 2.7 | Y9: 2.7 | Z9: 2.7 | AA9: 2.7 | AB9: 2.7 | AC9: 2.7 | AD9: 2.7 | AE9: 2.7 | AF9: 2.7 | AG9: 2.7 | AH9: 2.7 | AI9: 2.7 | AJ9: 2.7 | AK9: 2.7 | AL9: 2.7 | AM9: 2.7 | AN9: 2.7 | AO9: 2.7 | AP9: 2.7 | AQ9: 2.7 | AR9: 2.7 | AS9: 2.7 | AT9: 2.7 | AU9: 2.7 | AV9: 2.7 | AW9: 2.7 | AX9: 2.7 | AY9: 2.7 | AZ9: 2.7 | BA9: 2.7 | BB9: 2.7 | BC9: 2.7 | BD9: 2.7
A10: Argentina | B10: ARG | C10: .. | D10: .. | E10: 8.7166667e-12 | F10: 1.3871667e-11 | G10: 1.4039167e-11 | H10: 1.6956667e-11 | I10: 2.0915e-11 | J10: 3.33425e-11 | K10: 3.5e-11 | L10: 3.5e-11 | M10: 3.7916667e-11 | N10: 4.5216667e-11 | O10: 5e-11 | P10: 5e-11 | Q10: 5e-11 | R10: 3.6575e-10 | S10: 1.3998333e-09 | T10: 4.0763333e-09 | U10: 7.9575e-09 | V10: 1.3169667e-08 | W10: 1.8371583e-08 | X10: 4.4026917e-08 | Y10: 2.5922533e-07 | Z10: 1.0529957e-06 | AA10: 6.7649117e-06 | AB10: 6.01809e-05 | AC10: 9.4303167e-05 | AD10: 0.00021442983 | AE10: 0.00087526042 | AF10: 0.042333961 | AG10: 0.48758908 | AH10: 0.95355442 | AI10: 0.99064167 | AJ10: 0.99894583 | AK10: 0.99900833 | AL10: 0.99975 | AM10: 0.9996625 | AN10: 0.9995 | AO10: 0.9995 | AP10: 0.9995 | AQ10: 0.9995 | AR10: 0.9995 | AS10: 3.0632567 | AT10: 2.9006292 | AU10: 2.9233008 | AV10: 2.9036575 | AW10: 3.0543133 | AX10: 3.0956488 | AY10: 3.1441646 | AZ10: 3.7101068 | BA10: 3.8962952 | BB10: 4.1101396 | BC10: 4.5369344 | BD10: 5.4593527
A11: Armenia | B11: ARM | C11: .. | D11: .. | E11: .. | F11: .. | G11: .. | H11: .. | I11: .. | J11: .. | K11: .. | L11: .. | M11: .. | N11: .. | O11: .. | P11: .. | Q11: .. | R11: .. | S11: .. | T11: .. | U11: .. | V11: .. | W11: .. | X11: .. | Y11: .. | Z11: .. | AA11: .. | AB11: .. | AC11: .. | AD11: .. | AE11: .. | AF11: .. | AG11: .. | AH11: .. | AI11: .. | AJ11: 9.105 | AK11: 288.65083 | AL11: 405.90833 | AM11: 414.0415 | AN11: 490.84679 | AO11: 504.915 | AP11: 535.06183 | AQ11: 539.52583 | AR11: 555.07826 | AS11: 573.35333 | AT11: 578.76295 | AU11: 533.45083 | AV11: 457.68694 | AW11: 416.04037 | AX11: 342.07912 | AY11: 305.9694 | AZ11: 363.28329 | BA11: 373.66047 | BB11: 372.50088 | BC11: 401.76398 | BD11: 409.62575
A12: Aruba | B12: ABW | C12: .. | D12: .. | E12: .. | F12: .. | G12: .. | H12: .. | I12: .. | J12: .. | K12: .. | L12: .. | M12: .. | N12: .. | O12: .. | P12: .. | Q12: .. | R12: .. | S12: .. | T12: .. | U12: .. | V12: .. | W12: .. | X12: .. | Y12: .. | Z12: .. | AA12: .. | AB12: .. | AC12: 1.79 | AD12: 1.79 | AE12: 1.79 | AF12: 1.79 | AG12: 1.79 | AH12: 1.79 | AI12: 1.79 | AJ12: 1.79 | AK12: 1.79 | AL12: 1.79 | AM12: 1.79 | AN12: 1.79 | AO12: 1.79 | AP12: 1.79 | AQ12: 1.79 | AR12: 1.79 | AS12: 1.79 | AT12: 1.79 | AU12: 1.79 | AV12: 1.79 | AW12: 1.79 | AX12: 1.79 | AY12: 1.79 | AZ12: 1.79 | BA12: 1.79 | BB12: 1.79 | BC12: 1.79 | BD12: 1.79
A13: Australia | B13: AUS | C13: 0.892857 | D13: 0.892857 | E13: 0.892857 | F13: 0.892857 | G13: 0.892857 | H13: 0.892857 | I13: 0.892857 | J13: 0.892857 | K13: 0.892857 | L13: 0.892857 | M13: 0.892857 | N13: 0.88267026 | O13: 0.83869781 | P13: 0.7034971 | Q13: 0.69666587 | R13: 0.76387125 | S13: 0.81828408 | T13: 0.901825 | U13: 0.87365925 | V13: 0.89464092 | W13: 0.87824433 | X13: 0.87021458 | Y13: 0.98586283 | Z13: 1.110015 | AA13: 1.1395192 | AB13: 1.431895 | AC13: 1.4959742 | AD13: 1.42818 | AE13: 1.2799083 | AF13: 1.2645967 | AG13: 1.2810567 | AH13: 1.2837558 | AI13: 1.3616483 | AJ13: 1.47056 | AK13: 1.3677508 | AL13: 1.3490325 | AM13: 1.2778633 | AN13: 1.34738 | AO13: 1.5918283 | AP13: 1.54995 | AQ13: 1.7248267 | AR13: 1.9334425 | AS13: 1.8405625 | AT13: 1.5419142 | AU13: 1.3597525 | AV13: 1.3094733 | AW13: 1.3279734 | AX13: 1.1950725 | AY13: 1.1921783 | AZ13: 1.2821888 | BA13: 1.0901595 | BB13: 0.9694632 | BC13: 0.96580103 | BD13: 1.0358431
A14: Austria | B14: AUT | C14: 26 | D14: 26 | E14: 26 | F14: 26 | G14: 26 | H14: 26 | I14: 26 | J14: 26 | K14: 26 | L14: 26 | M14: 26 | N14: 24.985584 | O14: 23.115333 | P14: 19.58 | Q14: 18.6925 | R14: 17.41675 | S14: 17.939667 | T14: 16.526917 | U14: 14.521667 | V14: 13.3675 | W14: 12.938 | X14: 15.926833 | Y14: 17.05925 | Z14: 17.963333 | AA14: 20.009083 | AB14: 20.6895 | AC14: 15.267133 | AD14: 12.6425 | AE14: 12.347667 | AF14: 13.230667 | AG14: 11.369833 | AH14: 11.675917 | AI14: 10.989333 | AJ14: 11.632183 | AK14: 11.421825 | AL14: 10.081496 | AM14: 10.586557 | AN14: 12.204244 | AO14: 12.379065 | AP14: .. | AQ14: .. | AR14: .. | AS14: .. | AT14: .. | AU14: .. | AV14: .. | AW14: .. | AX14: .. | AY14: .. | AZ14: .. | BA14: .. | BB14: .. | BC14: .. | BD14: ..
A15: Azerbaijan | B15: AZE | C15: .. | D15: .. | E15: .. | F15: .. | G15: .. | H15: .. | I15: .. | J15: .. | K15: .. | L15: .. | M15: .. | N15: .. | O15: .. | P15: .. | Q15: .. | R15: .. | S15: .. | T15: .. | U15: .. | V15: .. | W15: .. | X15: .. | Y15: .. | Z15: .. | AA15: .. | AB15: .. | AC15: .. | AD15: .. | AE15: .. | AF15: .. | AG15: .. | AH15: .. | AI15: 0.01084 | AJ15: 0.019995 | AK15: 0.314045 | AL15: 0.8827085 | AM15: 0.86025283 | AN15: 0.797075 | AO15: 0.77379969 | AP15: 0.82403333 | AQ15: 0.89483075 | AR15: 0.93131667 | AS15: 0.97216417 | AT15: 0.982146 | AU15: 0.9826955 | AV15: 0.945421 | AW15: 0.893445 | AX15: 0.85812381 | AY15: 0.82161958 | AZ15: 0.80378333 | BA15: 0.80265 | BB15: 0.78968639 | BC15: 0.78564535 | BD15: 0.78454108
A16: Bahamas, The | B16: BHS | C16: 1.02041 | D16: 1.02041 | E16: 1.02041 | F16: 1.02041 | G16: 1.02041 | H16: 1.02041 | I16: 1.02041 | J16: 1.02041 | K16: 1.02041 | L16: 1.02041 | M16: 1.0017008 | N16: 1 | O16: 1 | P16: 1 | Q16: 1 | R16: 1 | S16: 1 | T16: 1 | U16: 1 | V16: 1 | W16: 1 | X16: 1 | Y16: 1 | Z16: 1 | AA16: 1 | AB16: 1 | AC16: 1 | AD16: 1 | AE16: 1 | AF16: 1 | AG16: 1 | AH16: 1 | AI16: 1 | AJ16: 1 | AK16: 1 | AL16: 1 | AM16: 1 | AN16: 1 | AO16: 1 | AP16: 1 | AQ16: 1 | AR16: 1 | AS16: 1 | AT16: 1 | AU16: 1 | AV16: 1 | AW16: 1 | AX16: 1 | AY16: 1 | AZ16: 1 | BA16: 1 | BB16: 1 | BC16: 1 | BD16: 1
A17: Bahrain | B17: BHR | C17: .. | D17: .. | E17: .. | F17: .. | G17: .. | H17: .. | I17: 0.47619 | J17: 0.47619 | K17: 0.47619 | L17: 0.47619 | M17: 0.47619 | N17: 0.47479629 | O17: 0.43859778 | P17: 0.39963031 | Q17: 0.39474 | R17: 0.3955 | S17: 0.39559917 | T17: 0.39565 | U17: 0.38745333 | V17: 0.3816175 | W17: 0.37700023 | X17: 0.376 | Y17: 0.376 | Z17: 0.376 | AA17: 0.376 | AB17: 0.376 | AC17: 0.376 | AD17: 0.376 | AE17: 0.376 | AF17: 0.376 | AG17: 0.376 | AH17: 0.376 | AI17: 0.376 | AJ17: 0.37599999 | AK17: 0.37599996 | AL17: 0.37599997 | AM17: 0.37599997 | AN17: 0.37599996 | AO17: 0.37599996 | AP17: 0.37599998 | AQ17: 0.376 | AR17: 0.376 | AS17: 0.376 | AT17: 0.376 | AU17: 0.376 | AV17: 0.376 | AW17: 0.376 | AX17: 0.376 | AY17: 0.376 | AZ17: 0.376 | BA17: 0.376 | BB17: 0.376 | BC17: 0.376 | BD17: 0.376
A18: Bangladesh | B18: BGD | C18: .. | D18: .. | E18: .. | F18: .. | G18: .. | H18: .. | I18: .. | J18: .. | K18: .. | L18: .. | M18: .. | N18: 7.8688426 | O18: 7.7001842 | P18: 7.849816 | Q18: 8.2260022 | R18: 12.18618 | S18: 15.399169 | T18: 15.3751 | U18: 15.016117 | V18: 15.551925 | W18: 15.454058 | X18: 17.986692 | Y18: 22.117883 | Z18: 24.615425 | AA18: 25.353933 | AB18: 27.994592 | AC18: 30.4069 | AD18: 30.949833 | AE18: 31.733249 | AF18: 32.27 | AG18: 34.568808 | AH18: 36.596183 | AI18: 38.950758 | AJ18: 39.567257 | AK18: 40.211739 | AL18: 40.278318 | AM18: 41.794168 | AN18: 43.892116 | AO18: 46.905652 | AP18: 49.0854 | AQ18: 52.141667 | AR18: 55.806667 | AS18: 57.888 | AT18: 58.15004 | AU18: 59.512658 | AV18: 64.327475 | AW18: 68.933233 | AX18: 68.874875 | AY18: 68.598275 | AZ18: 69.039067 | BA18: 69.649292 | BB18: 74.1524 | BC18: 81.862658 | BD18: 78.103235
A19: Barbados | B19: BRB | C19: 1.71429 | D19: 1.71429 | E19: 1.71429 | F19: 1.71429 | G19: 1.71429 | H19: 1.71429 | I19: 1.71429 | J19: 1.7380992 | K19: 2 | L19: 2 | M19: 2 | N19: 1.9748762 | O19: 1.9212807 | P19: 1.9592205 | Q19: 2.0532309 | R19: 2.0188666 | S19: 2 | T19: 2 | U19: 2 | V19: 2 | W19: 2 | X19: 2 | Y19: 2 | Z19: 2 | AA19: 2 | AB19: 2 | AC19: 2 | AD19: 2 | AE19: 2 | AF19: 2 | AG19: 2 | AH19: 2 | AI19: 2 | AJ19: 2 | AK19: 2 | AL19: 2 | AM19: 2 | AN19: 2 | AO19: 2 | AP19: 2 | AQ19: 2 | AR19: 2 | AS19: 2 | AT19: 2 | AU19: 2 | AV19: 2 | AW19: 2 | AX19: 2 | AY19: 2 | AZ19: 2 | BA19: 2 | BB19: 2 | BC19: 2 | BD19: 2
A20: Belarus | B20: BLR | C20: .. | D20: .. | E20: .. | F20: .. | G20: .. | H20: .. | I20: .. | J20: .. | K20: .. | L20: .. | M20: .. | N20: .. | O20: .. | P20: .. | Q20: .. | R20: .. | S20: .. | T20: .. | U20: .. | V20: .. | W20: .. | X20: .. | Y20: .. | Z20: .. | AA20: .. | AB20: .. | AC20: .. | AD20: .. | AE20: .. | AF20: .. | AG20: .. | AH20: .. | AI20: .. | AJ20: .. | AK20: .. | AL20: 11.520967 | AM20: 13.229877 | AN20: 26.02055 | AO20: 46.12762 | AP20: 249.29533 | AQ20: 876.75 | AR20: 1390 | AS20: 1790.9167 | AT20: 2051.2708 | AU20: 2160.2575 | AV20: 2153.82 | AW20: 2144.5642 | AX20: 2146.0783 | AY20: 2136.3975 | AZ20: 2793.0492 | BA20: 2978.51 | BB20: 4974.6333 | BC20: 8336.8983 | BD20: 8880.0525
A21: Belgium | B21: BEL | C21: 50 | D21: 50 | E21: 50 | F21: 50 | G21: 50 | H21: 50 | I21: 50 | J21: 50 | K21: 50 | L21: 50 | M21: 50 | N21: 49.056977 | O21: 44.014583 | P21: 38.9765 | Q21: 38.9515 | R21: 36.778917 | S21: 38.605167 | T21: 35.84275 | U21: 31.492083 | V21: 29.318667 | W21: 29.241667 | X21: 37.12925 | Y21: 45.690583 | Z21: 51.131667 | AA21: 57.783917 | AB21: 59.378 | AC21: 44.671917 | AD21: 37.334083 | AE21: 36.768333 | AF21: 39.404 | AG21: 33.417917 | AH21: 34.14825 | AI21: 32.1495 | AJ21: 34.596521 | AK21: 33.456497 | AL21: 29.480017 | AM21: 30.961513 | AN21: 35.773891 | AO21: 36.298641 | AP21: .. | AQ21: .. | AR21: .. | AS21: .. | AT21: .. | AU21: .. | AV21: .. | AW21: .. | AX21: .. | AY21: .. | AZ21: .. | BA21: .. | BB21: .. | BC21: .. | BD21: ..
A22: Belize | B22: BLZ | C22: 1.42857 | D22: 1.42857 | E22: 1.42857 | F22: 1.42857 | G22: 1.42857 | H22: 1.42857 | I22: 1.42857 | J22: 1.4484117 | K22: 1.66667 | L22: 1.66667 | M22: 1.66667 | N22: 1.6436821 | O22: 1.6015618 | P22: 1.6326838 | Q22: 1.7109268 | R22: 1.8080437 | S22: 2.2256731 | T22: 2 | U22: 2 | V22: 2 | W22: 2 | X22: 2 | Y22: 2 | Z22: 2 | AA22: 2 | AB22: 2 | AC22: 2 | AD22: 2 | AE22: 2 | AF22: 2 | AG22: 2 | AH22: 2 | AI22: 2 | AJ22: 2 | AK22: 2 | AL22: 2 | AM22: 2 | AN22: 2 | AO22: 2 | AP22: 2 | AQ22: 2 | AR22: 2 | AS22: 2 | AT22: 2 | AU22: 2 | AV22: 2 | AW22: 2 | AX22: 2 | AY22: 2 | AZ22: 2 | BA22: 2 | BB22: 2 | BC22: 2 | BD22: 2
A23: Benin | B23: BEN | C23: 245.1951 | D23: 245.2601 | E23: 245.01385 | F23: 245.01635 | G23: 245.02718 | H23: 245.06093 | I23: 245.67844 | J23: 246.00094 | K23: 247.56469 | L23: 259.96057 | M23: 276.40314 | N23: 275.35646 | O23: 252.02763 | P23: 222.88918 | Q23: 240.70467 | R23: 214.3129 | S23: 238.95049 | T23: 245.67969 | U23: 225.65586 | V23: 212.72164 | W23: 211.27956 | X23: 271.73145 | Y23: 328.60625 | Z23: 381.06604 | AA23: 436.95667 | AB23: 449.26296 | AC23: 346.3059 | AD23: 300.53656 | AE23: 297.84822 | AF23: 319.0083 | AG23: 272.26479 | AH23: 282.10691 | AI23: 264.6918 | AJ23: 283.16258 | AK23: 555.2047 | AL23: 499.14843 | AM23: 511.55243 | AN23: 583.66937 | AO23: 589.95177 | AP23: 615.69913 | AQ23: 711.97627 | AR23: 733.03851 | AS23: 696.9882 | AT23: 581.20031 | AU23: 528.28481 | AV23: 527.46814 | AW23: 522.89011 | AX23: 479.26678 | AY23: 447.80526 | AZ23: 472.18629 | BA23: 495.27702 | BB23: 471.86611 | BC23: 510.52714 | BD23: 494.04004
A24: Bermuda | B24: BMU | C24: 0.85714251 | D24: 0.85714251 | E24: 0.85714251 | F24: 0.85714251 | G24: 0.85714251 | H24: 0.85714251 | I24: 0.85714251 | J24: 0.86904709 | K24: 1 | L24: 1 | M24: 1 | N24: 1 | O24: 1 | P24: 1 | Q24: 1 | R24: 1 | S24: 1 | T24: 1 | U24: 1 | V24: 1 | W24: 1 | X24: 1 | Y24: 1 | Z24: 1 | AA24: 1 | AB24: 1 | AC24: 1 | AD24: 1 | AE24: 1 | AF24: 1 | AG24: 1 | AH24: 1 | AI24: 1 | AJ24: 1 | AK24: 1 | AL24: 1 | AM24: 1 | AN24: 1 | AO24: 1 | AP24: 1 | AQ24: 1 | AR24: 1 | AS24: 1 | AT24: 1 | AU24: 1 | AV24: 1 | AW24: 1 | AX24: 1 | AY24: 1 | AZ24: 1 | BA24: 1 | BB24: 1 | BC24: 1 | BD24: 1
A25: Bhutan | B25: BTN | C25: 4.7619 | D25: 4.7619 | E25: 4.7619 | F25: 4.7619 | G25: 4.7619 | H25: 4.7619 | I25: 6.359125 | J25: 7.5 | K25: 7.5 | L25: 7.5 | M25: 7.5 | N25: 7.4919352 | O25: 7.5944684 | P25: 7.7420386 | Q25: 8.1016032 | R25: 8.3758919 | S25: 8.9604127 | T25: 8.7385762 | U25: 8.1928403 | V25: 8.1257909 | W25: 7.8629447 | X25: 8.6585228 | Y25: 9.4551319 | Z25: 10.098898 | AA25: 11.362583 | AB25: 12.36875 | AC25: 12.610833 | AD25: 12.9615 | AE25: 13.917083 | AF25: 16.2255 | AG25: 17.505325 | AH25: 22.742433 | AI25: 25.918083 | AJ25: 30.493292 | AK25: 31.373742 | AL25: 32.427077 | AM25: 35.433173 | AN25: 36.313286 | AO25: 41.259365 | AP25: 43.055428 | AQ25: 44.941605 | AR25: 47.186414 | AS25: 48.610319 | AT25: 46.583284 | AU25: 45.316467 | AV25: 44.099975 | AW25: 45.307008 | AX25: 41.348533 | AY25: 43.505183 | AZ25: 48.405267 | BA25: 45.725812 | BB25: 46.670467 | BC25: 53.437233 | BD25: 58.597845
A26: Bolivia | B26: BOL | C26: 1.188e-05 | D26: 1.188e-05 | E26: 1.188e-05 | F26: 1.188e-05 | G26: 1.188e-05 | H26: 1.188e-05 | I26: 1.188e-05 | J26: 1.188e-05 | K26: 1.188e-05 | L26: 1.188e-05 | M26: 1.188e-05 | N26: 1.188e-05 | O26: 1.3295e-05 | P26: 2.001e-05 | Q26: 2.001e-05 | R26: 2.001e-05 | S26: 2.001e-05 | T26: 2.001e-05 | U26: 2.001e-05 | V26: 2.0403333e-05 | W26: 2.452e-05 | X26: 2.452e-05 | Y26: 6.4071667e-05 | Z26: 0.00023163 | AA26: 0.0031359092 | AB26: 0.44002901 | AC26: 1.9219583 | AD26: 2.05485 | AE26: 2.3502417 | AF26: 2.6916833 | AG26: 3.17265 | AH26: 3.5806083 | AI26: 3.9005167 | AJ26: 4.2650833 | AK26: 4.6205167 | AL26: 4.8003417 | AM26: 5.0746125 | AN26: 5.2542583 | AO26: 5.5101333 | AP26: 5.8124083 | AQ26: 6.1835417 | AR26: 6.6069167 | AS26: 7.17 | AT26: 7.6591667 | AU26: 7.9362667 | AV26: 8.0660625 | AW26: 8.0116167 | AX26: 7.8512452 | AY26: 7.2383207 | AZ26: 7.02 | BA26: 7.0166667 | BB26: 6.9369625 | BC26: 6.91 | BD26: 6.91
A27: Bosnia and Herzegovina | B27: BIH | C27: .. | D27: .. | E27: .. | F27: .. | G27: .. | H27: .. | I27: .. | J27: .. | K27: .. | L27: .. | M27: .. | N27: .. | O27: .. | P27: .. | Q27: .. | R27: .. | S27: .. | T27: .. | U27: .. | V27: .. | W27: .. | X27: .. | Y27: .. | Z27: .. | AA27: .. | AB27: .. | AC27: .. | AD27: .. | AE27: .. | AF27: .. | AG27: .. | AH27: .. | AI27: .. | AJ27: .. | AK27: .. | AL27: .. | AM27: .. | AN27: 1.7340558 | AO27: 1.7596676 | AP27: 1.8357954 | AQ27: 2.1228595 | AR27: 2.1856596 | AS27: 2.0781704 | AT27: 1.7329322 | AU27: 1.575157 | AV27: 1.572722 | AW27: 1.559072 | AX27: 1.4290027 | AY27: 1.3351957 | AZ27: 1.4078912 | BA27: 1.4767396 | BB27: 1.4069366 | BC27: 1.52221 | BD27: 1.4730513
A28: Botswana | B28: BWA | C28: 0.71332088 | D28: 0.71469444 | E28: 0.71326549 | F28: 0.71528719 | G28: 0.71725865 | H28: 0.7163344 | I28: 0.71698343 | J28: 0.71704962 | K28: 0.71699816 | L28: 0.71805713 | M28: 0.71641352 | N28: 0.715217 | O28: 0.76912285 | P28: 0.69411414 | Q28: 0.679477 | R28: 0.7395077 | S28: 0.869565 | T28: 0.84195967 | U28: 0.828157 | V28: 0.81500667 | W28: 0.777225 | X28: 0.83673833 | Y28: 1.0296608 | Z28: 1.0969258 | AA28: 1.2983733 | AB28: 1.9025667 | AC28: 1.8791442 | AD28: 1.6789408 | AE28: 1.8285875 | AF28: 2.0148858 | AG28: 1.8604658 | AH28: 2.0215567 | AI28: 2.109725 | AJ28: 2.423075 | AK28: 2.6846455 | AL28: 2.7722067 | AM28: 3.3241967 | AN28: 3.6507633 | AO28: 4.22588 | AP28: 4.6243953 | AQ28: 5.1018158 | AR28: 5.8411589 | AS28: 6.3278007 | AT28: 4.9499286 | AU28: 4.6928874 | AV28: 5.1103544 | AW28: 5.8365712 | AX28: 6.1388192 | AY28: 6.8268567 | AZ28: 7.1551377 | BA28: 6.7936212 | BB28: 6.8382358 | BC28: 7.6191417 | BD28: 8.3989083
A29: Brazil | B29: BRA | C29: 8.0997053e-14 | D29: 1.1684348e-13 | E29: 1.6776416e-13 | F29: 2.488694e-13 | G29: 5.4202392e-13 | H29: 8.2165489e-13 | I29: 9.6071305e-13 | J29: 1.1526032e-12 | K29: 1.4695953e-12 | L29: 1.7633628e-12 | M29: 1.9878538e-12 | N29: 2.2882209e-12 | O29: 2.56796e-12 | P29: 2.6509405e-12 | Q29: 2.9383611e-12 | R29: 3.5168445e-12 | S29: 4.6187073e-12 | T29: 6.1208673e-12 | U29: 7.8197498e-12 | V29: 1.1660691e-11 | W29: 2.2812319e-11 | X29: 4.0300109e-11 | Y29: 7.7685443e-11 | Z29: 2.4971817e-10 | AA29: 7.9974132e-10 | AB29: 2.6832423e-09 | AC29: 5.9096823e-09 | AD29: 1.6976308e-08 | AE29: 1.1354767e-07 | AF29: 1.2263874e-06 | AG29: 2.9557268e-05 | AH29: 0.00017596144 | AI29: 0.0019530235 | AJ29: 0.038276611 | AK29: 0.66468351 | AL29: 0.91766667 | AM29: 1.0051 | AN29: 1.0779917 | AO29: 1.1605167 | AP29: 1.8139328 | AQ29: 1.8294231 | AR29: 2.3496317 | AS29: 2.920363 | AT29: 3.0774751 | AU29: 2.9251194 | AV29: 2.43439 | AW29: 2.1753267 | AX29: 1.9470583 | AY29: 1.8337667 | AZ29: 1.9994282 | BA29: 1.7592267 | BB29: 1.6728288 | BC29: 1.9530686 | BD29: 2.1573457
A30: Brunei Darussalam | B30: BRN | C30: 3.06122 | D30: 3.06122 | E30: 3.06122 | F30: 3.06122 | G30: 3.06122 | H30: 3.06122 | I30: 3.06122 | J30: 3.06122 | K30: 3.06122 | L30: 3.06122 | M30: 3.06122 | N30: 3.0522604 | O30: 2.8195559 | P30: 2.4585797 | Q30: 2.4368667 | R30: 2.3713 | S30: 2.4708417 | T30: 2.4394 | U30: 2.274025 | V30: 2.1745583 | W30: 2.1412083 | X30: 2.1126917 | Y30: 2.140025 | Z30: 2.11305 | AA30: 2.1330833 | AB30: 2.20015 | AC30: 2.1774167 | AD30: 2.1059833 | AE30: 2.012425 | AF30: 1.9502583 | AG30: 1.8125333 | AH30: 1.72755 | AI30: 1.6289667 | AJ30: 1.6157908 | AK30: 1.5274442 | AL30: 1.417375 | AM30: 1.4100408 | AN30: 1.4848058 | AO30: 1.6736017 | AP30: 1.6949567 | AQ30: 1.7239633 | AR30: 1.7917225 | AS30: 1.7905883 | AT30: 1.7421833 | AU30: 1.6902283 | AV30: 1.6643975 | AW30: 1.5889333 | AX30: 1.5071017 | AY30: 1.4171667 | AZ30: 1.4545693 | BA30: 1.3635095 | BB30: 1.257913 | BC30: 1.249567 | BD30: 1.2511657
A31: Bulgaria | B31: BGR | C31: 0.00117 | D31: 0.00117 | E31: 0.00117 | F31: 0.00117 | G31: 0.00117 | H31: 0.00117 | I31: 0.00117 | J31: 0.00117 | K31: 0.00117 | L31: 0.00117 | M31: 0.00117 | N31: 0.00117 | O31: 0.00108 | P31: 0.00097916667 | Q31: 0.00097 | R31: .. | S31: .. | T31: .. | U31: .. | V31: .. | W31: .. | X31: .. | Y31: .. | Z31: .. | AA31: .. | AB31: 0.00103 | AC31: 0.00094 | AD31: 0.00087 | AE31: 0.00083 | AF31: 0.00084 | AG31: 0.00219 | AH31: 0.01778825 | AI31: 0.023341167 | AJ31: 0.027593583 | AK31: 0.054133667 | AL31: 0.067170833 | AM31: 0.17788867 | AN31: 1.6818792 | AO31: 1.7603583 | AP31: 1.8363833 | AQ31: 2.123275 | AR31: 2.1847083 | AS31: 2.076975 | AT31: 1.7327017 | AU31: 1.5751089 | AV31: 1.5741333 | AW31: 1.5592667 | AX31: 1.42905 | AY31: 1.3371167 | AZ31: 1.4066917 | BA31: 1.4773917 | BB31: 1.4064583 | BC31: 1.52205 | BD31: 1.4735667
A32: Burkina Faso | B32: BFA | C32: 245.1951 | D32: 245.2601 | E32: 245.01385 | F32: 245.01635 | G32: 245.02718 | H32: 245.06093 | I32: 245.67844 | J32: 246.00094 | K32: 247.56469 | L32: 259.96057 | M32: 276.40314 | N32: 275.35646 | O32: 252.02763 | P32: 222.88918 | Q32: 240.70467 | R32: 214.3129 | S32: 238.95049 | T32: 245.67969 | U32: 225.65586 | V32: 212.72164 | W32: 211.27956 | X32: 271.73145 | Y32: 328.60625 | Z32: 381.06604 | AA32: 436.95667 | AB32: 449.26296 | AC32: 346.3059 | AD32: 300.53656 | AE32: 297.84822 | AF32: 319.0083 | AG32: 272.26479 | AH32: 282.10691 | AI32: 264.6918 | AJ32: 283.16258 | AK32: 555.2047 | AL32: 499.14843 | AM32: 511.55243 | AN32: 583.66937 | AO32: 589.95177 | AP32: 615.69913 | AQ32: 711.97627 | AR32: 733.03851 | AS32: 696.9882 | AT32: 581.20031 | AU32: 528.28481 | AV32: 527.46814 | AW32: 522.89011 | AX32: 479.26678 | AY32: 447.80526 | AZ32: 472.18629 | BA32: 495.27702 | BB32: 471.86611 | BC32: 510.52714 | BD32: 494.04004
A33: Burundi | B33: BDI | C33: 50 | D33: 50 | E33: 50 | F33: 50 | G33: 50 | H33: 84.375 | I33: 87.5 | J33: 87.5 | K33: 87.5 | L33: 87.5 | M33: 87.5 | N33: 87.5 | O33: 87.5 | P33: 80.026083 | Q33: 78.75 | R33: 78.75 | S33: 86.25 | T33: 90 | U33: 90 | V33: 90 | W33: 90 | X33: 90 | Y33: 90 | Z33: 92.948333 | AA33: 119.70917 | AB33: 120.69075 | AC33: 114.17108 | AD33: 123.56383 | AE33: 140.395 | AF33: 158.66667 | AG33: 171.25542 | AH33: 181.51258 | AI33: 208.30267 | AJ33: 242.78 | AK33: 252.6625 | AL33: 249.7575 | AM33: 302.74667 | AN33: 352.35083 | AO33: 447.76583 | AP33: 563.5625 | AQ33: 720.67333 | AR33: 830.35333 | AS33: 930.74917 | AT33: 1082.62 | AU33: 1100.9 | AV33: 1081.5772 | AW33: 1028.6836 | AX33: 1081.8697 | AY33: 1185.6908 | AZ33: 1230.1792 | BA33: 1230.7483 | BB33: 1261.0733 | BC33: 1442.5056 | BD33: 1555.0908
A34: Cambodia | B34: KHM | C34: 28.75 | D34: 28.75 | E34: 28.75 | F34: 28.75 | G34: 28.75 | H34: 28.75 | I34: 28.75 | J34: 28.75 | K34: 28.75 | L34: 28.75 | M34: 28.75 | N34: 28.36017 | O34: 27.053417 | P34: 24.515167 | Q34: 25.408167 | R34: 25.54325 | S34: 30.229083 | T34: 34.046492 | U34: 35.50075 | V34: 37.433 | W34: 40.174917 | X34: 48.694667 | Y34: 58.293333 | Z34: 71.685833 | AA34: 84.877917 | AB34: 91.631667 | AC34: 80.144917 | AD34: 72.465833 | AE34: 72.0675 | AF34: 77.978083 | AG34: 70.031333 | AH34: 71.408333 | AI34: 68.017583 | AJ34: 80.426597 | AK34: 81.890833 | AL34: 76.853333 | AM34: 82.591467 | AN34: 93.176667 | AO34: 98.1575 | AP34: 103.50243 | AQ34: 119.68715 | AR34: 123.22783 | AS34: 117.16757 | AT34: 97.702988 | AU34: 88.807599 | AV34: 88.670312 | AW34: 87.90072 | AX34: 80.567397 | AY34: 75.27854 | AZ34: 79.377127 | BA34: 83.258807 | BB34: 79.323304 | BC34: 85.822435 | BD34: 83.050863
A35: Cameroon | B35: CMR | C35: 35 | D35: 35 | E35: 35 | F35: 35 | G35: 35 | H35: 35 | I35: 35 | J35: 35 | K35: 35 | L35: 43.558333 | M35: 55.54 | N35: 75.821667 | O35: 162.25 | P35: 244.91667 | Q35: .. | R35: .. | S35: .. | T35: .. | U35: .. | V35: .. | W35: .. | X35: .. | Y35: .. | Z35: .. | AA35: .. | AB35: .. | AC35: .. | AD35: .. | AE35: .. | AF35: .. | AG35: 426.25 | AH35: 718.33333 | AI35: 1266.5833 | AJ35: 2689 | AK35: 2545.25 | AL35: 2450.8333 | AM35: 2624.0833 | AN35: 2946.25 | AO35: 3744.4167 | AP35: 3807.8333 | AQ35: 3840.75 | AR35: 3916.3333 | AS35: 3912.0833 | AT35: 3973.3333 | AU35: 4016.25 | AV35: 4092.5 | AW35: 4103.25 | AX35: 4056.1667 | AY35: 4054.1667 | AZ35: 4139.3333 | BA35: 4184.9167 | BB35: 4058.5 | BC35: 4033 | BD35: 4027.25
A36: Canada | B36: CAN | C36: 245.1951 | D36: 245.2601 | E36: 245.01385 | F36: 245.01635 | G36: 245.02718 | H36: 245.06093 | I36: 245.67844 | J36: 246.00094 | K36: 247.56469 | L36: 259.96057 | M36: 276.40314 | N36: 275.35646 | O36: 252.02763 | P36: 222.88918 | Q36: 240.70467 | R36: 214.3129 | S36: 238.95049 | T36: 245.67969 | U36: 225.65586 | V36: 212.72164 | W36: 211.27956 | X36: 271.73145 | Y36: 328.60625 | Z36: 381.06604 | AA36: 436.95667 | AB36: 449.26296 | AC36: 346.3059 | AD36: 300.53656 | AE36: 297.84822 | AF36: 319.0083 | AG36: 272.26479 | AH36: 282.10691 | AI36: 264.6918 | AJ36: 283.16258 | AK36: 555.2047 | AL36: 499.14843 | AM36: 511.55243 | AN36: 583.66937 | AO36: 589.95177 | AP36: 615.69913 | AQ36: 711.97627 | AR36: 733.03851 | AS36: 696.9882 | AT36: 581.20031 | AU36: 528.28481 | AV36: 527.46814 | AW36: 522.89011 | AX36: 479.26678 | AY36: 447.80526 | AZ36: 472.18629 | BA36: 495.27702 | BB36: 471.86611 | BC36: 510.52714 | BD36: 494.04004
A37: Cape Verde | B37: CPV | C37: 0.96978333 | D37: 1.0130667 | E37: 1.0687667 | F37: 1.0785083 | G37: 1.0786083 | H37: 1.0779833 | I37: 1.0773167 | J37: 1.0787083 | K37: 1.077475 | L37: 1.076775 | M37: 1.044915 | N37: 1.0097917 | O37: 0.98993333 | P37: 1.0000833 | Q37: 0.97803333 | R37: 1.0171583 | S37: 0.986025 | T37: 1.06345 | U37: 1.140675 | V37: 1.171425 | W37: 1.1692167 | X37: 1.1989083 | Y37: 1.2337333 | Z37: 1.2324167 | AA37: 1.2950667 | AB37: 1.3654833 | AC37: 1.3895 | AD37: 1.3259917 | AE37: 1.2307083 | AF37: 1.1839917 | AG37: 1.166775 | AH37: 1.1457167 | AI37: 1.208725 | AJ37: 1.2900742 | AK37: 1.3656383 | AL37: 1.3724408 | AM37: 1.3634683 | AN37: 1.3846167 | AO37: 1.4834631 | AP37: 1.4857317 | AQ37: 1.48511 | AR37: 1.5487608 | AS37: 1.5693183 | AT37: 1.4010517 | AU37: 1.3010192 | AV37: 1.2117633 | AW37: 1.1343633 | AX37: 1.0740992 | AY37: 1.06704 | AZ37: 1.1431006 | BA37: 1.0301628 | BB37: 0.98953069 | BC37: 0.99918831 | BD37: 1.0297966
A38: Cayman Islands | B38: CYM | C38: 0.71428571 | D38: 0.71428571 | E38: 0.71428571 | F38: 0.71428571 | G38: 0.71428571 | H38: 0.71428571 | I38: 0.71428571 | J38: 0.72607141 | K38: 0.83333333 | L38: 0.83333333 | M38: 0.82741502 | N38: 0.83275503 | O38: 0.79936051 | P38: 0.81566069 | Q38: 0.833333 | R38: 0.833333 | S38: 0.833333 | T38: 0.833333 | U38: 0.833333 | V38: 0.833333 | W38: 0.833333 | X38: 0.833333 | Y38: 0.833333 | Z38: 0.833333 | AA38: 0.833333 | AB38: 0.833333 | AC38: 0.833333 | AD38: 0.833333 | AE38: 0.833333 | AF38: 0.833332 | AG38: 0.83333 | AH38: 0.83333 | AI38: 0.83333 | AJ38: 0.83333 | AK38: 0.83333 | AL38: 0.83333 | AM38: 0.83333 | AN38: 0.833331 | AO38: 0.83333 | AP38: 0.83333 | AQ38: 0.83333 | AR38: 0.83333 | AS38: 0.83333 | AT38: 0.83333 | AU38: 0.83333 | AV38: 0.83333 | AW38: 0.83333 | AX38: .. | AY38: .. | AZ38: .. | BA38: .. | BB38: .. | BC38: .. | BD38: ..
A39: Central African Republic | B39: CAF | C39: 245.1951 | D39: 245.2601 | E39: 245.01385 | F39: 245.01635 | G39: 245.02718 | H39: 245.06093 | I39: 245.67844 | J39: 246.00094 | K39: 247.56469 | L39: 259.96057 | M39: 276.40314 | N39: 275.35646 | O39: 252.02763 | P39: 222.88918 | Q39: 240.70467 | R39: 214.3129 | S39: 238.95049 | T39: 245.67969 | U39: 225.65586 | V39: 212.72164 | W39: 211.27956 | X39: 271.73145 | Y39: 328.60625 | Z39: 381.06604 | AA39: 436.95667 | AB39: 449.26296 | AC39: 346.3059 | AD39: 300.53656 | AE39: 297.84822 | AF39: 319.0083 | AG39: 272.26479 | AH39: 282.10691 | AI39: 264.6918 | AJ39: 283.16258 | AK39: 555.2047 | AL39: 499.14843 | AM39: 511.55243 | AN39: 583.66937 | AO39: 589.95177 | AP39: 615.69913 | AQ39: 711.97627 | AR39: 733.03851 | AS39: 696.9882 | AT39: 581.20031 | AU39: 528.28481 | AV39: 527.46814 | AW39: 522.89011 | AX39: 479.26678 | AY39: 447.80526 | AZ39: 472.18629 | BA39: 495.27702 | BB39: 471.86611 | BC39: 510.52714 | BD39: 494.04004
A40: Chad | B40: TCD | C40: 245.1951 | D40: 245.2601 | E40: 245.01385 | F40: 245.01635 | G40: 245.02718 | H40: 245.06093 | I40: 245.67844 | J40: 246.00094 | K40: 247.56469 | L40: 259.96057 | M40: 276.40314 | N40: 275.35646 | O40: 252.02763 | P40: 222.88918 | Q40: 240.70467 | R40: 214.3129 | S40: 238.95049 | T40: 245.67969 | U40: 225.65586 | V40: 212.72164 | W40: 211.27956 | X40: 271.73145 | Y40: 328.60625 | Z40: 381.06604 | AA40: 436.95667 | AB40: 449.26296 | AC40: 346.3059 | AD40: 300.53656 | AE40: 297.84822 | AF40: 319.0083 | AG40: 272.26479 | AH40: 282.10691 | AI40: 264.6918 | AJ40: 283.16258 | AK40: 555.2047 | AL40: 499.14843 | AM40: 511.55243 | AN40: 583.66937 | AO40: 589.95177 | AP40: 615.69913 | AQ40: 711.97627 | AR40: 733.03851 | AS40: 696.9882 | AT40: 581.20031 | AU40: 528.28481 | AV40: 527.46814 | AW40: 522.89011 | AX40: 479.26678 | AY40: 447.80526 | AZ40: 472.18629 | BA40: 495.27702 | BB40: 471.86611 | BC40: 510.52714 | BD40: 494.04004
A41: Channel Islands | B41: CHI | C41: .. | D41: .. | E41: .. | F41: .. | G41: .. | H41: .. | I41: .. | J41: .. | K41: .. | L41: .. | M41: .. | N41: .. | O41: .. | P41: .. | Q41: .. | R41: .. | S41: .. | T41: .. | U41: .. | V41: .. | W41: .. | X41: .. | Y41: .. | Z41: .. | AA41: .. | AB41: .. | AC41: .. | AD41: .. | AE41: .. | AF41: .. | AG41: .. | AH41: .. | AI41: .. | AJ41: .. | AK41: .. | AL41: .. | AM41: .. | AN41: .. | AO41: .. | AP41: .. | AQ41: .. | AR41: .. | AS41: .. | AT41: .. | AU41: .. | AV41: .. | AW41: .. | AX41: .. | AY41: .. | AZ41: .. | BA41: .. | BB41: .. | BC41: .. | BD41: ..
A42: Chile | B42: CHL | C42: 0.0010489694 | D42: 0.001050136 | E42: 0.0010576358 | F42: 0.001621786 | G42: 0.0023074326 | H42: 0.0031566578 | I42: 0.0038511376 | J42: 0.0050682687 | K42: 0.0068764659 | L42: 0.0086175817 | M42: 0.011277504 | N42: 0.012208644 | O42: 0.020835225 | P42: 0.071641908 | Q42: 0.59282626 | R42: 4.9104167 | S42: 13.054167 | T42: 21.535833 | U42: 31.655833 | V42: 37.245833 | W42: 39 | X42: 39 | Y42: 50.908333 | Z42: 78.788333 | AA42: 98.4775 | AB42: 160.86 | AC42: 192.93 | AD42: 219.40667 | AE42: 245.01167 | AF42: 266.95417 | AG42: 304.90333 | AH42: 349.21583 | AI42: 362.57583 | AJ42: 404.16583 | AK42: 420.17667 | AL42: 396.77333 | AM42: 412.26667 | AN42: 419.295 | AO42: 460.2875 | AP42: 508.77667 | AQ42: 539.5875 | AR42: 634.93833 | AS42: 688.93667 | AT42: 691.3975 | AU42: 609.52917 | AV42: 559.7675 | AW42: 530.275 | AX42: 522.46417 | AY42: 522.46104 | AZ42: 560.85989 | BA42: 510.24917 | BB42: 483.6675 | BC42: 486.4713 | BD42: 495.27288
A43: China | B43: CHN | C43: 2.4618095 | D43: 2.4618095 | E43: 2.4618095 | F43: 2.4618095 | G43: 2.4618095 | H43: 2.4618095 | I43: 2.4618095 | J43: 2.4618095 | K43: 2.4618095 | L43: 2.4618095 | M43: 2.4618095 | N43: 2.4618095 | O43: 2.245067 | P43: 1.989416 | Q43: 1.9612 | R43: 1.8598 | S43: 1.9414 | T43: 1.8578238 | U43: 1.6836 | V43: 1.555 | W43: 1.4984 | X43: 1.7045333 | Y43: 1.8925417 | Z43: 1.975675 | AA43: 2.3200417 | AB43: 2.9366583 | AC43: 3.4527917 | AD43: 3.7221 | AE43: 3.7221 | AF43: 3.7651083 | AG43: 4.7832083 | AH43: 5.3233917 | AI43: 5.5145917 | AJ43: 5.7619583 | AK43: 8.6187427 | AL43: 8.3514167 | AM43: 8.314175 | AN43: 8.2898167 | AO43: 8.2789583 | AP43: 8.27825 | AQ43: 8.2785042 | AR43: 8.2770683 | AS43: 8.2769575 | AT43: 8.2770367 | AU43: 8.2768008 | AV43: 8.1943167 | AW43: 7.9734383 | AX43: 7.6075325 | AY43: 6.948655 | AZ43: 6.8314161 | BA43: 6.770269 | BB43: 6.4614613 | BC43: 6.3123328 | BD43: 6.1957583
A44: Colombia | B44: COL | C44: 6.635 | D44: 6.7 | E44: 6.9012083 | F44: 9 | G44: 9 | H44: 10.475 | I44: 13.5 | J44: 14.506392 | K44: 16.290667 | L44: 17.320142 | M44: 18.4431 | N44: 19.931933 | O44: 21.865642 | P44: 23.636983 | Q44: 26.064125 | R44: 30.928942 | S44: 34.693925 | T44: 36.774867 | U44: 39.094642 | V44: 42.549775 | W44: 47.280308 | X44: 54.49055 | Y44: 64.084717 | Z44: 78.8543 | AA44: 100.81724 | AB44: 142.31167 | AC44: 194.26142 | AD44: 242.6075 | AE44: 299.17383 | AF44: 382.56808 | AG44: 502.25925 | AH44: 633.04517 | AI44: 759.282 | AJ44: 863.06468 | AK44: 844.83589 | AL44: 912.82641 | AM44: 1036.6864 | AN44: 1140.9629 | AO44: 1426.0375 | AP44: 1756.2308 | AQ44: 2087.9038 | AR44: 2299.6332 | AS44: 2504.2413 | AT44: 2877.6525 | AU44: 2628.6129 | AV44: 2320.8342 | AW44: 2361.1394 | AX44: 2078.2918 | AY44: 1967.7113 | AZ44: 2158.2559 | BA44: 1898.5696 | BB44: 1848.1395 | BC44: 1796.8959 | BD44: 1868.7853
A45: Comoros | B45: COM | C45: 245.19302 | D45: 245.25802 | E45: 245.01177 | F45: 245.01427 | G45: 245.02511 | H45: 245.05886 | I45: 245.67635 | J45: 245.99885 | K45: 247.5626 | L45: 259.95837 | M45: 276.40079 | N45: 275.35431 | O45: 252.02549 | P45: 222.88729 | Q45: 240.70263 | R45: 214.31108 | S45: 238.94847 | T45: 245.6776 | U45: 225.65395 | V45: 212.71984 | W45: 211.27777 | X45: 271.72915 | Y45: 328.60347 | Z45: 381.06281 | AA45: 436.95296 | AB45: 449.25916 | AC45: 346.30297 | AD45: 300.53402 | AE45: 297.84569 | AF45: 319.0056 | AG45: 272.26248 | AH45: 282.10452 | AI45: 264.68956 | AJ45: 283.16018 | AK45: 416.39882 | AL45: 374.35709 | AM45: 383.65999 | AN45: 437.74709 | AO45: 442.45884 | AP45: 461.77458 | AQ45: 533.98248 | AR45: 549.77916 | AS45: 522.74142 | AT45: 435.90046 | AU45: 396.21381 | AV45: 395.60131 | AW45: 392.16778 | AX45: 359.45027 | AY45: 335.85411 | AZ45: 354.1399 | BA45: 371.45795 | BB45: 353.89977 | BC45: 382.89555 | BD45: 370.53022
A46: Congo, Dem. Rep. | B46: COD | C46: 1.7e-13 | D46: 1.75e-13 | E46: 2.1e-13 | F46: 2.525e-13 | G46: 5.5e-13 | H46: 5.5e-13 | I46: 5.5e-13 | J46: 1.1566667e-12 | K46: 1.67e-12 | L46: 1.67e-12 | M46: 1.67e-12 | N46: 1.67e-12 | O46: 1.67e-12 | P46: 1.67e-12 | Q46: 1.67e-12 | R46: 1.67e-12 | S46: 2.6408333e-12 | T46: 2.855e-12 | U46: 2.7866667e-12 | V46: 5.7608333e-12 | W46: 9.3308333e-12 | X46: 1.4608333e-11 | Y46: 1.91625e-11 | Z46: 4.2955e-11 | AA46: 1.2040417e-10 | AB46: 1.662075e-10 | AC46: 1.9870583e-10 | AD46: 3.74595e-10 | AE46: 6.2343e-10 | AF46: 1.2712083e-09 | AG46: 2.3947483e-09 | AH46: 5.1945694e-08 | AI46: 2.1513626e-06 | AJ46: 2.5144168e-05 | AK46: 0.011941192 | AL46: 0.070244717 | AM46: 0.50184918 | AN46: 1.3134476 | AO46: 1.6072324 | AP46: 4.0206868 | AQ46: 21.831112 | AR46: 206.73851 | AS46: 346.68793 | AT46: 405.39745 | AU46: 399.47579 | AV46: 473.90801 | AW46: 468.27882 | AX46: 516.74989 | AY46: 559.29251 | AZ46: 809.78583 | BA46: 905.91346 | BB46: 919.4913 | BC46: 919.75541 | BD46: 919.79277
A47: Congo, Rep. | B47: COG | C47: 245.1951 | D47: 245.2601 | E47: 245.01385 | F47: 245.01635 | G47: 245.02718 | H47: 245.06093 | I47: 245.67844 | J47: 246.00094 | K47: 247.56469 | L47: 259.96057 | M47: 276.40314 | N47: 275.35646 | O47: 252.02763 | P47: 222.88918 | Q47: 240.70467 | R47: 214.3129 | S47: 238.95049 | T47: 245.67969 | U47: 225.65586 | V47: 212.72164 | W47: 211.27956 | X47: 271.73145 | Y47: 328.60625 | Z47: 381.06604 | AA47: 436.95667 | AB47: 449.26296 | AC47: 346.3059 | AD47: 300.53656 | AE47: 297.84822 | AF47: 319.0083 | AG47: 272.26479 | AH47: 282.10691 | AI47: 264.6918 | AJ47: 283.16258 | AK47: 555.2047 | AL47: 499.14843 | AM47: 511.55243 | AN47: 583.66937 | AO47: 589.95177 | AP47: 615.69913 | AQ47: 711.97627 | AR47: 733.03851 | AS47: 696.9882 | AT47: 581.20031 | AU47: 528.28481 | AV47: 527.46814 | AW47: 522.89011 | AX47: 479.26678 | AY47: 447.80526 | AZ47: 472.18629 | BA47: 495.27702 | BB47: 471.86611 | BC47: 510.52714 | BD47: 494.04004
A48: Costa Rica | B48: CRI | C48: 5.615 | D48: 5.9516667 | E48: 6.625 | F48: 6.625 | G48: 6.625 | H48: 6.625 | I48: 6.625 | J48: 6.625 | K48: 6.625 | L48: 6.625 | M48: 6.625 | N48: 6.6258333 | O48: 6.635 | P48: 6.6467583 | Q48: 7.9299973 | R48: 8.57 | S48: 8.57 | T48: 8.57 | U48: 8.57 | V48: 8.57 | W48: 8.57 | X48: 21.763333 | Y48: 37.406667 | Z48: 41.094167 | AA48: 44.532683 | AB48: 50.45335 | AC48: 55.985892 | AD48: 62.7762 | AE48: 75.804733 | AF48: 81.504208 | AG48: 91.579292 | AH48: 122.43242 | AI48: 134.50633 | AJ48: 142.17167 | AK48: 157.06667 | AL48: 179.72917 | AM48: 207.68917 | AN48: 232.5975 | AO48: 257.22917 | AP48: 285.68469 | AQ48: 308.18667 | AR48: 328.87083 | AS48: 359.81753 | AT48: 398.66222 | AU48: 437.935 | AV48: 477.78674 | AW48: 511.30182 | AX48: 516.61739 | AY48: 526.23551 | AZ48: 573.28796 | BA48: 525.8292 | BB48: 505.66424 | BC48: 502.90146 | BD48: 499.76683
A49: Cote d'Ivoire | B49: CIV | C49: 245.1951 | D49: 245.2601 | E49: 245.01385 | F49: 245.01635 | G49: 245.02718 | H49: 245.06093 | I49: 245.67844 | J49: 246.00094 | K49: 247.56469 | L49: 259.96057 | M49: 276.40314 | N49: 275.35646 | O49: 252.02763 | P49: 222.88918 | Q49: 240.70467 | R49: 214.3129 | S49: 238.95049 | T49: 245.67969 | U49: 225.65586 | V49: 212.72164 | W49: 211.27956 | X49: 271.73145 | Y49: 328.60625 | Z49: 381.06604 | AA49: 436.95667 | AB49: 449.26296 | AC49: 346.3059 | AD49: 300.53656 | AE49: 297.84822 | AF49: 319.0083 | AG49: 272.26479 | AH49: 282.10691 | AI49: 264.6918 | AJ49: 283.16258 | AK49: 555.2047 | AL49: 499.14843 | AM49: 511.55243 | AN49: 583.66937 | AO49: 589.95177 | AP49: 615.69913 | AQ49: 711.97627 | AR49: 733.03851 | AS49: 696.9882 | AT49: 581.20031 | AU49: 528.28481 | AV49: 527.46814 | AW49: 522.89011 | AX49: 479.26678 | AY49: 447.80526 | AZ49: 472.18629 | BA49: 495.27702 | BB49: 471.86611 | BC49: 510.52714 | BD49: 494.04004
A50: Croatia | B50: HRV | C50: .. | D50: .. | E50: .. | F50: .. | G50: .. | H50: .. | I50: .. | J50: .. | K50: .. | L50: .. | M50: .. | N50: .. | O50: .. | P50: .. | Q50: .. | R50: .. | S50: .. | T50: .. | U50: .. | V50: .. | W50: .. | X50: .. | Y50: .. | Z50: .. | AA50: .. | AB50: .. | AC50: .. | AD50: .. | AE50: .. | AF50: .. | AG50: .. | AH50: .. | AI50: 0.26329825 | AJ50: 3.5791489 | AK50: 5.9980114 | AL50: 5.2307561 | AM50: 5.4341612 | AN50: 6.1605826 | AO50: 6.3632857 | AP50: 7.1117428 | AQ50: 8.2776664 | AR50: 8.341541 | AS50: 7.8716825 | AT50: 6.7049688 | AU50: 6.0343407 | AV50: 5.9492369 | AW50: 5.8377932 | AX50: 5.3645357 | AY50: 4.9350397 | AZ50: 5.2839464 | BA50: 5.4980106 | BB50: 5.3438697 | BC50: 5.8502918 | BD50: 5.7048802
A51: Cuba | B51: CUB | C51: .. | D51: .. | E51: .. | F51: .. | G51: .. | H51: .. | I51: .. | J51: .. | K51: .. | L51: .. | M51: .. | N51: .. | O51: .. | P51: .. | Q51: .. | R51: .. | S51: .. | T51: .. | U51: .. | V51: .. | W51: .. | X51: .. | Y51: .. | Z51: .. | AA51: .. | AB51: .. | AC51: .. | AD51: .. | AE51: .. | AF51: .. | AG51: .. | AH51: .. | AI51: .. | AJ51: .. | AK51: .. | AL51: .. | AM51: .. | AN51: .. | AO51: .. | AP51: .. | AQ51: .. | AR51: .. | AS51: .. | AT51: .. | AU51: .. | AV51: .. | AW51: .. | AX51: .. | AY51: .. | AZ51: .. | BA51: .. | BB51: .. | BC51: .. | BD51: ..
A52: Curacao | B52: CUW | C52: .. | D52: .. | E52: .. | F52: .. | G52: .. | H52: .. | I52: .. | J52: .. | K52: .. | L52: .. | M52: .. | N52: .. | O52: .. | P52: .. | Q52: .. | R52: .. | S52: .. | T52: .. | U52: .. | V52: .. | W52: .. | X52: .. | Y52: .. | Z52: .. | AA52: .. | AB52: .. | AC52: .. | AD52: .. | AE52: .. | AF52: .. | AG52: .. | AH52: .. | AI52: .. | AJ52: .. | AK52: .. | AL52: .. | AM52: .. | AN52: .. | AO52: .. | AP52: .. | AQ52: .. | AR52: .. | AS52: .. | AT52: .. | AU52: .. | AV52: .. | AW52: .. | AX52: .. | AY52: .. | AZ52: .. | BA52: .. | BB52: .. | BC52: .. | BD52: ..
A53: Cyprus | B53: CYP | C53: 0.357143 | D53: 0.357143 | E53: 0.357143 | F53: 0.357143 | G53: 0.357143 | H53: 0.357143 | I53: 0.357143 | J53: 0.36210333 | K53: 0.416667 | L53: 0.416667 | M53: 0.416667 | N53: 0.4107306 | O53: 0.38357237 | P53: 0.3499505 | Q53: 0.36469271 | R53: 0.36890724 | S53: 0.41049569 | T53: 0.40812158 | U53: 0.37351258 | V53: 0.35444386 | W53: 0.35305169 | X53: 0.42143076 | Y53: 0.4753859 | Z53: 0.52664077 | AA53: 0.58838586 | AB53: 0.61255232 | AC53: 0.51814308 | AD53: 0.48109658 | AE53: 0.46662883 | AF53: 0.49462492 | AG53: 0.45807992 | AH53: 0.4644285 | AI53: 0.44954858 | AJ53: 0.49740517 | AK53: 0.492191 | AL53: 0.45242017 | AM53: 0.46631125 | AN53: 0.51389733 | AO53: 0.51782558 | AP53: 0.54294775 | AQ53: 0.62240912 | AR53: 0.64310703 | AS53: 0.61065999 | AT53: 0.51744326 | AU53: 0.46860055 | AV53: 0.46407051 | AW53: 0.45891595 | AX53: 0.426125 | AY53: .. | AZ53: .. | BA53: .. | BB53: .. | BC53: .. | BD53: ..
A54: Czech Republic | B54: CZE | C54: .. | D54: .. | E54: .. | F54: .. | G54: .. | H54: .. | I54: .. | J54: .. | K54: .. | L54: .. | M54: .. | N54: .. | O54: .. | P54: .. | Q54: .. | R54: .. | S54: .. | T54: .. | U54: .. | V54: .. | W54: .. | X54: .. | Y54: .. | Z54: .. | AA54: .. | AB54: .. | AC54: .. | AD54: .. | AE54: .. | AF54: .. | AG54: .. | AH54: .. | AI54: .. | AJ54: 29.152833 | AK54: 28.785083 | AL54: 26.540667 | AM54: 27.144917 | AN54: 31.698417 | AO54: 32.281167 | AP54: 34.56925 | AQ54: 38.598417 | AR54: 38.035328 | AS54: 32.738518 | AT54: 28.209 | AU54: 25.69975 | AV54: 23.957417 | AW54: 22.595583 | AX54: 20.293667 | AY54: 17.071667 | AZ54: 19.063 | BA54: 19.09825 | BB54: 17.695917 | BC54: 19.5775 | BD54: 19.570583
A55: Denmark | B55: DNK | C55: 6.90714 | D55: 6.90714 | E55: 6.90714 | F55: 6.90714 | G55: 6.90714 | H55: 6.90714 | I55: 6.90714 | J55: 6.9565417 | K55: 7.5 | L55: 7.5 | M55: 7.5 | N55: 7.426338 | O55: 6.9492917 | P55: 6.0495 | Q55: 6.0949 | R55: 5.74615 | S55: 6.045025 | T55: 6.0031917 | U55: 5.514625 | V55: 5.2609583 | W55: 5.6359417 | X55: 7.1233667 | Y55: 8.3324417 | Z55: 9.1449917 | AA55: 10.356592 | AB55: 10.596392 | AC55: 8.0909917 | AD55: 6.8403167 | AE55: 6.731525 | AF55: 7.310175 | AG55: 6.1885583 | AH55: 6.3964583 | AI55: 6.0361333 | AJ55: 6.4839392 | AK55: 6.3605517 | AL55: 5.6023667 | AM55: 5.7986717 | AN55: 6.6044592 | AO55: 6.7008267 | AP55: 6.97624 | AQ55: 8.0831442 | AR55: 8.3228175 | AS55: 7.8947142 | AT55: 6.5876733 | AU55: 5.9910567 | AV55: 5.99691 | AW55: 5.9467783 | AX55: 5.4437008 | AY55: 5.0981308 | AZ55: 5.3608667 | BA55: 5.624075 | BB55: 5.3687115 | BC55: 5.7924755 | BD55: 5.6163117
A56: Djibouti | B56: DJI | C56: 214.392 | D56: 214.392 | E56: 214.392 | F56: 214.392 | G56: 214.392 | H56: 214.392 | I56: 214.392 | J56: 214.392 | K56: 214.392 | L56: 214.392 | M56: 214.392 | N56: 213.77875 | O56: 197.466 | P56: 179.94233 | Q56: 177.721 | R56: 177.721 | S56: 177.721 | T56: 177.721 | U56: 177.721 | V56: 177.721 | W56: 177.721 | X56: 177.721 | Y56: 177.721 | Z56: 177.721 | AA56: 177.721 | AB56: 177.721 | AC56: 177.721 | AD56: 177.721 | AE56: 177.721 | AF56: 177.721 | AG56: 177.721 | AH56: 177.721 | AI56: 177.721 | AJ56: 177.721 | AK56: 177.721 | AL56: 177.721 | AM56: 177.721 | AN56: 177.721 | AO56: 177.721 | AP56: 177.721 | AQ56: 177.721 | AR56: 177.721 | AS56: 177.721 | AT56: 177.721 | AU56: 177.721 | AV56: 177.721 | AW56: 177.721 | AX56: 177.721 | AY56: 177.721 | AZ56: 177.721 | BA56: 177.721 | BB56: 177.721 | BC56: 177.721 | BD56: 177.721
A57: Dominica | B57: DMA | C57: 1.71429 | D57: 1.71429 | E57: 1.71429 | F57: 1.71429 | G57: 1.71429 | H57: 1.71429 | I57: 1.71429 | J57: 1.7619083 | K57: 2 | L57: 2 | M57: 2 | N57: 1.9748727 | O57: 1.9212781 | P57: 1.9592192 | Q57: 2.0532324 | R57: 2.1697958 | S57: 2.6146708 | T57: 2.7 | U57: 2.7 | V57: 2.7 | W57: 2.7 | X57: 2.7 | Y57: 2.7 | Z57: 2.7 | AA57: 2.7 | AB57: 2.7 | AC57: 2.7 | AD57: 2.7 | AE57: 2.7 | AF57: 2.7 | AG57: 2.7 | AH57: 2.7 | AI57: 2.7 | AJ57: 2.7 | AK57: 2.7 | AL57: 2.7 | AM57: 2.7 | AN57: 2.7 | AO57: 2.7 | AP57: 2.7 | AQ57: 2.7 | AR57: 2.7 | AS57: 2.7 | AT57: 2.7 | AU57: 2.7 | AV57: 2.7 | AW57: 2.7 | AX57: 2.7 | AY57: 2.7 | AZ57: 2.7 | BA57: 2.7 | BB57: 2.7 | BC57: 2.7 | BD57: 2.7
A58: Dominican Republic | B58: DOM | C58: 1 | D58: 1 | E58: 1 | F58: 1 | G58: 1 | H58: 1 | I58: 1 | J58: 1 | K58: 1 | L58: 1 | M58: 1 | N58: 1 | O58: 1 | P58: 1 | Q58: 1 | R58: 1 | S58: 1 | T58: 1 | U58: 1 | V58: 1 | W58: 1 | X58: 1 | Y58: 1 | Z58: 1 | AA58: 1 | AB58: 3.1126083 | AC58: 2.9043333 | AD58: 3.8447583 | AE58: 6.1125167 | AF58: 6.34 | AG58: 8.5253 | AH58: 12.692425 | AI58: 12.774183 | AJ58: 12.675783 | AK58: 13.160142 | AL58: 13.59735 | AM58: 13.774583 | AN58: 14.265475 | AO58: 15.266592 | AP58: 16.033083 | AQ58: 16.415017 | AR58: 16.951617 | AS58: 18.609825 | AT58: 30.830708 | AU58: 42.09883 | AV58: 30.510638 | AW58: 33.253692 | AX58: 33.311862 | AY58: 34.866102 | AZ58: 36.114052 | BA58: 37.306579 | BB58: 38.231559 | BC58: 39.335656 | BD58: 41.807735
A59: Ecuador | B59: ECU | C59: 15 | D59: 16.5 | E59: 18 | F59: 18 | G59: 18 | H59: 18 | I59: 18 | J59: 18 | K59: 18 | L59: 18 | M59: 20.9167 | N59: 25 | O59: 25.000138 | P59: 25.000042 | Q59: 25 | R59: 25 | S59: 25 | T59: 25 | U59: 25 | V59: 25 | W59: 25 | X59: 25 | Y59: 30.025833 | Z59: 44.115008 | AA59: 62.5359 | AB59: 69.55625 | AC59: 122.77924 | AD59: 170.46167 | AE59: 301.61083 | AF59: 526.34833 | AG59: 767.75083 | AH59: 1046.2493 | AI59: 1533.9617 | AJ59: 1919.105 | AK59: 2196.7283 | AL59: 2564.4942 | AM59: 3189.4742 | AN59: 3998.2667 | AO59: 5446.5729 | AP59: 11786.802 | AQ59: 24988.388 | AR59: 25000 | AS59: 25000 | AT59: 25000 | AU59: 25000 | AV59: 25000 | AW59: 25000 | AX59: .. | AY59: .. | AZ59: .. | BA59: .. | BB59: .. | BC59: .. | BD59: ..
A60: Egypt, Arab Rep. | B60: EGY | C60: 0.348242 | D60: 0.348242 | E60: 0.40448913 | F60: 0.43478261 | G60: 0.43478261 | H60: 0.43478261 | I60: 0.43478261 | J60: 0.43478261 | K60: 0.43478261 | L60: 0.43478261 | M60: 0.43478261 | N60: 0.434783 | O60: 0.43478261 | P60: 0.39795624 | Q60: 0.39130367 | R60: 0.39130367 | S60: 0.39130367 | T60: 0.39130367 | U60: 0.39130367 | V60: 0.7000007 | W60: 0.7000007 | X60: 0.7000007 | Y60: 0.7000007 | Z60: 0.7000007 | AA60: 0.7000007 | AB60: 0.7000007 | AC60: 0.7000007 | AD60: 0.7000007 | AE60: 0.7000007 | AF60: 0.86666667 | AG60: 1.55 | AH60: 3.1380083 | AI60: 3.3217483 | AJ60: 3.3525175 | AK60: 3.3851333 | AL60: 3.3922083 | AM60: 3.3914833 | AN60: 3.38875 | AO60: 3.388 | AP60: 3.39525 | AQ60: 3.47205 | AR60: 3.973 | AS60: 4.4996667 | AT60: 5.850875 | AU60: 6.1962417 | AV60: 5.7788333 | AW60: 5.7331667 | AX60: 5.6354333 | AY60: 5.4325 | AZ60: 5.5445533 | BA60: 5.6219429 | BB60: 5.9328277 | BC60: 6.0560583 | BD60: 6.870325
A61: El Salvador | B61: SLV | C61: 2.5 | D61: 2.5 | E61: 2.5 | F61: 2.5 | G61: 2.5 | H61: 2.5 | I61: 2.5 | J61: 2.5 | K61: 2.5 | L61: 2.5 | M61: 2.5 | N61: 2.5 | O61: 2.5000138 | P61: 2.5000042 | Q61: 2.4999979 | R61: 2.5 | S61: 2.5 | T61: 2.5 | U61: 2.5 | V61: 2.5 | W61: 2.5 | X61: 2.5 | Y61: 2.5 | Z61: 2.5 | AA61: 2.5 | AB61: 2.5 | AC61: 4.85215 | AD61: 5 | AE61: 5 | AF61: 5 | AG61: 6.8483333 | AH61: 8.0166667 | AI61: 8.3608333 | AJ61: 8.7025083 | AK61: 8.72875 | AL61: 8.7545833 | AM61: 8.755 | AN61: 8.75625 | AO61: 8.755 | AP61: 8.755 | AQ61: 8.755 | AR61: 8.75 | AS61: 8.75 | AT61: 8.75 | AU61: 8.75 | AV61: 8.75 | AW61: 8.75 | AX61: 8.75 | AY61: 8.75 | AZ61: 8.75 | BA61: 8.75 | BB61: 8.75 | BC61: 8.75 | BD61: 8.75
A62: Equatorial Guinea | B62: GNQ | C62: 245.1951 | D62: 245.2601 | E62: 245.01385 | F62: 245.01635 | G62: 245.02718 | H62: 245.06093 | I62: 245.67844 | J62: 246.00094 | K62: 247.56469 | L62: 259.96057 | M62: 276.40314 | N62: 258.65526 | O62: 252.02763 | P62: 222.88918 | Q62: 240.70467 | R62: 214.3129 | S62: 238.95049 | T62: 245.67969 | U62: 225.65586 | V62: 212.72164 | W62: 211.27956 | X62: 271.73145 | Y62: 328.60625 | Z62: 381.06604 | AA62: 436.95667 | AB62: 449.26296 | AC62: 346.3059 | AD62: 300.53656 | AE62: 297.84822 | AF62: 319.0083 | AG62: 272.26479 | AH62: 282.10691 | AI62: 264.6918 | AJ62: 283.16258 | AK62: 555.2047 | AL62: 499.14843 | AM62: 511.55243 | AN62: 583.66937 | AO62: 589.95177 | AP62: 615.69913 | AQ62: 711.97627 | AR62: 733.03851 | AS62: 696.9882 | AT62: 581.20031 | AU62: 528.28481 | AV62: 527.46814 | AW62: 522.89011 | AX62: 479.26678 | AY62: 447.80526 | AZ62: 472.18629 | BA62: 495.27702 | BB62: 471.86611 | BC62: 510.52714 | BD62: 494.04004
A63: Eritrea | B63: ERI | C63: 2.486859 | D63: 2.486859 | E63: 2.486859 | F63: 2.4881519 | G63: 2.5023737 | H63: 2.5023737 | I63: 2.5023737 | J63: 2.5023737 | K63: 2.5023737 | L63: 2.5023737 | M63: 2.5023737 | N63: 2.4958425 | O63: 2.3021838 | P63: 2.1007428 | Q63: 2.0719655 | R63: 2.0719655 | S63: 2.0719655 | T63: 2.0719655 | U63: 2.0719655 | V63: 2.0719655 | W63: 2.0719655 | X63: 2.0719655 | Y63: 2.0719655 | Z63: 2.0719655 | AA63: 2.0719655 | AB63: 2.0719655 | AC63: 2.0719655 | AD63: 2.0719655 | AE63: 2.0719655 | AF63: 2.0719655 | AG63: 2.0719655 | AH63: 2.0719655 | AI63: 2.805161 | AJ63: 5.0047475 | AK63: 5.470189 | AL63: 6.1641806 | AM63: 6.3577059 | AN63: 6.837275 | AO63: 7.3619304 | AP63: 8.1526333 | AQ63: 9.625 | AR63: 11.309452 | AS63: 13.958194 | AT63: 13.877891 | AU63: 13.7875 | AV63: 15.367917 | AW63: 15.375 | AX63: 15.375 | AY63: 15.375 | AZ63: 15.375 | BA63: 15.375 | BB63: 15.375 | BC63: 15.375 | BD63: 15.375
A64: Estonia | B64: EST | C64: .. | D64: .. | E64: .. | F64: .. | G64: .. | H64: .. | I64: .. | J64: .. | K64: .. | L64: .. | M64: .. | N64: .. | O64: .. | P64: .. | Q64: .. | R64: .. | S64: .. | T64: .. | U64: .. | V64: .. | W64: .. | X64: .. | Y64: .. | Z64: .. | AA64: .. | AB64: .. | AC64: .. | AD64: .. | AE64: .. | AF64: .. | AG64: .. | AH64: .. | AI64: .. | AJ64: 13.22275 | AK64: 12.99125 | AL64: 11.46475 | AM64: 12.038 | AN64: 13.88175 | AO64: 14.074667 | AP64: 14.677583 | AQ64: 16.968637 | AR64: 17.478072 | AS64: 16.611792 | AT64: 13.856411 | AU64: 12.595564 | AV64: 12.583787 | AW64: 12.465484 | AX64: 11.433853 | AY64: 10.694443 | AZ64: 11.257431 | BA64: 11.806848 | BB64: .. | BC64: .. | BD64: ..
A65: Ethiopia | B65: ETH | C65: 2.48447 | D65: 2.48447 | E65: 2.48447 | F65: 2.48447 | G65: 2.5 | H65: 2.5 | I65: 2.5 | J65: 2.5 | K65: 2.5 | L65: 2.5 | M65: 2.5 | N65: 2.493475 | O65: 2.3 | P65: 2.09875 | Q65: 2.07 | R65: 2.07 | S65: 2.07 | T65: 2.07 | U65: 2.07 | V65: 2.07 | W65: 2.07 | X65: 2.07 | Y65: 2.07 | Z65: 2.07 | AA65: 2.07 | AB65: 2.07 | AC65: 2.07 | AD65: 2.07 | AE65: 2.07 | AF65: 2.07 | AG65: 2.07 | AH65: 2.07 | AI65: 2.8025 | AJ65: 5 | AK65: 5.465 | AL65: 6.1583333 | AM65: 6.351675 | AN65: 6.7093417 | AO65: 7.1159083 | AP65: 7.94225 | AQ65: 8.2172583 | AR65: 8.4574917 | AS65: 8.56775 | AT65: 8.5996833 | AU65: 8.6355833 | AV65: 8.6664417 | AW65: 8.6986158 | AX65: 8.96595 | AY65: 9.5997417 | AZ65: 11.7776 | BA65: 14.40959 | BB65: 16.899226 | BC65: 17.704761 | BD65: ..
A66: Faeroe Islands | B66: FRO | C66: 6.90714 | D66: 6.90714 | E66: 6.90714 | F66: 6.90714 | G66: 6.90714 | H66: 6.90714 | I66: 6.90714 | J66: 6.956545 | K66: 7.5 | L66: 7.5 | M66: 7.5 | N66: 7.426338 | O66: 6.9492917 | P66: 6.0495 | Q66: 6.0949 | R66: 5.74615 | S66: 6.045025 | T66: 6.0031917 | U66: 5.514625 | V66: 5.2609583 | W66: 5.6359417 | X66: 7.1233667 | Y66: 8.3324417 | Z66: 9.1449917 | AA66: 10.356592 | AB66: 10.596392 | AC66: 8.0909917 | AD66: 6.8403167 | AE66: 6.731525 | AF66: 7.310175 | AG66: 6.1885583 | AH66: 6.3964583 | AI66: 6.0361333 | AJ66: 6.4839392 | AK66: 6.3605517 | AL66: 5.6023667 | AM66: 5.7986717 | AN66: 6.6044592 | AO66: 6.7008267 | AP66: 6.97624 | AQ66: 8.0831442 | AR66: 8.3228175 | AS66: 7.8947142 | AT66: 6.5876733 | AU66: 5.9910567 | AV66: 5.99691 | AW66: 5.9467783 | AX66: 5.4437008 | AY66: 5.0981308 | AZ66: 5.3608667 | BA66: 5.624075 | BB66: 5.3687115 | BC66: 5.7924755 | BD66: 5.6163117
A67: Fiji | B67: FJI | C67: 0.792858 | D67: 0.792858 | E67: 0.792858 | F67: 0.792858 | G67: 0.792858 | H67: 0.792858 | I67: 0.792858 | J67: 0.805854 | K67: 0.870834 | L67: 0.870834 | M67: 0.870834 | N67: 0.85882323 | O67: 0.82518371 | P67: 0.79422383 | Q67: 0.80560383 | R67: 0.82188306 | S67: 0.8977154 | T67: 0.91744033 | U67: 0.84677075 | V67: 0.83574325 | W67: 0.81796467 | X67: 0.85462658 | Y67: 0.93244867 | Z67: 1.0170203 | AA67: 1.0825967 | AB67: 1.1535542 | AC67: 1.1328658 | AD67: 1.2438583 | AE67: 1.4302583 | AF67: 1.4833333 | AG67: 1.4809083 | AH67: 1.4755575 | AI67: 1.5029908 | AJ67: 1.541775 | AK67: 1.464125 | AL67: 1.4063333 | AM67: 1.4033 | AN67: 1.443675 | AO67: 1.9868167 | AP67: 1.969625 | AQ67: 2.128625 | AR67: 2.2766333 | AS67: 2.1866917 | AT67: 1.8956 | AU67: 1.73295 | AV67: 1.6909667 | AW67: 1.7311833 | AX67: 1.6102833 | AY67: 1.5937083 | AZ67: 1.9557083 | BA67: 1.9183083 | BB67: 1.7931943 | BC67: 1.7898939 | BD67: 1.841388
A68: Finland | B68: FIN | C68: 3.2 | D68: 3.2 | E68: 3.2 | F68: 3.2 | G68: 3.2 | H68: 3.2 | I68: 3.2 | J68: 3.4499925 | K68: 4.19997 | L68: 4.19997 | M68: 4.19997 | N68: 4.1844178 | O68: 4.1463333 | P68: 3.8211667 | Q68: 3.77375 | R68: 3.6786667 | S68: 3.8644167 | T68: 4.0294167 | U68: 4.1173333 | V68: 3.8953333 | W68: 3.7300833 | X68: 4.31525 | Y68: 4.8204167 | Z68: 5.5700833 | AA68: 6.01 | AB68: 6.1978958 | AC68: 5.06952 | AD68: 4.395565 | AE68: 4.1828333 | AF68: 4.2912158 | AG68: 3.823505 | AH68: 4.0439792 | AI68: 4.47944 | AJ68: 5.7122917 | AK68: 5.2235125 | AL68: 4.3666667 | AM68: 4.59355 | AN68: 5.191435 | AO68: 5.3440658 | AP68: .. | AQ68: .. | AR68: .. | AS68: .. | AT68: .. | AU68: .. | AV68: .. | AW68: .. | AX68: .. | AY68: .. | AZ68: .. | BA68: .. | BB68: .. | BC68: .. | BD68: ..
A69: France | B69: FRA | C69: 4.93706 | D69: 4.93706 | E69: 4.93706 | F69: 4.93706 | G69: 4.93706 | H69: 4.93706 | I69: 4.93706 | J69: 4.93706 | K69: 4.93706 | L69: 5.1941975 | M69: 5.55419 | N69: 5.5406014 | O69: 5.0445445 | P69: 4.4527797 | Q69: 4.8096185 | R69: 4.2877995 | S69: 4.8028784 | T69: 4.9051733 | U69: 4.5131 | V69: 4.2544167 | W69: 4.225575 | X69: 5.4346083 | Y69: 6.5721 | Z69: 7.6212917 | AA69: 8.7391 | AB69: 8.985225 | AC69: 6.9260917 | AD69: 6.0107083 | AE69: 5.9569417 | AF69: 6.3801417 | AG69: 5.445275 | AH69: 5.6421167 | AI69: 5.2938158 | AJ69: 5.66323 | AK69: 5.552045 | AL69: 4.9914825 | AM69: 5.1155225 | AN69: 5.8366917 | AO69: 5.8995157 | AP69: .. | AQ69: .. | AR69: .. | AS69: .. | AT69: .. | AU69: .. | AV69: .. | AW69: .. | AX69: .. | AY69: .. | AZ69: .. | BA69: .. | BB69: .. | BC69: .. | BD69: ..
A70: French Polynesia | B70: PYF | C70: 89.765 | D70: 89.765 | E70: 89.765 | F70: 89.765 | G70: 89.765 | H70: 89.765 | I70: 89.765 | J70: 89.765 | K70: 89.765 | L70: 94.44 | M70: 100.985 | N70: 100.68945 | O70: 91.645969 | P70: 81.050222 | Q70: 87.528549 | R70: 77.931589 | S70: 86.890671 | T70: 89.337638 | U70: 82.056282 | V70: 77.352953 | W70: 76.82856 | X70: 98.810962 | Y70: 119.49261 | Z70: 138.5688 | AA70: 158.89257 | AB70: 163.36756 | AC70: 125.92881 | AD70: 109.2855 | AE70: 108.30792 | AF70: 116.00246 | AG70: 99.004901 | AH70: 102.58384 | AI70: 96.251101 | AJ70: 102.96772 | AK70: 100.94617 | AL70: 90.754137 | AM70: 93.009407 | AN70: 106.12156 | AO70: 107.26381 | AP70: 112.00799 | AQ70: 129.52273 | AR70: 133.35437 | AS70: 126.7961 | AT70: 105.73196 | AU70: 96.105575 | AV70: 95.957007 | AW70: 95.124171 | AX70: 87.188215 | AY70: 81.464734 | AZ70: 85.900132 | BA70: 90.100798 | BB70: 85.841885 | BC70: 92.875099 | BD70: ..
A71: Gabon | B71: GAB | C71: 245.1951 | D71: 245.2601 | E71: 245.01385 | F71: 245.01635 | G71: 245.02718 | H71: 245.06093 | I71: 245.67844 | J71: 246.00094 | K71: 247.56469 | L71: 259.96057 | M71: 276.40314 | N71: 275.35646 | O71: 252.02763 | P71: 222.88918 | Q71: 240.70467 | R71: 214.3129 | S71: 238.95049 | T71: 245.67969 | U71: 225.65586 | V71: 212.72164 | W71: 211.27956 | X71: 271.73145 | Y71: 328.60625 | Z71: 381.06604 | AA71: 436.95667 | AB71: 449.26296 | AC71: 346.3059 | AD71: 300.53656 | AE71: 297.84822 | AF71: 319.0083 | AG71: 272.26479 | AH71: 282.10691 | AI71: 264.6918 | AJ71: 283.16258 | AK71: 555.2047 | AL71: 499.14843 | AM71: 511.55243 | AN71: 583.66937 | AO71: 589.95177 | AP71: 615.69913 | AQ71: 711.97627 | AR71: 733.03851 | AS71: 696.9882 | AT71: 581.20031 | AU71: 528.28481 | AV71: 527.46814 | AW71: 522.89011 | AX71: 479.26678 | AY71: 447.80526 | AZ71: 472.18629 | BA71: 495.27702 | BB71: 471.86611 | BC71: 510.52714 | BD71: 494.04004
A72: Gambia, The | B72: GMB | C72: 1.7857107 | D72: 1.7857107 | E72: 1.7857107 | F72: 1.7857107 | G72: 1.7857107 | H72: 1.7857107 | I72: 1.7857107 | J72: 1.8353139 | K72: 2.08333 | L72: 2.08333 | M72: 2.08333 | N72: 2.0545983 | O72: 2.0013328 | P72: 1.7024046 | Q72: 1.7109268 | R72: 1.8080437 | S72: 2.2256731 | T72: 2.2930189 | U72: 2.0857453 | V72: 1.8884158 | W72: 1.7209828 | X72: 1.9901702 | Y72: 2.2895102 | Z72: 2.6385746 | AA72: 3.5840573 | AB72: 3.8938738 | AC72: 6.9249711 | AD72: 7.0744001 | AE72: 6.7084232 | AF72: 7.5835829 | AG72: 7.8789922 | AH72: 8.7331408 | AI72: 8.8957149 | AJ72: 9.1144195 | AK72: 9.581771 | AL72: 9.5442648 | AM72: 9.7971735 | AN72: 10.200167 | AO72: 10.6431 | AP72: 11.395092 | AQ72: 12.787625 | AR72: 15.687158 | AS72: 19.917825 | AT72: 28.530508 | AU72: 30.030083 | AV72: 28.575433 | AW72: 28.065725 | AX72: 24.873433 | AY72: 22.19235 | AZ72: 26.644361 | BA72: 28.011954 | BB72: 29.46152 | BC72: 32.077134 | BD72: ..
A73: Georgia | B73: GEO | C73: .. | D73: .. | E73: .. | F73: .. | G73: .. | H73: .. | I73: .. | J73: .. | K73: .. | L73: .. | M73: .. | N73: .. | O73: .. | P73: .. | Q73: .. | R73: .. | S73: .. | T73: .. | U73: .. | V73: .. | W73: .. | X73: .. | Y73: .. | Z73: .. | AA73: .. | AB73: .. | AC73: .. | AD73: .. | AE73: .. | AF73: .. | AG73: .. | AH73: .. | AI73: .. | AJ73: .. | AK73: .. | AL73: .. | AM73: 1.2628 | AN73: 1.2975 | AO73: 1.3898167 | AP73: 2.0245167 | AQ73: 1.9761667 | AR73: 2.0730167 | AS73: 2.195675 | AT73: 2.14565 | AU73: 1.91665 | AV73: 1.812675 | AW73: 1.7804333 | AX73: 1.6704917 | AY73: 1.4907917 | AZ73: 1.6704871 | BA73: 1.7823417 | BB73: 1.6864954 | BC73: 1.6512583 | BD73: 1.66335
A74: Germany | B74: DEU | C74: 4.2 | D74: 4.0333333 | E74: 4 | F74: 4 | G74: 4 | H74: 4 | I74: 4 | J74: 4 | K74: 4 | L74: 3.9433333 | M74: 3.66 | N74: 3.5073935 | O74: 3.1886417 | P74: 2.6726 | Q74: 2.58775 | R74: 2.4602917 | S74: 2.518 | T74: 2.3221833 | U74: 2.008625 | V74: 1.8328833 | W74: 1.8176667 | X74: 2.26 | Y74: 2.4265917 | Z74: 2.5532583 | AA74: 2.8459417 | AB74: 2.9439667 | AC74: 2.1714833 | AD74: 1.7973917 | AE74: 1.756225 | AF74: 1.8800417 | AG74: 1.6157333 | AH74: 1.6595417 | AI74: 1.56165 | AJ74: 1.6533208 | AK74: 1.6227942 | AL74: 1.4331325 | AM74: 1.5047742 | AN74: 1.7340558 | AO74: 1.7596676 | AP74: .. | AQ74: .. | AR74: .. | AS74: .. | AT74: .. | AU74: .. | AV74: .. | AW74: .. | AX74: .. | AY74: .. | AZ74: .. | BA74: .. | BB74: .. | BC74: .. | BD74: ..
A75: Ghana | B75: GHA | C75: 7.1391597e-05 | D75: 7.1391597e-05 | E75: 7.1391597e-05 | F75: 7.1391597e-05 | G75: 7.1391597e-05 | H75: 7.1391597e-05 | I75: 7.1391597e-05 | J75: 8.6081195e-05 | K75: 0.00010198514 | L75: 0.00010198514 | M75: 0.00010198514 | N75: 0.00010342936 | O75: 0.00013326748 | P75: 0.00011643737 | Q75: 0.00011493817 | R75: 0.00011493817 | S75: 0.00011493817 | T75: 0.00011493817 | U75: 0.00017626318 | V75: 0.00027485215 | W75: 0.00027485215 | X75: 0.00027485215 | Y75: 0.00027485215 | Z75: 0.00088252277 | AA75: 0.0035966844 | AB75: 0.0054335772 | AC75: 0.0089156207 | AD75: 0.015365068 | AE75: 0.020223705 | AF75: 0.026985484 | AG75: 0.032615622 | AH75: 0.036763307 | AI75: 0.043685167 | AJ75: 0.064871188 | AK75: 0.095568239 | AL75: 0.11991387 | AM75: 0.16354717 | AN75: 0.20479628 | AO75: 0.2311659 | AP75: 0.26664297 | AQ75: 0.54491918 | AR75: 0.71630516 | AS75: 0.79241708 | AT75: 0.86676433 | AU75: 0.89949485 | AV75: 0.90627897 | AW75: 0.91645177 | AX75: 0.93524785 | AY75: 1.0578583 | AZ75: 1.4088 | BA75: 1.431025 | BB75: 1.51185 | BC75: 1.7958167 | BD75: 1.95405
A76: Greece | B76: GRC | C76: 30.0003 | D76: 30.00005 | E76: 30 | F76: 30 | G76: 30 | H76: 30 | I76: 30 | J76: 30 | K76: 30 | L76: 30 | M76: 30 | N76: 30 | O76: 30.0003 | P76: 29.62515 | Q76: 30.0003 | R76: 32.051325 | S76: 36.517583 | T76: 36.838417 | U76: 36.745417 | V76: 37.038417 | W76: 42.616583 | X76: 55.408417 | Y76: 66.803167 | Z76: 88.06425 | AA76: 112.71658 | AB76: 138.11908 | AC76: 139.98117 | AD76: 135.4295 | AE76: 141.8605 | AF76: 162.41658 | AG76: 158.51392 | AH76: 182.26642 | AI76: 190.62425 | AJ76: 229.24984 | AK76: 242.60282 | AL76: 231.66274 | AM76: 240.71154 | AN76: 273.05785 | AO76: 295.52911 | AP76: 305.6466 | AQ76: 365.39856 | AR76: .. | AS76: .. | AT76: .. | AU76: .. | AV76: .. | AW76: .. | AX76: .. | AY76: .. | AZ76: .. | BA76: .. | BB76: .. | BC76: .. | BD76: ..
A77: Greenland | B77: GRL | C77: 6.90714 | D77: 6.90714 | E77: 6.90714 | F77: 6.90714 | G77: 6.90714 | H77: 6.90714 | I77: 6.90714 | J77: 7.00595 | K77: 7.5 | L77: 7.5 | M77: 7.5 | N77: 7.4175957 | O77: 6.9492917 | P77: 6.0495 | Q77: 6.0949 | R77: 5.74615 | S77: 6.045025 | T77: 6.0031917 | U77: 5.514625 | V77: 5.2609583 | W77: 5.6359417 | X77: 7.1233667 | Y77: 8.3324417 | Z77: 9.1449917 | AA77: 10.356592 | AB77: 10.596392 | AC77: 8.0909917 | AD77: 6.8403167 | AE77: 6.731525 | AF77: 7.310175 | AG77: 6.1885583 | AH77: 6.3964583 | AI77: 6.0361333 | AJ77: 6.4839392 | AK77: 6.3605517 | AL77: 5.6023667 | AM77: 5.7986717 | AN77: 6.6044592 | AO77: 6.7008267 | AP77: 6.97624 | AQ77: 8.0831442 | AR77: 8.3228175 | AS77: 7.8947142 | AT77: 6.5876733 | AU77: 5.9910567 | AV77: 5.99691 | AW77: 5.9467783 | AX77: 5.4437008 | AY77: 5.0981308 | AZ77: 5.3608667 | BA77: 5.624075 | BB77: 5.3687115 | BC77: 5.7924755 | BD77: 5.6163117
A78: Grenada | B78: GRD | C78: 1.71429 | D78: 1.71429 | E78: 1.71429 | F78: 1.71429 | G78: 1.71429 | H78: 1.71429 | I78: 1.71429 | J78: 1.7619083 | K78: 2 | L78: 2 | M78: 2 | N78: 1.9748727 | O78: 1.9212781 | P78: 1.9592192 | Q78: 2.0532324 | R78: 2.1697958 | S78: 2.6146708 | T78: 2.7 | U78: 2.7 | V78: 2.7 | W78: 2.7 | X78: 2.7 | Y78: 2.7 | Z78: 2.7 | AA78: 2.7 | AB78: 2.7 | AC78: 2.7 | AD78: 2.7 | AE78: 2.7 | AF78: 2.7 | AG78: 2.7 | AH78: 2.7 | AI78: 2.7 | AJ78: 2.7 | AK78: 2.7 | AL78: 2.7 | AM78: 2.7 | AN78: 2.7 | AO78: 2.7 | AP78: 2.7 | AQ78: 2.7 | AR78: 2.7 | AS78: 2.7 | AT78: 2.7 | AU78: 2.7 | AV78: 2.7 | AW78: 2.7 | AX78: 2.7 | AY78: 2.7 | AZ78: 2.7 | BA78: 2.7 | BB78: 2.7 | BC78: 2.7 | BD78: 2.7
A79: Guam | B79: GUM | C79: .. | D79: .. | E79: .. | F79: .. | G79: .. | H79: .. | I79: .. | J79: .. | K79: .. | L79: .. | M79: .. | N79: .. | O79: .. | P79: .. | Q79: .. | R79: .. | S79: .. | T79: .. | U79: .. | V79: .. | W79: .. | X79: .. | Y79: .. | Z79: .. | AA79: .. | AB79: .. | AC79: .. | AD79: .. | AE79: .. | AF79: .. | AG79: .. | AH79: .. | AI79: .. | AJ79: .. | AK79: .. | AL79: .. | AM79: .. | AN79: .. | AO79: .. | AP79: .. | AQ79: .. | AR79: .. | AS79: .. | AT79: .. | AU79: .. | AV79: .. | AW79: .. | AX79: .. | AY79: .. | AZ79: .. | BA79: .. | BB79: .. | BC79: .. | BD79: ..
A80: Guatemala | B80: GTM | C80: 1 | D80: 1 | E80: 1 | F80: 1 | G80: 1 | H80: 1 | I80: 1 | J80: 1 | K80: 1 | L80: 1 | M80: 1 | N80: 1 | O80: 1 | P80: 1 | Q80: 1 | R80: 1 | S80: 1 | T80: 1 | U80: 1 | V80: 1 | W80: 1 | X80: 1 | Y80: 1 | Z80: 1 | AA80: 1 | AB80: 1 | AC80: 1.875 | AD80: 2.5 | AE80: 2.6195833 | AF80: 2.8161167 | AG80: 4.4857583 | AH80: 5.02888 | AI80: 5.17063 | AJ80: 5.6353625 | AK80: 5.7512008 | AL80: 5.8103425 | AM80: 6.0495125 | AN80: 6.0652692 | AO80: 6.3946533 | AP80: 7.38561 | AQ80: 7.7631592 | AR80: 7.8585925 | AS80: 7.821645 | AT80: 7.9408467 | AU80: 7.9464958 | AV80: 7.6339442 | AW80: 7.6026308 | AX80: 7.6733042 | AY80: 7.5600283 | AZ80: 8.1615554 | BA80: 8.0577708 | BB80: 7.7854183 | BC80: 7.8336054 | BD80: 7.8568137
A81: Guinea | B81: GIN | C81: 24.685 | D81: 24.685 | E81: 24.685 | F81: 24.685 | G81: 24.685 | H81: 24.685 | I81: 24.685 | J81: 24.685 | K81: 24.685 | L81: 24.685 | M81: 24.685 | N81: 24.612752 | O81: 22.736274 | P81: 20.716092 | Q81: 20.556276 | R81: 20.673265 | S81: 21.381957 | T81: 21.144483 | U81: 19.723541 | V81: 19.107013 | W81: 18.968893 | X81: 20.948117 | Y81: 22.366029 | Z81: 23.095184 | AA81: 24.089944 | AB81: 24.333099 | AC81: 333.4525 | AD81: 428.4025 | AE81: 474.39583 | AF81: 591.64583 | AG81: 660.16667 | AH81: 753.85808 | AI81: 902.00133 | AJ81: 955.49033 | AK81: 976.63642 | AL81: 991.4115 | AM81: 1004.0166 | AN81: 1095.3255 | AO81: 1236.8318 | AP81: 1387.4013 | AQ81: 1746.8699 | AR81: 1950.5583 | AS81: 1975.8438 | AT81: 1984.9313 | AU81: 2243.9313 | AV81: 3644.3333 | AW81: 5148.75 | AX81: 4197.752 | AY81: 4601.691 | AZ81: 4801.0832 | BA81: 5726.071 | BB81: 6658.0313 | BC81: .. | BD81: ..
A82: Guinea-Bissau | B82: GNB | C82: 0.44230769 | D82: 0.44230769 | E82: 0.44230769 | F82: 0.44230769 | G82: 0.44230769 | H82: 0.44230769 | I82: 0.44230769 | J82: 0.44230769 | K82: 0.44230769 | L82: 0.44230769 | M82: 0.44230769 | N82: 0.43631031 | O82: 0.41620641 | P82: 0.37715641 | Q82: 0.39089487 | R82: 0.39297308 | S82: 0.46506282 | T82: 0.51759905 | U82: 0.53905898 | V82: 0.52395467 | W82: 0.52016712 | X82: 0.57444163 | Y82: 0.6133241 | Z82: 0.64767013 | AA82: 1.6086282 | AB82: 2.4502564 | AC82: 3.1327436 | AD82: 8.6001282 | AE82: 17.07241 | AF82: 27.848385 | AG82: 33.62241 | AH82: 56.286256 | AI82: 106.67558 | AJ82: 155.10621 | AK82: 198.34064 | AL82: 278.0391 | AM82: 405.745 | AN82: 583.66937 | AO82: 589.95177 | AP82: 615.69913 | AQ82: 711.97627 | AR82: 733.03851 | AS82: 696.9882 | AT82: 581.20031 | AU82: 528.28481 | AV82: 527.46814 | AW82: 522.89011 | AX82: 479.26678 | AY82: 447.80526 | AZ82: 472.18629 | BA82: 495.27702 | BB82: 471.86611 | BC82: 510.52714 | BD82: 494.04004
A83: Guyana | B83: GUY | C83: 1.71429 | D83: 1.71429 | E83: 1.71429 | F83: 1.71429 | G83: 1.71429 | H83: 1.71429 | I83: 1.71429 | J83: 1.7380992 | K83: 2 | L83: 2 | M83: 2 | N83: 1.9886602 | O83: 2.087273 | P83: 2.1061762 | Q83: 2.2268553 | R83: 2.3553842 | S83: 2.55 | T83: 2.55 | U83: 2.55 | V83: 2.55 | W83: 2.55 | X83: 2.8125 | Y83: 3 | Z83: 3 | AA83: 3.8315717 | AB83: 4.251855 | AC83: 4.2724167 | AD83: 9.7558333 | AE83: 10 | AF83: 27.15875 | AG83: 39.533333 | AH83: 111.81067 | AI83: 125.0025 | AJ83: 126.73044 | AK83: 138.29024 | AL83: 141.98917 | AM83: 140.375 | AN83: 142.40083 | AO83: 150.51917 | AP83: 177.995 | AQ83: 182.43 | AR83: 187.32083 | AS83: 190.665 | AT83: 193.87833 | AU83: 198.3075 | AV83: 199.875 | AW83: 200.18833 | AX83: 202.34667 | AY83: 203.63333 | AZ83: 203.95 | BA83: 203.63583 | BB83: 204.0175 | BC83: 204.35833 | BD83: 205.39417
A84: Haiti | B84: HTI | C84: 5 | D84: 5 | E84: 5 | F84: 5 | G84: 5 | H84: 5 | I84: 5 | J84: 5 | K84: 5 | L84: 5 | M84: 5 | N84: 5 | O84: 5.0000184 | P84: 5 | Q84: 5.0000041 | R84: 5 | S84: 5 | T84: 5 | U84: 5 | V84: 5 | W84: 5 | X84: 5 | Y84: 5 | Z84: 5 | AA84: 5 | AB84: 5 | AC84: 5 | AD84: 5 | AE84: 5 | AF84: 5 | AG84: 5 | AH84: 6.0341667 | AI84: 9.8016667 | AJ84: 12.8225 | AK84: 15.04 | AL84: 15.109733 | AM84: 15.70115 | AN84: 16.6545 | AO84: 16.765667 | AP84: 16.937892 | AQ84: 21.170667 | AR84: 24.429083 | AS84: 29.250483 | AT84: 42.366758 | AU84: 38.352033 | AV84: 40.44855 | AW84: 40.408517 | AX84: 36.861417 | AY84: 39.107592 | AZ84: 41.197608 | BA84: 39.7974 | BB84: 40.522822 | BC84: 41.949723 | BD84: 43.462783
A85: Honduras | B85: HND | C85: 2 | D85: 2 | E85: 2 | F85: 2 | G85: 2 | H85: 2 | I85: 2 | J85: 2 | K85: 2 | L85: 2 | M85: 2 | N85: 2 | O85: 2.0000092 | P85: 2 | Q85: 2 | R85: 2 | S85: 2 | T85: 2 | U85: 2 | V85: 2 | W85: 2 | X85: 2 | Y85: 2 | Z85: 2 | AA85: 2 | AB85: 2 | AC85: 2 | AD85: 2 | AE85: 2 | AF85: 2 | AG85: 4.1119833 | AH85: 5.3166667 | AI85: 5.4979167 | AJ85: 6.4715833 | AK85: 8.4087575 | AL85: 9.4709867 | AM85: 11.705303 | AN85: 13.003474 | AO85: 13.385015 | AP85: 14.213168 | AQ85: 14.839203 | AR85: 15.473667 | AS85: 16.433383 | AT85: 17.345292 | AU85: 18.206221 | AV85: 18.832342 | AW85: 18.895208 | AX85: 18.8951 | AY85: 18.903758 | AZ85: 18.8951 | BA85: 18.8951 | BB85: 18.917142 | BC85: 19.50225 | BD85: ..
A86: Hong Kong SAR, China | B86: HKG | C86: 5.7143 | D86: 5.7143 | E86: 5.7143 | F86: 5.7143 | G86: 5.7143 | H86: 5.7143 | I86: 5.7143 | J86: 5.7431583 | K86: 6.0606 | L86: 6.0606 | M86: 6.0606 | N86: 5.9804105 | O86: 5.6414167 | P86: 5.1465 | Q86: 5.0315833 | R86: 4.9351667 | S86: 4.90475 | T86: 4.662 | U86: 4.6836667 | V86: 5.0026667 | W86: 4.9760833 | X86: 5.5893333 | Y86: 6.0699167 | Z86: 7.2651667 | AA86: 7.818 | AB86: 7.79075 | AC86: 7.8033333 | AD86: 7.79825 | AE86: 7.806 | AF86: 7.7999167 | AG86: 7.78975 | AH86: 7.7711667 | AI86: 7.7405833 | AJ86: 7.7355833 | AK86: 7.7284167 | AL86: 7.7358333 | AM86: 7.7342542 | AN86: 7.7420833 | AO86: 7.7453333 | AP86: 7.7575 | AQ86: 7.7911667 | AR86: 7.79875 | AS86: 7.7989167 | AT86: 7.78675 | AU86: 7.788 | AV86: 7.7773333 | AW86: 7.7678333 | AX86: 7.8014167 | AY86: 7.7868333 | AZ86: 7.75175 | BA86: 7.7691667 | BB86: 7.784 | BC86: 7.7564167 | BD86: 7.756
A87: Hungary | B87: HUN | C87: .. | D87: .. | E87: .. | F87: .. | G87: .. | H87: .. | I87: .. | J87: .. | K87: 60 | L87: 60 | M87: 60 | N87: 59.821617 | O87: 55.26 | P87: 48.966225 | Q87: 46.7524 | R87: 43.971383 | S87: 41.575267 | T87: 40.96075 | U87: 37.91135 | V87: 35.578 | W87: 32.532283 | X87: 34.314292 | Y87: 36.63055 | Z87: 42.67115 | AA87: 48.042208 | AB87: 50.1194 | AC87: 45.83215 | AD87: 46.970542 | AE87: 50.413208 | AF87: 59.066342 | AG87: 63.205867 | AH87: 74.735383 | AI87: 78.988392 | AJ87: 91.933183 | AK87: 105.16046 | AL87: 125.68143 | AM87: 152.64667 | AN87: 186.78917 | AO87: 214.40167 | AP87: 237.14583 | AQ87: 282.17917 | AR87: 286.49 | AS87: 257.88667 | AT87: 224.30667 | AU87: 202.74583 | AV87: 199.5825 | AW87: 210.39 | AX87: 183.62583 | AY87: 172.11333 | AZ87: 202.34167 | BA87: 207.94417 | BB87: 201.055 | BC87: 225.10417 | BD87: 223.695
A88: Iceland | B88: ISL | C88: 0.36190475 | D88: 0.40083333 | E88: 0.43 | F88: 0.43 | G88: 0.43 | H88: 0.43 | I88: 0.43 | J88: 0.44166667 | K88: 0.62166667 | L88: 0.88 | M88: 0.88 | N88: 0.88 | O88: 0.88260355 | P88: 0.90444936 | Q88: 0.99951667 | R88: 1.53695 | S88: 1.8217167 | T88: 1.9887 | U88: 2.7111083 | V88: 3.526 | W88: 4.7976417 | X88: 7.2241833 | Y88: 12.351533 | Z88: 24.842767 | AA88: 31.693742 | AB88: 41.507667 | AC88: 41.104158 | AD88: 38.677183 | AE88: 43.013983 | AF88: 57.041792 | AG88: 58.283775 | AH88: 58.996342 | AI88: 57.545933 | AJ88: 67.603182 | AK88: 69.944378 | AL88: 64.691667 | AM88: 66.5 | AN88: 70.904291 | AO88: 70.958333 | AP88: 72.335293 | AQ88: 78.615947 | AR88: 97.424603 | AS88: 91.661667 | AT88: 76.708983 | AU88: 70.191667 | AV88: 62.981667 | AW88: 70.18 | AX88: 64.055 | AY88: 87.947917 | AZ88: 123.63838 | BA88: 122.24181 | BB88: 115.95404 | BC88: 125.08279 | BD88: 122.17912
A89: India | B89: IND | C89: 4.7619 | D89: 4.7619 | E89: 4.7619 | F89: 4.7619 | G89: 4.7619 | H89: 4.7619 | I89: 6.359125 | J89: 7.5 | K89: 7.5 | L89: 7.5 | M89: 7.5 | N89: 7.4919352 | O89: 7.5944684 | P89: 7.7420386 | Q89: 8.1016032 | R89: 8.3758919 | S89: 8.9604127 | T89: 8.7385762 | U89: 8.1928403 | V89: 8.1257909 | W89: 7.8629447 | X89: 8.6585228 | Y89: 9.4551319 | Z89: 10.098898 | AA89: 11.362583 | AB89: 12.36875 | AC89: 12.610833 | AD89: 12.9615 | AE89: 13.917083 | AF89: 16.2255 | AG89: 17.5035 | AH89: 22.742433 | AI89: 25.918083 | AJ89: 30.493292 | AK89: 31.373742 | AL89: 32.427077 | AM89: 35.433173 | AN89: 36.313286 | AO89: 41.259365 | AP89: 43.055428 | AQ89: 44.941605 | AR89: 47.186414 | AS89: 48.610319 | AT89: 46.583284 | AU89: 45.316467 | AV89: 44.099975 | AW89: 45.307008 | AX89: 41.348533 | AY89: 43.505183 | AZ89: 48.405267 | BA89: 45.725812 | BB89: 46.670467 | BC89: 53.437233 | BD89: 58.597845
A90: Indonesia | B90: IDN | C90: .. | D90: .. | E90: .. | F90: .. | G90: .. | H90: .. | I90: .. | J90: 149.58333 | K90: 296.29167 | L90: 326 | M90: 362.83333 | N90: 391.875 | O90: 415 | P90: 415 | Q90: 415 | R90: 415 | S90: 415 | T90: 415 | U90: 442.04542 | V90: 623.0555 | W90: 626.994 | X90: 631.75667 | Y90: 661.42075 | Z90: 909.26483 | AA90: 1025.9448 | AB90: 1110.58 | AC90: 1282.56 | AD90: 1643.8483 | AE90: 1685.7042 | AF90: 1770.0592 | AG90: 1842.8133 | AH90: 1950.3175 | AI90: 2029.9208 | AJ90: 2087.1039 | AK90: 2160.7537 | AL90: 2248.608 | AM90: 2342.2963 | AN90: 2909.38 | AO90: 10013.622 | AP90: 7855.15 | AQ90: 8421.775 | AR90: 10260.85 | AS90: 9311.1917 | AT90: 8577.1333 | AU90: 8938.85 | AV90: 9704.7417 | AW90: 9159.3167 | AX90: 9141 | AY90: 9698.9625 | AZ90: 10389.938 | BA90: 9090.4333 | BB90: 8770.4333 | BC90: 9386.6292 | BD90: 10461.24
A91: Iran, Islamic Rep. | B91: IRN | C91: 75.75 | D91: 75.75 | E91: 75.75 | F91: 75.75 | G91: 75.75 | H91: 75.75 | I91: 75.75 | J91: 75.75 | K91: 75.75 | L91: 75.75 | M91: 75.75 | N91: 75.75 | O91: 75.74997 | P91: 68.885228 | Q91: 67.638085 | R91: 67.651687 | S91: 70.235687 | T91: 70.63033 | U91: 70.488636 | V91: 70.488636 | W91: 70.628446 | X91: 78.343072 | Y91: 83.618643 | Z91: 86.374576 | AA91: 90.047103 | AB91: 91.069201 | AC91: 78.774989 | AD91: 71.473993 | AE91: 68.696456 | AF91: 72.028767 | AG91: 68.109092 | AH91: 67.518478 | AI91: 65.564683 | AJ91: 1268.0177 | AK91: 1749.0895 | AL91: 1748.266 | AM91: 1751.102 | AN91: 1753.261 | AO91: 1752.2016 | AP91: 1753.2705 | AQ91: 1764.7711 | AR91: 1753.9012 | AS91: 6907.0204 | AT91: 8193.8875 | AU91: 8613.9894 | AV91: 8963.9589 | AW91: 9170.9429 | AX91: 9281.1518 | AY91: 9428.5283 | AZ91: 9864.3025 | BA91: 10254.176 | BB91: 10616.307 | BC91: 12175.547 | BD91: 18414.448
A92: Iraq | B92: IRQ | C92: 0.357143 | D92: 0.357143 | E92: 0.357143 | F92: 0.357143 | G92: 0.357143 | H92: 0.357143 | I92: 0.357143 | J92: 0.357143 | K92: 0.357143 | L92: 0.357143 | M92: 0.357143 | N92: 0.35372453 | O92: 0.3289488 | P92: 0.29972077 | Q92: 0.29568311 | R92: 0.29531367 | S92: 0.29531367 | T92: 0.29531367 | U92: 0.29531367 | V92: 0.29531367 | W92: 0.29531367 | X92: 0.29531367 | Y92: 0.29850455 | Z92: 0.31085731 | AA92: 0.31085731 | AB92: 0.31085731 | AC92: 0.31085731 | AD92: 0.31085731 | AE92: 0.31085731 | AF92: 0.31085731 | AG92: 0.31085731 | AH92: 0.31085731 | AI92: 0.31085731 | AJ92: 0.31085731 | AK92: 0.31085731 | AL92: 0.31085731 | AM92: 0.31085731 | AN92: 0.31085731 | AO92: 0.31085731 | AP92: 0.31085731 | AQ92: 0.31085731 | AR92: 0.31085731 | AS92: 0.31085739 | AT92: 2133.7778 | AU92: 1453.4167 | AV92: 1472 | AW92: 1467.4167 | AX92: 1254.5672 | AY92: 1193.0833 | AZ92: 1170 | BA92: 1170 | BB92: 1170 | BC92: 1166.1667 | BD92: 1166
A93: Ireland | B93: IRL | C93: 0.357143 | D93: 0.357143 | E93: 0.357143 | F93: 0.357143 | G93: 0.357143 | H93: 0.357143 | I93: 0.357143 | J93: 0.36210333 | K93: 0.416667 | L93: 0.416667 | M93: 0.416667 | N93: 0.41092022 | O93: 0.40039046 | P93: 0.40817095 | Q93: 0.42775644 | R93: 0.45204117 | S93: 0.55650983 | T93: 0.573272 | U93: 0.52150458 | V93: 0.48859487 | W93: 0.48664528 | X93: 0.62129807 | Y93: 0.70456164 | Z93: 0.80467792 | AA93: 0.9225535 | AB93: 0.945615 | AC93: 0.74312833 | AD93: 0.67291667 | AE93: 0.6564675 | AF93: 0.70554333 | AG93: 0.60458833 | AH93: 0.6212975 | AI93: 0.58772083 | AJ93: 0.67724931 | AK93: 0.6686281 | AL93: 0.62373307 | AM93: 0.62502837 | AN93: 0.65964313 | AO93: 0.702271 | AP93: .. | AQ93: .. | AR93: .. | AS93: .. | AT93: .. | AU93: .. | AV93: .. | AW93: .. | AX93: .. | AY93: .. | AZ93: .. | BA93: .. | BB93: .. | BC93: .. | BD93: ..
A94: Isle of Man | B94: IMN | C94: 0.357143 | D94: 0.357143 | E94: 0.357143 | F94: 0.357143 | G94: 0.357143 | H94: 0.357143 | I94: 0.357143 | J94: 0.367064 | K94: 0.416667 | L94: 0.416667 | M94: 0.416667 | N94: 0.40916028 | O94: 0.39968026 | P94: 0.40783034 | Q94: 0.429465 | R94: 0.45204117 | S94: 0.55650983 | T94: 0.573272 | U94: 0.52150458 | V94: 0.47218117 | W94: 0.430295 | X94: 0.49764133 | Y94: 0.57244683 | Z94: 0.65972458 | AA94: 0.75180667 | AB94: 0.779246 | AC94: 0.68219733 | AD94: 0.6119265 | AE94: 0.56217017 | AF94: 0.61117275 | AG94: 0.56317717 | AH94: 0.56701533 | AI94: 0.56977417 | AJ94: 0.66675655 | AK94: 0.6534266 | AL94: 0.63366812 | AM94: 0.64095826 | AN94: 0.61083611 | AO94: 0.60382359 | AP94: 0.61805685 | AQ94: 0.66093083 | AR94: 0.694655 | AS94: 0.66722333 | AT94: 0.6124725 | AU94: 0.54618 | AV94: 0.54999833 | AW94: 0.54348667 | AX94: 0.49977167 | AY94: 0.54396625 | AZ94: 0.64191926 | BA94: 0.64717935 | BB94: 0.62414084 | BC94: 0.63304699 | BD94: 0.63966058
A95: Israel | B95: ISR | C95: 0.00017999961 | D95: 0.00017999961 | E95: 0.00028999936 | F95: 0.00029999934 | G95: 0.00029999934 | H95: 0.00029999934 | I95: 0.00029999934 | J95: 0.00030833266 | K95: 0.00034999923 | L95: 0.00034999923 | M95: 0.00034999923 | N95: 0.00041999948 | O95: 0.00041797967 | P95: 0.00041946923 | Q95: 0.0004451534 | R95: 0.00063361493 | S95: 0.00079255715 | T95: 0.0010445458 | U95: 0.0017435372 | V95: 0.0025406369 | W95: 0.0051242917 | X95: 0.011430575 | Y95: 0.024267 | Z95: 0.056214492 | AA95: 0.29320967 | AB95: 1.1788493 | AC95: 1.4878417 | AD95: 1.5946417 | AE95: 1.5989333 | AF95: 1.9164167 | AG95: 2.016175 | AH95: 2.2791083 | AI95: 2.4590833 | AJ95: 2.8300833 | AK95: 3.0110552 | AL95: 3.0112917 | AM95: 3.19165 | AN95: 3.44935 | AO95: 3.800075 | AP95: 4.1397167 | AQ95: 4.0773333 | AR95: 4.20565 | AS95: 4.737825 | AT95: 4.5541333 | AU95: 4.4819833 | AV95: 4.4877 | AW95: 4.4558083 | AX95: 4.1080829 | AY95: 3.5880212 | AZ95: 3.9323355 | BA95: 3.738975 | BB95: 3.5781293 | BC95: 3.8559218 | BD95: 3.6107583
A96: Italy | B96: ITA | C96: 623.9875 | D96: 625 | E96: 625 | F96: 625 | G96: 625 | H96: 625 | I96: 625 | J96: 625 | K96: 625 | L96: 625 | M96: 625 | N96: 620.35929 | O96: 583.2175 | P96: 582.99583 | Q96: 650.34333 | R96: 652.84917 | S96: 832.335 | T96: 882.38833 | U96: 848.66333 | V96: 830.86167 | W96: 856.4475 | X96: 1136.765 | Y96: 1352.51 | Z96: 1518.8483 | AA96: 1756.9608 | AB96: 1909.4392 | AC96: 1490.81 | AD96: 1296.07 | AE96: 1301.6275 | AF96: 1372.0933 | AG96: 1198.1017 | AH96: 1240.6133 | AI96: 1232.4058 | AJ96: 1573.6659 | AK96: 1612.445 | AL96: 1628.9332 | AM96: 1542.947 | AN96: 1703.0969 | AO96: 1736.2074 | AP96: .. | AQ96: .. | AR96: .. | AS96: .. | AT96: .. | AU96: .. | AV96: .. | AW96: .. | AX96: .. | AY96: .. | AZ96: .. | BA96: .. | BB96: .. | BC96: .. | BD96: ..
A97: Jamaica | B97: JAM | C97: 0.714286 | D97: 0.714286 | E97: 0.714286 | F97: 0.714286 | G97: 0.714286 | H97: 0.714286 | I97: 0.714286 | J97: 0.724207 | K97: 0.833334 | L97: 0.83333375 | M97: 0.833333 | N97: 0.83280175 | O97: 0.76746 | P97: 0.90242675 | Q97: 0.90909 | R97: 0.90909 | S97: 0.90909 | T97: 0.90909 | U97: 1.4132583 | V97: 1.7647783 | W97: 1.78142 | X97: 1.78142 | Y97: 1.78142 | Z97: 1.9322175 | AA97: 3.9428042 | AB97: 5.5585583 | AC97: 5.4778333 | AD97: 5.4866667 | AE97: 5.4885542 | AF97: 5.7446417 | AG97: 7.184025 | AH97: 12.115875 | AI97: 22.96035 | AJ97: 24.94855 | AK97: 33.085933 | AL97: 35.142117 | AM97: 37.119558 | AN97: 35.404467 | AO97: 36.55 | AP97: 39.043517 | AQ97: 42.9857 | AR97: 45.99625 | AS97: 48.415942 | AT97: 57.740874 | AU97: 61.1972 | AV97: 62.280715 | AW97: 65.743858 | AX97: 69.192162 | AY97: 72.756203 | AZ97: 87.89412 | BA97: 87.196137 | BB97: 85.892458 | BC97: 88.750937 | BD97: 100.24106
A98: Japan | B98: JPN | C98: 360 | D98: 360 | E98: 360 | F98: 360 | G98: 360 | H98: 360 | I98: 360 | J98: 360 | K98: 360 | L98: 360 | M98: 360 | N98: 350.67769 | O98: 303.1725 | P98: 271.70167 | Q98: 292.0825 | R98: 296.7875 | S98: 296.5525 | T98: 268.51 | U98: 210.44167 | V98: 219.14 | W98: 226.74083 | X98: 220.53583 | Y98: 249.07667 | Z98: 237.51167 | AA98: 237.5225 | AB98: 238.53583 | AC98: 168.51983 | AD98: 144.6375 | AE98: 128.15167 | AF98: 137.96442 | AG98: 144.7925 | AH98: 134.70667 | AI98: 126.65133 | AJ98: 111.19779 | AK98: 102.20781 | AL98: 94.059579 | AM98: 108.77906 | AN98: 120.99086 | AO98: 130.9053 | AP98: 113.90681 | AQ98: 107.7655 | AR98: 121.52895 | AS98: 125.38802 | AT98: 115.93346 | AU98: 108.19257 | AV98: 110.21821 | AW98: 116.29931 | AX98: 117.75353 | AY98: 103.35949 | AZ98: 93.570089 | BA98: 87.779875 | BB98: 79.80702 | BC98: 79.790455 | BD98: 97.595658
A99: Jordan | B99: JOR | C99: 0.357143 | D99: 0.357143 | E99: 0.357143 | F99: 0.357143 | G99: 0.357143 | H99: 0.357143 | I99: 0.357143 | J99: 0.357143 | K99: 0.357143 | L99: 0.357143 | M99: 0.357143 | N99: 0.357143 | O99: 0.35714325 | P99: 0.32857087 | Q99: 0.32209167 | R99: 0.31979167 | S99: 0.33198333 | T99: 0.32926667 | U99: 0.305625 | V99: 0.30033333 | W99: 0.297925 | X99: 0.33043333 | Y99: 0.35249167 | Z99: 0.36307917 | AA99: 0.384465 | AB99: 0.394625 | AC99: 0.34996583 | AD99: 0.33845875 | AE99: 0.3742925 | AF99: 0.57457583 | AG99: 0.66371167 | AH99: 0.68086583 | AI99: 0.67981833 | AJ99: 0.69285083 | AK99: 0.69876417 | AL99: 0.7003775 | AM99: 0.709 | AN99: 0.709 | AO99: 0.709 | AP99: 0.709 | AQ99: 0.709 | AR99: 0.70898317 | AS99: 0.70899983 | AT99: 0.709 | AU99: 0.709 | AV99: 0.709 | AW99: 0.709 | AX99: 0.70899977 | AY99: 0.70966655 | AZ99: 0.71 | BA99: 0.71 | BB99: 0.71 | BC99: 0.71 | BD99: 0.71
A100: Kazakhstan | B100: KAZ | C100: .. | D100: .. | E100: .. | F100: .. | G100: .. | H100: .. | I100: .. | J100: .. | K100: .. | L100: .. | M100: .. | N100: .. | O100: .. | P100: .. | Q100: .. | R100: .. | S100: .. | T100: .. | U100: .. | V100: .. | W100: .. | X100: .. | Y100: .. | Z100: .. | AA100: .. | AB100: .. | AC100: .. | AD100: .. | AE100: .. | AF100: .. | AG100: .. | AH100: .. | AI100: .. | AJ100: .. | AK100: 35.538333 | AL100: 60.95 | AM100: 67.303333 | AN100: 75.4375 | AO100: 78.303333 | AP100: 119.52333 | AQ100: 142.13333 | AR100: 146.73583 | AS100: 153.27917 | AT100: 149.57583 | AU100: 136.035 | AV100: 132.88 | AW100: 126.08943 | AX100: 122.55417 | AY100: 120.29917 | AZ100: 147.49667 | BA100: 147.355 | BB100: 146.62083 | BC100: 149.1125 | BD100: 152.12917
...

Sheet PPP Exchange Rates
A1: Year | C1: =C2&"y" -> 1960y | D1: =D2&"y" -> 1961y | E1: =E2&"y" -> 1962y | F1: =F2&"y" -> 1963y | G1: =G2&"y" -> 1964y | H1: =H2&"y" -> 1965y | I1: =I2&"y" -> 1966y | J1: =J2&"y" -> 1967y | ... XFD1: =XFD2&"y" -> y
A2: Country Name | B2: Country Code | C2: 1960 | D2: 1961 | E2: 1962 | F2: 1963 | G2: 1964 | H2: 1965 | I2: 1966 | J2: 1967 | K2: 1968 | L2: 1969 | M2: 1970 | N2: 1971 | O2: 1972 | P2: 1973 | Q2: 1974 | R2: 1975 | S2: 1976 | T2: 1977 | U2: 1978 | V2: 1979 | W2: 1980 | X2: 1981 | Y2: 1982 | Z2: 1983 | AA2: 1984 | AB2: 1985 | AC2: 1986 | AD2: 1987 | AE2: 1988 | AF2: 1989 | AG2: 1990 | AH2: 1991 | AI2: 1992 | AJ2: 1993 | AK2: 1994 | AL2: 1995 | AM2: 1996 | AN2: 1997 | AO2: 1998 | AP2: 1999 | AQ2: 2000 | AR2: 2001 | AS2: 2002 | AT2: 2003 | AU2: 2004 | AV2: 2005 | AW2: 2006 | AX2: 2007 | AY2: 2008 | AZ2: 2009 | BA2: 2010 | BB2: 2011 | BC2: 2012 | BD2: 2013
A3: Arab World | B3: ARB
A4: Caribbean small states | B4: CSS
A5: East Asia & Pacific (all income levels) | B5: EAS
A6: East Asia & Pacific (developing only) | B6: EAP
A7: Euro area | B7: EMU
A8: Europe & Central Asia (all income levels) | B8: ECS
A9: Europe & Central Asia (developing only) | B9: ECA
A10: European Union | B10: EUU
A11: Heavily indebted poor countries (HIPC) | B11: HPC
A12: High income | B12: HIC
A13: High income: nonOECD | B13: NOC
A14: High income: OECD | B14: OEC
... A34: World | B34: WLD
A35: Afghanistan | B35: AFG | W35: .. | X35: .. | Y35: .. | Z35: .. | AA35: .. | AB35: .. | AC35: .. | AD35: .. | AE35: .. | AF35: .. | AG35: .. | AH35: .. | AI35: .. | AJ35: .. | AK35: .. | AL35: .. | AM35: .. | AN35: .. | AO35: .. | AP35: .. | AQ35: .. | AR35: .. | AS35: 9.6257434 | AT35: 10.542778 | AU35: 11.415158 | AV35: 12.266022 | AW35: 12.753588 | AX35: 15.204587 | AY35: 15.238234 | AZ35: 14.803214 | BA35: 16.006557 | BB35: 17.35617 | BC35: 18.47457 | BD35: 18.884921
A36: Albania | B36: ALB | W36: .. | X36: .. | Y36: .. | Z36: .. | AA36: .. | AB36: .. | AC36: .. | AD36: .. | AE36: .. | AF36: .. | AG36: 1.7988043 | AH36: 2.4123358 | AI36: 8.2474614 | AJ36: 17.306625 | AK36: 23.455897 | AL36: 24.257164 | AM36: 30.591964 | AN36: 34.271068 | AO36: 38.499234 | AP36: 39.656148 | AQ36: 40.450767 | AR36: 40.912315 | AS36: 41.622903 | AT36: 42.188126 | AU36: 43.529438 | AV36: 43.63988 | AW36: 41.671209 | AX36: 42.577129 | AY36: 41.813078 | AZ36: 41.657305 | BA36: 45.765695 | BB36: 45.443754 | BC36: 46.942206 | BD36: 46.869696
A37: Algeria | B37: DZA | W37: .. | X37: .. | Y37: .. | Z37: .. | AA37: .. | AB37: .. | AC37: .. | AD37: .. | AE37: .. | AF37: .. | AG37: 3.2336118 | AH37: 4.8128447 | AI37: 5.7372802 | AJ37: 6.3674202 | AK37: 8.0475997 | AL37: 10.135931 | AM37: 12.345305 | AN37: 12.987507 | AO37: 12.44585 | AP37: 13.602758 | AQ37: 16.572222 | AR37: 15.87585 | AS37: 15.842043 | AT37: 16.825561 | AU37: 18.382388 | AV37: 20.683222 | AW37: 22.182694 | AX37: 22.991195 | AY37: 26.105282 | AZ37: 23.014379 | BA37: 26.404628 | BB37: 30.501793 | BC37: 31.664646 | BD37: 31.980599
A38: American Samoa | B38: ASM | W38: .. | X38: .. | Y38: .. | Z38: .. | AA38: .. | AB38: .. | AC38: .. | AD38: .. | AE38: .. | AF38: .. | AG38: .. | AH38: .. | AI38: .. | AJ38: .. | AK38: .. | AL38: .. | AM38: .. | AN38: .. | AO38: .. | AP38: .. | AQ38: .. | AR38: .. | AS38: .. | AT38: .. | AU38: .. | AV38: .. | AW38: .. | AX38: .. | AY38: .. | AZ38: .. | BA38: .. | BB38: .. | BC38: .. | BD38: ..
A39: Andorra | B39: AND | W39: .. | X39: .. | Y39: .. | Z39: .. | AA39: .. | AB39: .. | AC39: .. | AD39: .. | AE39: .. | AF39: .. | AG39: .. | AH39: .. | AI39: .. | AJ39: .. | AK39: .. | AL39: .. | AM39: .. | AN39: .. | AO39: .. | AP39: .. | AQ39: .. | AR39: .. | AS39: .. | AT39: .. | AU39: .. | AV39: .. | AW39: .. | AX39: .. | AY39: .. | AZ39: .. | BA39: .. | BB39: .. | BC39: .. | BD39: ..
A40: Angola | B40: AGO | W40: .. | X40: .. | Y40: .. | Z40: .. | AA40: .. | AB40: .. | AC40: .. | AD40: .. | AE40: .. | AF40: .. | AG40: 1.0837933e-08 | AH40: 2.7837902e-08 | AI40: 9.6006205e-08 | AJ40: 1.269033e-06 | AK40: 2.7642547e-05 | AL40: 0.0005402562 | AM40: 0.029178625 | AN40: 0.055745988 | AO40: 0.074624209 | AP40: 0.48333314 | AQ40: 2.449142 | AR40: 4.9399502 | AS40: 11.797023 | AT40: 21.38377 | AU40: 29.095427 | AV40: 35.751065 | AW40: 39.208118 | AX40: 43.013263 | AY40: 50.492601 | AZ40: 46.389583 | BA40: 56.09897 | BB40: 68.314856 | BC40: 71.859474 | BD40: 72.56522
A41: Antigua and Barbuda | B41: ATG | W41: .. | X41: .. | Y41: .. | Z41: .. | AA41: .. | AB41: .. | AC41: .. | AD41: .. | AE41: .. | AF41: .. | AG41: 1.5369695 | AH41: 1.5278671 | AI41: 1.5295101 | AJ41: 1.5271837 | AK41: 1.540523 | AL41: 1.5562308 | AM41: 1.5676727 | AN41: 1.5748205 | AO41: 1.5955615 | AP41: 1.5883478 | AQ41: 1.7856402 | AR41: 1.7804028 | AS41: 1.7658553 | AT41: 1.7103663 | AU41: 1.6911888 | AV41: 1.7094522 | AW41: 1.6640102 | AX41: 1.6813676 | AY41: 1.7225052 | AZ41: 1.7396261 | BA41: 1.7431225 | BB41: 1.7314541 | BC41: 1.7451194 | BD41: 1.7594041
A42: Argentina | B42: ARG | W42: .. | X42: .. | Y42: .. | Z42: .. | AA42: .. | AB42: .. | AC42: .. | AD42: .. | AE42: .. | AF42: .. | AG42: .. | AH42: .. | AI42: .. | AJ42: .. | AK42: .. | AL42: .. | AM42: .. | AN42: .. | AO42: .. | AP42: .. | AQ42: .. | AR42: .. | AS42: .. | AT42: .. | AU42: .. | AV42: .. | AW42: .. | AX42: .. | AY42: .. | AZ42: .. | BA42: .. | BB42: 2.664829 | BC42: .. | BD42: ..
A43: Armenia | B43: ARM | W43: .. | X43: .. | Y43: .. | Z43: .. | AA43: .. | AB43: .. | AC43: .. | AD43: .. | AE43: .. | AF43: .. | AG43: 0.0058657194 | AH43: 0.010183567 | AI43: 0.066589906 | AJ43: 0.96988509 | AK43: 39.955378 | AL43: 102.2168 | AM43: 120.05033 | AN43: 138.96482 | AO43: 152.18117 | AP43: 150.11916 | AQ43: 144.76759 | AR43: 147.28392 | AS43: 148.49243 | AT43: 152.22331 | AU43: 157.51017 | AV43: 157.55968 | AW43: 159.92249 | AX43: 162.38221 | AY43: 168.81051 | AZ43: 171.80453 | BA43: 182.93714 | BB43: 187.09528 | BC43: 181.64508 | BD43: 184.64631
A44: Aruba | B44: ABW | W44: .. | X44: .. | Y44: .. | Z44: .. | AA44: .. | AB44: .. | AC44: .. | AD44: .. | AE44: .. | AF44: .. | AG44: .. | AH44: .. | AI44: .. | AJ44: .. | AK44: .. | AL44: .. | AM44: .. | AN44: .. | AO44: .. | AP44: .. | AQ44: .. | AR44: .. | AS44: .. | AT44: .. | AU44: .. | AV44: .. | AW44: .. | AX44: .. | AY44: .. | AZ44: .. | BA44: .. | BB44: 1.2601191 | BC44: .. | BD44: ..
A45: Australia | B45: AUS | W45: .. | X45: .. | Y45: .. | Z45: .. | AA45: .. | AB45: .. | AC45: .. | AD45: .. | AE45: .. | AF45: .. | AG45: 1.3614025 | AH45: 1.3479778 | AI45: 1.3240093 | AJ45: 1.3071771 | AK45: 1.3014185 | AL45: 1.3038751 | AM45: 1.3092755 | AN45: 1.3128848 | AO45: 1.2956094 | AP45: 1.29695 | AQ45: 1.3105296 | AR45: 1.3242612 | AS45: 1.3364899 | AT45: 1.3516922 | AU45: 1.3670628 | AV45: 1.3883558 | AW45: 1.4068288 | AX45: 1.4268731 | AY45: 1.4790727 | AZ45: 1.4424146 | BA45: 1.506132 | BB45: 1.5110517 | BC45: 1.5274044 | BD45: 1.5100601
A46: Austria | B46: AUT | W46: .. | X46: .. | Y46: .. | Z46: .. | AA46: .. | AB46: .. | AC46: .. | AD46: .. | AE46: .. | AF46: .. | AG46: 0.91762794 | AH46: 0.92043197 | AI46: 0.93121891 | AJ46: 0.93465065 | AK46: 0.93827612 | AL46: 0.93577548 | AM46: 0.93075825 | AN46: 0.92450095 | AO46: 0.91743376 | AP46: 0.91708873 | AQ46: 0.8991954 | AR46: 0.91650459 | AS46: 0.89570046 | AT46: 0.88439945 | AU46: 0.87481986 | AV46: 0.88640438 | AW46: 0.85557948 | AX46: 0.86820305 | AY46: 0.85249366 | AZ46: 0.84100654 | BA46: 0.84139983 | BB46: 0.8300201 | BC46: 0.84196132 | BD46: 0.8368289
A47: Azerbaijan | B47: AZE | W47: .. | X47: .. | Y47: .. | Z47: .. | AA47: .. | AB47: .. | AC47: .. | AD47: .. | AE47: .. | AF47: .. | AG47: 7.4269878e-06 | AH47: 1.3193371e-05 | AI47: 0.00015031831 | AJ47: 0.0012444334 | AK47: 0.018097101 | AL47: 0.11446441 | AM47: 0.14211161 | AN47: 0.15263156 | AO47: 0.14953817 | AP47: 0.15061868 | AQ47: 0.16567162 | AR47: 0.16603423 | AS47: 0.16862223 | AT47: 0.17525188 | AU47: 0.18475969 | AV47: 0.20791033 | AW47: 0.22450552 | AX47: 0.26458874 | AY47: 0.33156665 | AZ47: 0.26674885 | BA47: 0.29981513 | BB47: 0.36039382 | BC47: 0.35930663 | BD47: 0.35756148
A48: Bahamas, The | B48: BHS | W48: .. | X48: .. | Y48: .. | Z48: .. | AA48: .. | AB48: .. | AC48: .. | AD48: .. | AE48: .. | AF48: .. | AG48: 0.7908879 | AH48: 0.7849972 | AI48: 0.79747007 | AJ48: 0.77229669 | AK48: 0.7727094 | AL48: 0.76299391 | AM48: 0.75668388 | AN48: 1.0020154 | AO48: 1.0214893 | AP48: 1.0569679 | AQ48: 1.0430119 | AR48: 1.0232558 | AS48: 1.0476858 | AT48: 1.0390189 | AU48: 1.0233768 | AV48: 1.0417152 | AW48: 1.0190145 | AX48: 1.0219294 | AY48: 1.0172726 | AZ48: 0.99903866 | BA48: 0.98589068 | BB48: 0.94924949 | BC48: 0.94832127 | BD48: ..
A49: Bahrain | B49: BHR | W49: .. | X49: .. | Y49: .. | Z49: .. | AA49: .. | AB49: .. | AC49: .. | AD49: .. | AE49: .. | AF49: .. | AG49: 0.13985843 | AH49: 0.13280818 | AI49: 0.12526007 | AJ49: 0.11864639 | AK49: 0.12469019 | AL49: 0.12347449 | AM49: 0.12149839 | AN49: 0.12056755 | AO49: 0.11085609 | AP49: 0.11219857 | AQ49: 0.14260823 | AR49: 0.13472436 | AS49: 0.13741521 | AT49: 0.1461002 | AU49: 0.15783165 | AV49: 0.17393116 | AW49: 0.18366468 | AX49: 0.19400926 | AY49: 0.21193532 | AZ49: 0.18297812 | BA49: 0.19423792 | BB49: 0.21074717 | BC49: 0.20940584 | BD49: 0.21117017
A50: Bangladesh | B50: BGD | W50: .. | X50: .. | Y50: .. | Z50: .. | AA50: .. | AB50: .. | AC50: .. | AD50: .. | AE50: .. | AF50: .. | AG50: 13.510994 | AH50: 13.938594 | AI50: 14.033436 | AJ50: 13.746568 | AK50: 13.967722 | AL50: 14.687321 | AM50: 15.034669 | AN50: 15.23853 | AO50: 15.870114 | AP50: 16.375127 | AQ50: 16.309073 | AR50: 16.196552 | AS50: 16.461143 | AT50: 16.869328 | AU50: 17.115484 | AV50: 17.425153 | AW50: 17.779871 | AX50: 18.495641 | AY50: 19.735708 | AZ50: 20.862092 | BA50: 21.946964 | BB50: 23.145432 | BC50: 24.676771 | BD50: 25.918767
A51: Barbados | B51: BRB | W51: .. | X51: .. | Y51: .. | Z51: .. | AA51: .. | AB51: .. | AC51: .. | AD51: .. | AE51: .. | AF51: .. | AG51: 1.8599517 | AH51: 1.8392176 | AI51: 1.8290984 | AJ51: 1.865988 | AK51: 1.8475098 | AL51: 1.8749237 | AM51: 1.9279605 | AN51: 1.8831122 | AO51: 2.0175487 | AP51: 2.0316683 | AQ51: 1.999853 | AR51: 2.0016241 | AS51: 1.9935508 | AT51: 1.9787376 | AU51: 2.037164 | AV51: 2.1044682 | AW51: 2.1412089 | AX51: 2.1463028 | AY51: 2.1111347 | AZ51: 2.2100717 | BA51: 2.1027345 | BB51: 2.0167963 | BC51: 1.9166101 | BD51: ..
A52: Belarus | B52: BLR | W52: .. | X52: .. | Y52: .. | Z52: .. | AA52: .. | AB52: .. | AC52: .. | AD52: .. | AE52: .. | AF52: .. | AG52: 8.1231883e-05 | AH52: 0.00016006252 | AI52: 0.0018374582 | AJ52: 0.020701491 | AK52: 0.41454292 | AL52: 3.092212 | AM52: 4.6679405 | AN52: 7.8777098 | AO52: 13.761216 | AP52: 56.548254 | AQ52: 157.74272 | AR52: 276.85952 | AS52: 395.0811 | AT52: 506.19722 | AU52: 604.40978 | AV52: 696.47202 | AW52: 748.34221 | AX52: 822.47866 | AY52: 977.42536 | AZ52: 1025.4636 | BA52: 1125.3753 | BB52: 1889.3077 | BC52: 3257.6221 | BD52: 3818.8428
A53: Belgium | B53: BEL | W53: .. | X53: .. | Y53: .. | Z53: .. | AA53: .. | AB53: .. | AC53: .. | AD53: .. | AE53: .. | AF53: .. | AG53: 0.90116415 | AH53: 0.89724373 | AI53: 0.90728021 | AJ53: 0.92157836 | AK53: 0.92126718 | AL53: 0.91345904 | AM53: 0.91308522 | AN53: 0.91212618 | AO53: 0.92446498 | AP53: 0.92126835 | AQ53: 0.8899211 | AR53: 0.88481963 | AS53: 0.8652244 | AT53: 0.87833049 | AU53: 0.89693743 | AV53: 0.89960007 | AW53: 0.88206438 | AX53: 0.88758002 | AY53: 0.87350448 | AZ53: 0.85501322 | BA53: 0.85405767 | BB53: 0.83896208 | BC53: 0.84936981 | BD53: 0.84743032
A54: Belize | B54: BLZ | W54: .. | X54: .. | Y54: .. | Z54: .. | AA54: .. | AB54: .. | AC54: .. | AD54: .. | AE54: .. | AF54: .. | AG54: 1.3217262 | AH54: 1.2464229 | AI54: 1.2672989 | AJ54: 1.258284 | AK54: 1.2762636 | AL54: 1.3261834 | AM54: 1.3280374 | AN54: 1.2864121 | AO54: 1.2917359 | AP54: 1.2450811 | AQ54: 1.222739 | AR54: 1.1931253 | AS54: 1.1958526 | AT54: 1.1386906 | AU54: 1.1312668 | AV54: 1.1211842 | AW54: 1.1352179 | AX54: 1.1583807 | AY54: 1.1606882 | AZ54: 1.1224516 | BA54: 1.1157725 | BB54: 1.1498015 | BC54: 1.1473219 | BD54: 1.145325
A55: Benin | B55: BEN | W55: .. | X55: .. | Y55: .. | Z55: .. | AA55: .. | AB55: .. | AC55: .. | AD55: .. | AE55: .. | AF55: .. | AG55: 121.12521 | AH55: 118.11307 | AI55: 118.97305 | AJ55: 118.97134 | AK55: 157.29858 | AL55: 177.3503 | AM55: 186.19973 | AN55: 189.78154 | AO55: 197.56703 | AP55: 195.63523 | AQ55: 199.94658 | AR55: 200.66769 | AS55: 202.16035 | AT55: 201.57119 | AU55: 196.93371 | AV55: 199.25501 | AW55: 199.41395 | AX55: 199.15722 | AY55: 209.37708 | AZ55: 211.8422 | BA55: 213.2105 | BB55: 214.03456 | BC55: 223.28095 | BD55: 221.97043
A56: Bermuda | B56: BMU | W56: .. | X56: .. | Y56: .. | Z56: .. | AA56: .. | AB56: .. | AC56: .. | AD56: .. | AE56: .. | AF56: .. | AG56: 1.0218354 | AH56: 1.0525367 | AI56: 1.0580263 | AJ56: 1.0871331 | AK56: 1.0853317 | AL56: 1.1075779 | AM56: 1.4071159 | AN56: 1.4391142 | AO56: 1.4627015 | AP56: 1.4812186 | AQ56: 1.3869544 | AR56: 1.3373244 | AS56: 1.4300972 | AT56: 1.4416833 | AU56: 1.4690588 | AV56: 1.5196606 | AW56: 1.5536152 | AX56: 1.6022352 | AY56: 1.6043073 | AZ56: 1.5973656 | BA56: 1.5948158 | BB56: 1.5635887 | BC56: 1.5928915 | BD56: ..
A57: Bhutan | B57: BTN | W57: .. | X57: .. | Y57: .. | Z57: .. | AA57: .. | AB57: .. | AC57: .. | AD57: .. | AE57: .. | AF57: .. | AG57: 6.4535333 | AH57: 6.7931803 | AI57: 7.2591854 | AJ57: 7.6709042 | AK57: 8.476325 | AL57: 8.9713429 | AM57: 9.5202126 | AN57: 10.528707 | AO57: 11.510376 | AP57: 12.19209 | AQ57: 12.193759 | AR57: 12.548419 | AS57: 12.961758 | AT57: 13.099852 | AU57: 13.233693 | AV57: 13.573556 | AW57: 13.881318 | AX57: 13.943086 | AY57: 14.449039 | AZ57: 15.034282 | BA57: 15.743589 | BB57: 16.855757 | BC57: 18.330501 | BD57: 19.089266
A58: Bolivia | B58: BOL | W58: .. | X58: .. | Y58: .. | Z58: .. | AA58: .. | AB58: .. | AC58: .. | AD58: .. | AE58: .. | AF58: .. | AG58: 0.93828706 | AH58: 1.0687178 | AI58: 1.182807 | AJ58: 1.2310687 | AK58: 1.3012646 | AL58: 1.4203357 | AM58: 1.5563884 | AN58: 1.6175061 | AO58: 1.7129769 | AP58: 1.7295859 | AQ58: 1.7790217 | AR58: 1.7716992 | AS58: 1.7941055 | AT58: 1.8702965 | AU58: 1.965439 | AV58: 2.0174927 | AW58: 2.2247644 | AX58: 2.3270471 | AY58: 2.5194059 | AZ58: 2.4396613 | BA58: 2.6220635 | BB58: 2.9461307 | BC58: 3.0957218 | BD58: 3.2327577
A59: Bosnia and Herzegovina | B59: BIH | W59: .. | X59: .. | Y59: .. | Z59: .. | AA59: .. | AB59: .. | AC59: .. | AD59: .. | AE59: .. | AF59: .. | AG59: .. | AH59: .. | AI59: .. | AJ59: .. | AK59: 0.55191181 | AL59: 0.58846646 | AM59: 0.47933869 | AN59: 0.53259527 | AO59: 0.51854506 | AP59: 0.55396163 | AQ59: 0.69759707 | AR59: 0.70217198 | AS59: 0.72239922 | AT59: 0.71470766 | AU59: 0.71353387 | AV59: 0.71816758 | AW59: 0.71214641 | AX59: 0.7320879 | AY59: 0.75510779 | AZ59: 0.74030058 | BA59: 0.73954538 | BB59: 0.7244703 | BC59: 0.72671608 | BD59: 0.71198992
A60: Botswana | B60: BWA | W60: .. | X60: .. | Y60: .. | Z60: .. | AA60: .. | AB60: .. | AC60: .. | AD60: .. | AE60: .. | AF60: .. | AG60: 0.97658946 | AH60: 0.99408968 | AI60: 1.0364545 | AJ60: 1.1446245 | AK60: 1.2268328 | AL60: 1.2877539 | AM60: 1.4684207 | AN60: 1.5199698 | AO60: 1.6489633 | AP60: 1.8571739 | AQ60: 2.073245 | AR60: 2.1952932 | AS60: 2.1877416 | AT60: 2.214782 | AU60: 2.3729569 | AV60: 2.6549395 | AW60: 2.778615 | AX60: 2.8295633 | AY60: 3.0177679 | AZ60: 3.097403 | BA60: 3.6394253 | BB60: 3.7640211 | BC60: 3.7583359 | BD60: 3.9209524
A61: Brazil | B61: BRA | W61: .. | X61: .. | Y61: .. | Z61: .. | AA61: .. | AB61: .. | AC61: .. | AD61: .. | AE61: .. | AF61: .. | AG61: 1.1917955e-05 | AH61: 5.931352e-05 | AI61: 0.00061945154 | AJ61: 0.012714261 | AK61: 0.29276933 | AL61: 0.55499591 | AM61: 0.63816332 | AN61: 0.67539518 | AO61: 0.69644949 | AP61: 0.74484636 | AQ61: 0.77329099 | AR61: 0.82375243 | AS61: 0.89692356 | AT61: 1.0000546 | AU61: 1.0515945 | AV61: 1.0924082 | AW61: 1.1250224 | AX61: 1.1602091 | AY61: 1.2328288 | AZ61: 1.3113164 | BA61: 1.4022448 | BB61: 1.4710749 | BC61: 1.5170667 | BD61: 1.608399
A62: Brunei Darussalam | B62: BRN | W62: .. | X62: .. | Y62: .. | Z62: .. | AA62: .. | AB62: .. | AC62: .. | AD62: .. | AE62: .. | AF62: .. | AG62: 0.4974554 | AH62: 0.46778214 | AI62: 0.46525046 | AJ62: 0.4410232 | AK62: 0.39398644 | AL62: 0.39702377 | AM62: 0.40740454 | AN62: 0.43493801 | AO62: 0.38015022 | AP62: 0.41825162 | AQ62: 0.52762162 | AR62: 0.48696066 | AS62: 0.48138571 | AT62: 0.50076521 | AU62: 0.56483417 | AV62: 0.64998517 | AW62: 0.69396063 | AX62: 0.68359431 | AY62: 0.75560057 | AZ62: 0.58418135 | BA62: 0.60783635 | BB62: 0.71744772 | BC62: 0.70477759 | BD62: 0.67237599
A63: Bulgaria | B63: BGR | W63: .. | X63: .. | Y63: .. | Z63: .. | AA63: .. | AB63: .. | AC63: .. | AD63: .. | AE63: .. | AF63: .. | AG63: 0.00096440016 | AH63: 0.0030477592 | AI63: 0.0047551357 | AJ63: 0.0070175807 | AK63: 0.011867085 | AL63: 0.018875631 | AM63: 0.040742271 | AN63: 0.41863459 | AO63: 0.50911972 | AP63: 0.52266092 | AQ63: 0.53808051 | AR63: 0.55833912 | AS63: 0.55648812 | AT63: 0.55724928 | AU63: 0.57726208 | AV63: 0.5990714 | AW63: 0.60660852 | AX63: 0.63704038 | AY63: 0.65321323 | AZ63: 0.65532724 | BA63: 0.66174885 | BB63: 0.66025157 | BC63: 0.67529656 | BD63: 0.67451324
A64: Burkina Faso | B64: BFA | W64: .. | X64: .. | Y64: .. | Z64: .. | AA64: .. | AB64: .. | AC64: .. | AD64: .. | AE64: .. | AF64: .. | AG64: 177.16663 | AH64: 164.66023 | AI64: 161.35454 | AJ64: 155.3315 | AK64: 174.35869 | AL64: 182.35804 | AM64: 179.71176 | AN64: 179.43831 | AO64: 191.6078 | AP64: 197.2909 | AQ64: 189.69636 | AR64: 192.98808 | AS64: 195.87774 | AT64: 194.89132 | AU64: 189.86338 | AV64: 190.84205 | AW64: 183.92898 | AX64: 183.22059 | AY64: 196.17492 | AZ64: 199.30282 | BA64: 211.09459 | BB64: 213.65917 | BC64: 214.00602 | BD64: 206.78929
A65: Burundi | B65: BDI | W65: .. | X65: .. | Y65: .. | Z65: .. | AA65: .. | AB65: .. | AC65: .. | AD65: .. | AE65: .. | AF65: .. | AG65: 50.824324 | AH65: 51.201602 | AI65: 52.764143 | AJ65: 55.528031 | AK65: 57.979958 | AL65: 65.940784 | AM65: 74.117626 | AN65: 96.479376 | AO65: 106.37291 | AP65: 120.55835 | AQ65: 163.78806 | AR65: 182.08216 | AS65: 181.16977 | AT65: 198.83829 | AU65: 218.97527 | AV65: 252.17892 | AW65: 251.61865 | AX65: 262.03106 | AY65: 318.66963 | AZ65: 342.31668 | BA65: 379.83513 | BB65: 425.7683 | BC65: 482.96329 | BD65: 539.76059
A66: Cambodia | B66: KHM | W66: .. | X66: .. | Y66: .. | Z66: .. | AA66: .. | AB66: .. | AC66: .. | AD66: .. | AE66: .. | AF66: .. | AG66: 58.57341 | AH66: 59.404616 | AI66: 55.689653 | AJ66: 81.241396 | AK66: 56.34188 | AL66: 54.336865 | AM66: 53.070849 | AN66: 51.742264 | AO66: 51.015025 | AP66: 54.125353 | AQ66: 48.741348 | AR66: 50.106132 | AS66: 49.168593 | AT66: 50.577495 | AU66: 46.110651 | AV66: 43.87575 | AW66: 44.5422 | AX66: 47.187962 | AY66: 47.925009 | AZ66: 48.593171 | BA66: 48.254444 | BB66: 48.591679 | BC66: 48.066497 | BD66: 48.998549
A67: Cameroon | B67: CMR | W67: .. | X67: .. | Y67: .. | Z67: .. | AA67: .. | AB67: .. | AC67: .. | AD67: .. | AE67: .. | AF67: .. | AG67: .. | AH67: .. | AI67: .. | AJ67: 960.80232 | AK67: 899.24712 | AL67: 982.30908 | AM67: 998.51932 | AN67: 1024.781 | AO67: 1115.3008 | AP67: 1121.3854 | AQ67: 1061.3445 | AR67: 1064.9936 | AS67: 1056.3875 | AT67: 1054.3072 | AU67: 1075.6774 | AV67: 1105.5825 | AW67: 1122.27 | AX67: 1164.5283 | AY67: 1282.18 | AZ67: 1304.2521 | BA67: 1328.867 | BB67: 1347.1147 | BC67: 1343.0399 | BD67: 1333.9654
A68: Canada | B68: CAN | W68: .. | X68: .. | Y68: .. | Z68: .. | AA68: .. | AB68: .. | AC68: .. | AD68: .. | AE68: .. | AF68: .. | AG68: 162.06025 | AH68: 162.44072 | AI68: 156.78979 | AJ68: 177.79958 | AK68: 199.13361 | AL68: 213.5651 | AM68: 215.38145 | AN68: 219.67333 | AO68: 225.2746 | AP68: 226.43052 | AQ68: 227.68776 | AR68: 227.43706 | AS68: 231.27011 | AT68: 227.55094 | AU68: 224.81951 | AV68: 223.5644 | AW68: 225.44564 | AX68: 222.76027 | AY68: 228.85829 | AZ68: 219.52806 | BA68: 223.4096 | BB68: 227.21166 | BC68: 239.91184 | BD68: 239.72598
